src/mul_core.sv
/*

iverilog -DTEST_BENCH_MUL_CORE -DNO_ES_FIELD -DN=8 -DES=0  -o mul_core.out ../src/mul_core.sv && ./mul_core.out

iverilog -DTEST_BENCH_MUL_CORE               -DN=16 -DES=1 -o mul_core.out ../src/mul_core.sv && ./mul_core.out

yosys -p "synth_intel -family max10 -top mul_core -vqm mul_core.vqm" \
    ../src/mul_core.sv > yosys_mul_core.out

TODO: get rid of unnecessary flags
*/
module mul_core #(
        parameter N = 8,
        parameter S = $clog2(N),
        parameter ES = 0
    )(
        input           p1_is_zero,
        input           p1_is_inf,
        input           p1_sign,
        input           p1_reg_s,
        input  [S:0]    p1_reg_len,
        input  [S:0]    p1_k,
`ifndef NO_ES_FIELD
        input  [ES-1:0] p1_exp,
`endif
        input  [N-1:0]  p1_mant,

        input           p2_is_zero,
        input           p2_is_inf,
        input           p2_sign,
        input           p2_reg_s,
        input  [S:0]    p2_reg_len,
        input  [S:0]    p2_k,
`ifndef NO_ES_FIELD        
        input  [ES-1:0] p2_exp,
`endif
        input  [N-1:0]  p2_mant,

        output          pout_is_zero,
        output          pout_is_inf,
        output          pout_sign,
        output          pout_reg_s,
        output [S:0]    pout_reg_len,
        output [S:0]    pout_k,
`ifndef NO_ES_FIELD
        output [ES-1:0] pout_exp,
`endif
        output [N-1:0]  pout_mant
    );

    function [N-1:0] min(
            input [N-1:0] a, b
        );
        min = a <= b ? a : b;
    endfunction

    function [N-1:0] max(
            input [N-1:0] a, b
        );
        max = a >= b ? a : b;
    endfunction

    parameter MSB = 1 << (N - 1);

    assign pout_is_zero = p1_is_zero || p2_is_zero;
    assign pout_is_inf = (!p1_is_zero && p2_is_inf) || (p1_is_inf && !p2_is_zero);      // ...missing something?

    wire [S:0] k, k_adjusted_I, k_adjusted_II, k_adjusted_III;
    assign k = p1_k + p2_k;

`ifndef NO_ES_FIELD
    wire [ES-1:0] exp, exp_adjusted_I, exp_adjusted_II, exp_adjusted_III;                          // fix size later

    assign exp = p1_exp + p2_exp;
`endif

    
    wire [S-1:0] F1, F2; // mantissae field size
    assign F1 = N - 1 - p1_reg_len - ES;
    assign F2 = N - 1 - p2_reg_len - ES;
    
    wire [N-1:0] f1, f2; // mantissae fields, left aligned (N bits)
    assign f1 = MSB | p1_mant << (N - 1 - F1);
    assign f2 = MSB | p2_mant << (N - 1 - F2);



    wire [2*N-1:0] prod_mantissae, prod_mantissae_adjusted;
    assign prod_mantissae = f1 * f2;

    wire mant_carry;
    assign mant_carry = prod_mantissae[2*N-1];

    wire exp_carry, exp_carry_I;

`ifndef NO_ES_FIELD
    assign exp_carry = exp[ES];
`else
    assign exp_carry = 0;
`endif

    assign k_adjusted_I = exp_carry == 1 ? k + 1 : k;

    assign exp_adjusted_I = exp_carry == 1 ? 
`ifndef NO_ES_FIELD
    exp & {ES{1'b1}} 
`else
    exp
`endif 
    : exp;

    assign exp_adjusted_II = mant_carry == 1 ? exp_adjusted_I + 1 : exp_adjusted_I;
    
    assign exp_carry_I = 
`ifndef NO_ES_FIELD
    exp_adjusted_II[ES];
`else
    0;
`endif

    assign k_adjusted_II = exp_carry_I == 1 ? k_adjusted_I + 1 : k_adjusted_I;
    assign exp_adjusted_III = exp_carry_I == 1 ? 
`ifndef NO_ES_FIELD
    exp_adjusted_II & {ES{1'b1}} 
`else
    exp_adjusted_II
`endif
    : exp_adjusted_II;

    assign prod_mantissae_adjusted = mant_carry == 1 ? prod_mantissae >> 1 : prod_mantissae;


    // adjust k based of whether it (over|under)flows or not.
    assign k_adjusted_III = k_adjusted_II >= 0 ? min(k_adjusted_II,  (N - 2)) : 
                                                 max(k_adjusted_II, -(N - 2)) ;

    
    wire [S:0] reg_len;
    assign reg_len = k_adjusted_III >= 0 ? k_adjusted_III + 2 : -k_adjusted_III + 1; // not bound checked

    wire [N-1:0] mant_len;
    assign mant_len = N - 1 - ES - reg_len;

    wire [(2*N)-1:0] mant_fraction_only;
    assign mant_fraction_only = prod_mantissae_adjusted & {2*N-2{1'b1}};
    
    wire [N-1:0] final_mant;
    assign final_mant = mant_fraction_only >> (2*N - mant_len - 2);

    assign pout_sign = p1_sign ^ p2_sign;
    assign pout_reg_s = 0; /* dontcare */
    assign pout_regime_bits = 0; /* dontcare */
    assign pout_reg_len = 0; /* dontcare */
    assign pout_k = k_adjusted_III;
`ifndef NO_ES_FIELD
    assign pout_exp = exp_adjusted_III;
`endif
    assign pout_mant = final_mant;

endmodule





`ifdef TEST_BENCH_MUL_CORE
module tb_mul_core;


`ifdef N
    parameter N = `N;
`else
    parameter N = 8;
`endif

    parameter S = $clog2(N);

`ifdef ES
    parameter ES = `ES;
`else
    parameter ES = 0;
`endif  

    reg            p1_is_zero;
    reg            p1_is_inf;
    reg            p1_sign;
    reg            p1_reg_s;
    reg   [S:0]    p1_reg_len;
    reg   [S:0]    p1_k;
`ifndef NO_ES_FIELD        
    reg   [ES-1:0] p1_exp;
`endif
    reg   [N-1:0]  p1_mant;

    reg            p2_is_zero;
    reg            p2_is_inf;
    reg            p2_sign;
    reg            p2_reg_s;
    reg   [N-1:0]  p2_regime_bits;
    reg   [S:0]    p2_reg_len;
    reg   [S:0]    p2_k;
`ifndef NO_ES_FIELD    
    reg   [ES-1:0] p2_exp;
`endif
    reg   [N-1:0]  p2_mant;

    wire           pout_is_zero;
    wire           pout_is_inf;
    wire           pout_sign;
    wire           pout_reg_s;
    wire  [S:0]    pout_reg_len;
    wire  [S:0]    pout_k;
`ifndef NO_ES_FIELD    
    wire  [ES-1:0] pout_exp;
`endif
    wire  [N-1:0]  pout_mant;

    reg            pout_is_zero_expected;
    reg            pout_is_inf_expected;
    reg            pout_sign_expected;
    reg            pout_reg_s_expected;
    reg   [S:0]    pout_reg_len_expected;
    reg   [S:0]    pout_k_expected;
`ifndef NO_ES_FIELD    
    reg   [ES-1:0] pout_exp_expected;
`endif
    reg   [N-1:0]  pout_mant_expected;

    reg [N:0] test_no;

    reg [N-1:0] p1_hex, p2_hex, pout_hex;

    reg diff_pout_is_zero;
    reg diff_pout_is_inf;
    reg diff_pout_sign;
    reg diff_pout_reg_s;
    reg diff_pout_reg_len;
    reg diff_pout_k;
`ifndef NO_ES_FIELD
    reg diff_pout_exp;
`endif
    reg diff_pout_mant;


    mul_core #(
        .N                  (N),
        .S                  (S),
        .ES                 (ES)
    ) mul_core_inst (
        /************ inputs ************/
        .p1_is_zero         (p1_is_zero),   
        .p1_is_inf          (p1_is_inf), 
        .p1_sign            (p1_sign), 
        .p1_reg_s           (p1_reg_s),
        .p1_reg_len         (p1_reg_len),
        .p1_k               (p1_k),
`ifndef NO_ES_FIELD    
        .p1_exp             (p1_exp),
`endif
        .p1_mant            (p1_mant),
    

        .p2_is_zero         (p2_is_zero), 
        .p2_is_inf          (p2_is_inf),   
        .p2_sign            (p2_sign),   
        .p2_reg_s           (p2_reg_s),
        .p2_reg_len         (p2_reg_len),
        .p2_k               (p2_k),
`ifndef NO_ES_FIELD    
        .p2_exp             (p2_exp),
`endif
        .p2_mant            (p2_mant),
        
        /************ outputs ************/
        .pout_is_zero       (pout_is_zero),
        .pout_is_inf        (pout_is_inf),
        .pout_sign          (pout_sign),
        .pout_reg_s         (pout_reg_s),
        .pout_reg_len       (pout_reg_len),
        .pout_k             (pout_k),
`ifndef NO_ES_FIELD
        .pout_exp           (pout_exp),
`endif
        .pout_mant          (pout_mant)
    );


    always @(*) begin
        diff_pout_is_zero = pout_is_zero === pout_is_zero_expected ? 0 : 1'bx;
        diff_pout_is_inf = pout_is_inf === pout_is_inf_expected ? 0 : 1'bx;
        diff_pout_sign = pout_sign === pout_sign_expected ? 0 : 1'bx;
        diff_pout_reg_s = pout_reg_s === pout_reg_s_expected ? 0 : 1'bx;
        diff_pout_reg_len = pout_reg_len === pout_reg_len_expected ? 0 : 1'bx;
        diff_pout_k = pout_k === pout_k_expected ? 0 : 1'bx;
`ifndef NO_ES_FIELD
        diff_pout_exp = pout_exp === pout_exp_expected ? 0 : 1'bx;
`endif
        diff_pout_mant = pout_mant === pout_mant_expected ? 0 : 1'bx;
        
    end


    initial begin
        
             if (N == 8 && ES == 0) $dumpfile("tb_mul_core_P8E0.vcd");
        else if (N == 5 && ES == 1) $dumpfile("tb_mul_core_P5E1.vcd");
        else if (N == 16 && ES == 1)$dumpfile("tb_mul_core_P16E1.vcd");
        else                        $dumpfile("tb_mul_core.vcd");

        $dumpvars(0, tb_mul_core);                        
            
        if (N == 8 && ES == 0) begin
            `include "../src/tb_posit_mul_core_P8E0.sv"
        end

        if (N == 16 && ES == 1) begin
            `include "../src/tb_posit_mul_core_P16E1.sv"
        end

        #10;
    end

endmodule
`endif

waveforms/tb_mul_core_P16E1.vcd
$date
	Tue Dec 21 13:58:05 2021
$end
$version
	Icarus Verilog
$end
$timescale
	1s
$end
$scope module tb_mul_core $end
$var wire 5 ! pout_reg_len [4:0] $end
$var wire 1 " pout_reg_s $end
$var wire 1 # pout_sign $end
$var wire 16 $ pout_mant [15:0] $end
$var wire 5 % pout_k [4:0] $end
$var wire 1 & pout_is_zero $end
$var wire 1 ' pout_is_inf $end
$var wire 1 ( pout_exp $end
$var reg 1 ) diff_pout_exp $end
$var reg 1 * diff_pout_is_inf $end
$var reg 1 + diff_pout_is_zero $end
$var reg 1 , diff_pout_k $end
$var reg 1 - diff_pout_mant $end
$var reg 1 . diff_pout_reg_len $end
$var reg 1 / diff_pout_reg_s $end
$var reg 1 0 diff_pout_sign $end
$var reg 1 1 p1_exp $end
$var reg 16 2 p1_hex [15:0] $end
$var reg 1 3 p1_is_inf $end
$var reg 1 4 p1_is_zero $end
$var reg 5 5 p1_k [4:0] $end
$var reg 16 6 p1_mant [15:0] $end
$var reg 5 7 p1_reg_len [4:0] $end
$var reg 1 8 p1_reg_s $end
$var reg 1 9 p1_sign $end
$var reg 1 : p2_exp $end
$var reg 16 ; p2_hex [15:0] $end
$var reg 1 < p2_is_inf $end
$var reg 1 = p2_is_zero $end
$var reg 5 > p2_k [4:0] $end
$var reg 16 ? p2_mant [15:0] $end
$var reg 5 @ p2_reg_len [4:0] $end
$var reg 1 A p2_reg_s $end
$var reg 1 B p2_sign $end
$var reg 1 C pout_exp_expected $end
$var reg 16 D pout_hex [15:0] $end
$var reg 1 E pout_is_inf_expected $end
$var reg 1 F pout_is_zero_expected $end
$var reg 5 G pout_k_expected [4:0] $end
$var reg 16 H pout_mant_expected [15:0] $end
$var reg 5 I pout_reg_len_expected [4:0] $end
$var reg 1 J pout_reg_s_expected $end
$var reg 1 K pout_sign_expected $end
$var reg 17 L test_no [16:0] $end
$scope module mul_core_inst $end
$var wire 1 M exp_carry $end
$var wire 1 N exp_carry_I $end
$var wire 32 O mant_fraction_only [31:0] $end
$var wire 1 1 p1_exp $end
$var wire 1 3 p1_is_inf $end
$var wire 1 4 p1_is_zero $end
$var wire 5 P p1_k [4:0] $end
$var wire 16 Q p1_mant [15:0] $end
$var wire 5 R p1_reg_len [4:0] $end
$var wire 1 8 p1_reg_s $end
$var wire 1 9 p1_sign $end
$var wire 1 : p2_exp $end
$var wire 1 < p2_is_inf $end
$var wire 1 = p2_is_zero $end
$var wire 5 S p2_k [4:0] $end
$var wire 16 T p2_mant [15:0] $end
$var wire 5 U p2_reg_len [4:0] $end
$var wire 1 A p2_reg_s $end
$var wire 1 B p2_sign $end
$var wire 1 ( pout_exp $end
$var wire 1 ' pout_is_inf $end
$var wire 1 & pout_is_zero $end
$var wire 5 V pout_k [4:0] $end
$var wire 16 W pout_mant [15:0] $end
$var wire 5 X pout_reg_len [4:0] $end
$var wire 1 " pout_reg_s $end
$var wire 1 Y pout_regime_bits $end
$var wire 1 # pout_sign $end
$var wire 5 Z reg_len [4:0] $end
$var wire 32 [ prod_mantissae_adjusted [31:0] $end
$var wire 32 \ prod_mantissae [31:0] $end
$var wire 16 ] mant_len [15:0] $end
$var wire 1 ^ mant_carry $end
$var wire 5 _ k_adjusted_III [4:0] $end
$var wire 5 ` k_adjusted_II [4:0] $end
$var wire 5 a k_adjusted_I [4:0] $end
$var wire 5 b k [4:0] $end
$var wire 16 c final_mant [15:0] $end
$var wire 16 d f2 [15:0] $end
$var wire 16 e f1 [15:0] $end
$var wire 1 f exp_adjusted_III $end
$var wire 1 g exp_adjusted_II $end
$var wire 1 h exp_adjusted_I $end
$var wire 1 i exp $end
$var wire 4 j F2 [3:0] $end
$var wire 4 k F1 [3:0] $end
$scope function max $end
$var reg 16 l a [15:0] $end
$var reg 16 m b [15:0] $end
$upscope $end
$scope function min $end
$var reg 16 n a [15:0] $end
$var reg 16 o b [15:0] $end
$upscope $end
$upscope $end
$upscope $end
$enddefinitions $end
#0
$dumpvars
b1110 o
b0xxxxx n
b1111111111110010 m
b0xxxxx l
b1100 k
b1100 j
0i
0h
1g
1f
b1110001101101000 e
b1011111010101000 d
bx c
b11111 b
bx a
bx `
bx _
1^
bx ]
b10101001010111000110110001000000 \
b1010100101011100011011000100000 [
bx Z
0Y
b0 X
bx W
bx V
b10 U
b11111010101 T
b0 S
b10 R
b110001101101 Q
b11111 P
b10100101011100011011000100000 O
xN
xM
b1 L
1K
1J
b10 I
b10100101100 H
b0 G
0F
0E
b1010101011010100 D
1C
1B
1A
b10 @
b11111010101 ?
b0 >
0=
0<
b1010100000101011 ;
1:
09
08
b10 7
b110001101101 6
b11111 5
04
03
b11110001101101 2
11
00
x/
x.
x-
x,
0+
0*
0)
1(
0'
0&
bx %
bx $
1#
0"
b0 !
$end
#10
b1110000010011100100000000000 O
b1001110000010011100100000000000 [
b1010100010000000 d
b10011100000100111001000000000000 \
b1110110100100000 e
b1001 j
0#
b0xxx a
b1110000 H
b11 G
b101 I
0K
b111101001110000 D
b10100010 ?
b10100010 T
0:
b11 >
b11 S
b101 @
b101 U
0B
b111100010100010 ;
b110110100100 6
b110110100100 Q
0i
01
b11 b
b0 5
b0 P
18
b100110110100100 2
b10 L
#20
0(
0f
0g
b100100100110101011101000000000 O
b1100100100110101011101000000000 [
0^
b1001101010100000 d
b1100100100110101011101000000000 \
b1010011010010000 e
0)
0/
b1100 j
1#
b111xx a
b1011 k
b10010010011 H
0C
b11110 G
b11 I
0J
1K
b1110101101101101 D
b1101010100 ?
b1101010100 T
1:
b11111 >
b11111 S
b10 @
b10 U
0A
1B
b1100110010101100 ;
b1001101001 6
b1001101001 Q
0i
11
b11101 b
b11110 5
b11110 P
b11 7
b11 R
08
b1101001101001 2
b11 L
#30
b101110000110011000101000000000 O
1(
1f
b1101110000110011000101000000000 [
1g
b1001011011000000 d
b1101110000110011000101000000000 \
b1011101011111000 e
0)
b1011 j
1h
b1111x a
b1100 k
0#
b10111000011 H
1C
0K
b1110111000011 D
b101101100 ?
b101101100 T
b11110 >
b11110 S
b11 @
b11 U
b1110011010010100 ;
b11101011111 6
b11101011111 Q
1i
01
b11110 b
b0 5
b0 P
b10 7
b10 R
18
19
b1011100010100001 2
b100 L
#40
0(
0f
0g
b11100001000111001011000000000 O
1^
b1011100001000111001011000000000 [
b1101110000110000 d
b10111000010001110010110000000000 \
b1101011001000000 e
0)
x/
b1100 j
b0xx a
b1011 k
1#
b111000010 H
0C
b10 G
b100 I
1J
1K
b1000111000111110 D
b101110000110 ?
b101110000110 T
b0 >
b0 S
b10 @
b10 U
1A
b1010010001111010 ;
b10101100100 6
b10101100100 Q
b1 b
b1 5
b1 P
b11 7
b11 R
09
b110010101100100 2
b101 L
#50
b10110001110111101010000000000 O
0)
b1010110001110111101010000000000 [
0(
0f
0^
0g
b1000010100110000 d
b1010110001110111101010000000000 \
b1010010111000000 e
0#
0h
b0xxx a
b1001 k
b1011001 H
b100 G
b110 I
0K
b111110001011001 D
b10100110 ?
b10100110 T
0B
b101000010100110 ;
b10010111 6
b10010111 Q
0i
11
b11 b
b11 5
b11 P
b101 7
b101 R
b111101010010111 2
b110 L
#60
1(
1f
1g
b11100111011100011110000000000 O
1^
b1011100111011100011110000000000 [
b1111101101000000 d
b10111001110111000111100000000000 \
b1011110101100000 e
0)
0/
1#
b1111x a
b1100 k
b1110011110 H
1C
b11110 G
b11 I
0J
1K
b1110010001100010 D
b111101101000 ?
b111101101000 T
0:
b11111 >
b11111 S
0A
1B
b1101000010011000 ;
b11110101100 6
b11110101100 Q
0i
01
b11110 b
b11111 5
b11111 P
b10 7
b10 R
08
b10011110101100 2
b111 L
#70
x(
xf
xg
b0xxxxxxxxxxxxxxxxxxxxxxxxxxxxxx O
bx [
x^
b1xxxxxxxxxxxxxxx d
bx \
b1111000100000000 e
x)
0,
x/
bx j
0#
1&
bx a
b1011 k
b0 H
0C
bx G
bx I
xJ
0K
1F
b0 D
b0 ?
b0 T
bx >
bx S
bx @
bx U
xA
0B
1=
b0 ;
b11100010000 6
b11100010000 Q
bx b
b11110 5
b11110 P
b11 7
b11 R
b1011100010000 2
b1000 L
#80
0)
0(
0f
0g
b100110000111110011000000000000 O
0^
b1100110000111110011000000000000 [
b1100110000111110011000000000000 \
b1011010100000000 d
b1001000001110000 e
x,
b0xx a
b1001 j
1#
0&
b10011000100 H
b1 G
b11 I
1J
1K
0F
b1001101100111100 D
b11010100 ?
b11010100 T
b1 b
b11 >
b11 S
b101 @
b101 U
1A
1B
0=
b1000011100101100 ;
b100000111 6
b100000111 Q
b1000100000111 2
b1001 L
#90
x)
x(
xf
b0xxxxxxxxxxxxxxxxxxxxxxxxxxxxxx O
xg
x^
bx [
b1011100011001000 d
bx \
b1xxxxxxxxxxxxxxx e
0,
1h
b1100 j
0#
bx a
bx k
1&
b0 H
bx G
bx I
xJ
0K
1F
b0 D
b11100011001 ?
b11100011001 T
1i
1:
b11111 >
b11111 S
b10 @
b10 U
0A
0B
b11011100011001 ;
b0 6
b0 Q
bx b
bx 5
bx P
bx 7
bx R
x8
14
b0 2
b1010 L
#100
0)
0(
0f
0g
b11010010001100001111000000000 O
b1011010010001100001111000000000 [
1^
b10110100100011000011110000000000 \
b1110110011100000 e
b1100001100100000 d
x,
1#
b0xx a
b1011 k
0&
b110100100 H
b10 G
b100 I
1J
1K
0F
b1000111001011100 D
b100001100100 ?
b100001100100 T
b0 >
b0 S
1A
1B
b1010011110011100 ;
b11011001110 6
b11011001110 Q
b1 b
b1 5
b1 P
b11 7
b11 R
18
04
b110011011001110 2
b1011 L
#110
b101010011010110010000000000 O
b1000101010011010110010000000000 [
b1001011011000000 d
b10001010100110101100100000000000 \
b1110101101100000 e
b1010 k
0#
b1010101 H
0K
b111000001010101 D
b1011011000 ?
b1011011000 T
b11111 >
b11111 S
0A
b1100110100101000 ;
b1101011011 6
b1101011011 Q
b1 b
b10 5
b10 P
b100 7
b100 R
19
b1000110010100101 2
b1100 L
#120
x)
x(
xf
xg
b0xxxxxxxxxxxxxxxxxxxxxxxxxxxxxx O
bx [
x^
b1000001100101000 d
bx \
b1xxxxxxxxxxxxxxx e
1'
0,
x0
0*
bx a
bx k
b0 H
bx G
bx I
xJ
1K
1E
b1000000000000000 D
b1100101 ?
b1100101 T
b0 >
b0 S
1A
b1010111110011011 ;
b0 6
b0 Q
bx b
bx 5
bx P
bx 7
bx R
x8
13
b1000000000000000 2
b1101 L
#130
0)
1(
1f
1g
b111011010101100001011100000000 O
0^
b1111011010101100001011100000000 [
b1111011010101100001011100000000 \
b1101000010100000 e
b1001011101011000 d
0'
x,
0/
00
0*
b1100 k
1#
b111011010110 H
1C
b11111 G
b10 I
0J
0E
b1100000100101010 D
b1011101011 ?
b1011101011 T
b11111 >
b11111 S
0A
b1100110100010101 ;
b101000010100 6
b101000010100 Q
b11111 b
b0 5
b0 P
b10 7
b10 R
18
09
03
b100101000010100 2
b1110 L
#140
b100010101100010000001010000000 O
b1100010101100010000001010000000 [
b1010010101111000 d
b1100010101100010000001010000000 \
b1001100010110000 e
b100010101100 H
b1100011101010100 D
b10010101111 ?
b10010101111 T
0:
b0 >
b0 S
1A
0B
b100010010101111 ;
b1100010110 6
b1100010110 Q
1i
11
b11111 b
b11111 5
b11111 P
08
19
b1100110011101010 2
b1111 L
#150
b0xxxxxxxxxxxxxxxxxxxxxxxxxxxxxx O
x(
xf
x^
bx [
xg
b1xxxxxxxxxxxxxxx d
1'
bx \
b1100011100000000 e
x)
0,
x/
x0
0*
bx j
0#
0h
b1000 k
b0 H
0C
bx G
bx I
xJ
1E
b1000000000000000 D
b0 ?
b0 T
bx >
bx S
bx @
bx U
xA
1B
1<
b1000000000000000 ;
b10001110 6
b10001110 Q
0i
01
bx b
b11011 5
b11011 P
b110 7
b110 R
b1111110101110010 2
b10000 L
#160
0)
0(
0f
0g
b10010101101110010111100000000 O
b1010010101101110010111100000000 [
1^
b10100101011011100101111000000000 \
b1011110001000000 d
0'
b1110000011111000 e
x,
0/
00
0*
b111xx a
b1011 j
1h
b1100 k
b1001010111 H
b11110 G
b11 I
0J
0K
0E
b1001001010111 D
b1111000100 ?
b1111000100 T
b11101 b
b11110 >
b11110 S
b11 @
b11 U
0A
0<
b1110110000111100 ;
b110000011111 6
b110000011111 Q
1i
11
b11111 5
b11111 P
b10 7
b10 R
b1100001111100001 2
b10001 L
#170
b10111100100000110000000000000 O
b1010111100100000110000000000000 [
b1100011001100000 d
b10101111001000001100000000000000 \
b1110001000000000 e
b1111x a
b1010 k
b10111100100 H
b11111 G
b10 I
b10010111100100 D
b10001100110 ?
b10001100110 T
b1 >
b1 S
1A
0B
b110010001100110 ;
b1100010000 6
b1100010000 Q
b11110 b
b11101 5
b11101 P
b100 7
b100 R
09
b111100010000 2
b10010 L
#180
b11001010001000101000000000000 O
b1011001010001000101000000000000 [
b1110011001000000 d
b10110010100010001010000000000000 \
b1100011010000000 e
b1010 j
1#
b1110x a
b1100 k
b110010100 H
b11101 G
b100 I
1K
b1111011001101100 D
b1100110010 ?
b1100110010 T
b11101 >
b11101 S
b100 @
b100 U
0A
1B
b1111010011001110 ;
b100011010000 6
b100011010000 Q
b11100 b
b11111 5
b11111 P
b10 7
b10 R
b11100011010000 2
b10011 L
#190
1(
1f
1g
b110100000100100000000000000000 O
b1110100000100100000000000000000 [
0^
b1010011000000000 d
b1110100000100100000000000000000 \
b1011001100000000 e
0)
x/
b110 j
b10xx a
b1001 k
b111 H
1C
b1001 G
b1011 I
1J
b1000000000010001 D
b10011 ?
b10011 T
b110 >
b110 S
b1000 @
b1000 U
1A
0B
b111111100010011 ;
b11001100 6
b11001100 Q
b1001 b
b11 5
b11 P
b101 7
b101 R
18
19
b1000010100110100 2
b10100 L
#200
0(
0f
0g
b1001000000010010001000000000 O
1^
b1001001000000010010001000000000 [
b1011000010100000 d
b10010010000000100100010000000000 \
b1101001110100000 e
0)
b1011 j
b0x a
b1010 k
b100100000 H
0C
b1 G
b11 I
b1001111011100000 D
b1100001010 ?
b1100001010 T
b11110 >
b11110 S
b11 @
b11 U
0A
b1001100001010 ;
b1010011101 6
b1010011101 Q
b0 b
b10 5
b10 P
b100 7
b100 R
b1000100101100011 2
b10101 L
#210
b111010000100110101101100000 O
b1000111010000100110101101100000 [
b1010000110011000 d
b10001110100001001101011011000000 \
b1110000111001000 e
b1100 j
bx a
b1100 k
b111010001 H
b0 G
b10 I
b1011111000101111 D
b10000110011 ?
b10000110011 T
b11111 >
b11111 S
b10 @
b10 U
1B
b1101101111001101 ;
b110000111001 6
b110000111001 Q
b11111 b
b0 5
b0 P
b10 7
b10 R
09
b101110000111001 2
b10110 L
#220
b1101101010110100110000000000 O
b1001101101010110100110000000000 [
b1101100111000000 d
b10011011010101101001100000000000 \
b1011011010100000 e
0/
b1110x a
b1001 j
b11011011 H
b11101 G
b100 I
0J
b1111011100100101 D
b101100111 ?
b101100111 T
1:
b11100 b
b11100 >
b11100 S
b101 @
b101 U
b1111100010011001 ;
b11011010100 6
b11011010100 Q
1i
01
b100011011010100 2
b10111 L
#230
b1000001111100100011100100000 O
b1001000001111100100011100100000 [
b1011110110011000 d
b10010000011111001000111001000000 \
b1100001100011000 e
x/
b1100 j
bx a
b1000010000 H
b0 G
b10 I
1J
b1011110111110000 D
b11110110011 ?
b11110110011 T
0:
b0 >
b0 S
b10 @
b10 U
1A
0B
b100011110110011 ;
b100001100011 6
b100001100011 Q
1i
11
b11111 b
b11111 5
b11111 P
08
19
b1100011110011101 2
b11000 L
#240
b10001100111111001111100000000 O
b1010001100111111001111100000000 [
1(
1f
1g
b1011100101000000 d
b10100011001111110011111000000000 \
b1110000110011000 e
0)
0/
b1110x a
b1010 j
0h
b10001101 H
1C
b11100 G
b101 I
0J
b1111100101110011 D
b111001010 ?
b111001010 T
b11100 b
b11101 >
b11101 S
b100 @
b100 U
0A
1B
b1111011000110110 ;
b110000110011 6
b110000110011 Q
0i
01
09
b10110000110011 2
b11001 L
#250
b101110101101011110101111100000 O
0(
0f
b1101110101101011110101111100000 [
0g
b1111101000101000 d
b11011101011010111101011111000000 \
b1110001010011000 e
0)
x/
1h
bx a
b1100 j
0#
b101110101101 H
0C
b0 G
b10 I
1J
0K
b100101110101101 D
b111101000101 ?
b111101000101 T
1i
1:
b11111 b
b0 >
b0 S
b10 @
b10 U
1A
b1010000010111011 ;
b110001010011 6
b110001010011 Q
19
b1101001110101101 2
b11010 L
#260
b110100110101110100000100000000 O
0)
b1110100110101110100000100000000 [
0(
0f
0^
0g
b1010011100111000 d
b1110100110101110100000100000000 \
b1011001011100000 e
0/
0h
b1111x a
b1011 k
1#
b110100110110 H
b11111 G
0J
1K
b1101001011001010 D
b10011100111 ?
b10011100111 T
b1010101100011001 ;
b1100101110 6
b1100101110 Q
0i
11
b11110 b
b11110 5
b11110 P
b11 7
b11 R
09
b1101100101110 2
b11011 L
#270
b10000100100001000000000000000 O
1(
1f
b1010000100100001000000000000000 [
1g
b1000011110110000 d
b1010000100100001000000000000000 \
b1001100000000000 e
0)
0#
1h
bx a
b1100 k
b10000100100 H
1C
0K
b11010000100100 D
b11110110 ?
b11110110 T
b11111 >
b11111 S
0A
0B
b11000011110110 ;
b1100000000 6
b1100000000 Q
1i
01
b11111 b
b0 5
b0 P
b10 7
b10 R
18
b100001100000000 2
b11100 L
#280
0(
0f
0g
b10100101100010111011100000000 O
1^
b1010100101100010111011100000000 [
b1110110011100000 d
b10101001011000101110111000000000 \
b1011011100010000 e
0)
b1010 j
b1110x a
b101001011 H
0C
b11101 G
b100 I
b100101001011 D
b1101100111 ?
b1101100111 T
0:
b11101 >
b11101 S
b100 @
b100 U
b101101100111 ;
b11011100010 6
b11011100010 Q
1i
11
b11100 b
b11111 5
b11111 P
08
b11011011100010 2
b11101 L
#290
b10110010011110100101100000000 O
b1010110010011110100101100000000 [
b1101000100010000 d
b10101100100111101001011000000000 \
b1101001101100000 e
b1011 j
b1111x a
b1010 k
1#
b10110010100 H
b11111 G
b10 I
1K
b1101101001101100 D
b10100010001 ?
b10100010001 T
b1 >
b1 S
b11 @
b11 U
1A
b110010100010001 ;
b1010011011 6
b1010011011 Q
b11110 b
b11101 5
b11101 P
b100 7
b100 R
19
b1111000101100101 2
b11110 L
#300
1(
1f
1g
b101000010000101011111000000000 O
b1101000010000101011111000000000 [
0^
b1001110111100000 d
b1101000010000101011111000000000 \
b1010100100010000 e
0)
0#
b1110x a
b1011 k
b101000010 H
1C
b11100 G
b101 I
0K
b11101000010 D
b111011110 ?
b111011110 T
1:
b11110 >
b11110 S
0A
1B
b1110011000100010 ;
b1010010001 6
b1010010001 Q
1i
01
b11100 b
b11110 5
b11110 P
b11 7
b11 R
b1110110101101111 2
b11111 L
#310
b100000010101011000000000000000 O
b1100000010101011000000000000000 [
b1001011001100000 d
b1100000010101011000000000000000 \
b1010010000000000 e
b111xx a
b1001 k
1#
b1000000101 H
b11101 G
b100 I
1K
b1111000111111011 D
b101100110 ?
b101100110 T
0:
b1 >
b1 S
1A
b1001111010011010 ;
b10010000 6
b10010000 Q
1i
11
b11101 b
b11100 5
b11100 P
b101 7
b101 R
09
b11010010000 2
b100000 L
#320
b110011110110110100010000000000 O
0(
0f
b1110011110110110100010000000000 [
0g
b1000010101100000 d
b1110011110110110100010000000000 \
b1101111001100000 e
0)
b1100 j
0h
b1111x a
b1100 k
b11001111011 H
0C
b11110 G
b11 I
b1110100110000101 D
b10101100 ?
b10101100 T
b11111 >
b11111 S
b10 @
b10 U
0A
0B
b10000010101100 ;
b101111001100 6
b101111001100 Q
0i
01
b11110 b
b11111 5
b11111 P
b10 7
b10 R
19
b1101010000110100 2
b100001 L
#330
1(
1f
1g
b100000111000010010011100000000 O
1^
b1100000111000010010011100000000 [
b1101110110010000 d
b11000001110000100100111000000000 \
b1101111111100000 e
0)
x/
0#
bx a
b100000111000 H
1C
b0 G
b10 I
1J
0K
b101100000111000 D
b101110110010 ?
b101110110010 T
1:
1B
b1100010001001110 ;
b101111111100 6
b101111111100 Q
0i
11
b11111 b
b0 5
b0 P
18
b1010010000000100 2
b100010 L
#340
0)
b111000001101000000000000000 O
1(
1f
b1000111000001101000000000000000 [
1g
0^
b1000000111100000 d
b1000111000001101000000000000000 \
b1000110000000000 e
0/
1h
b1010 j
b1110x a
b111000 H
b11100 G
b101 I
0J
b11000111000 D
b1111 ?
b1111 T
1i
0:
b11101 >
b11101 S
b100 @
b100 U
b1111011111110001 ;
b110000000 6
b110000000 Q
b11100 b
b11111 5
b11111 P
08
b1100111010000000 2
b100011 L
