src/mul_core.sv
/*

iverilog -DTEST_BENCH_MUL_CORE -DNO_ES_FIELD -DN=8 -DES=0  -o mul_core.out ../src/mul_core.sv && ./mul_core.out

iverilog -DTEST_BENCH_MUL_CORE               -DN=16 -DES=1 -o mul_core.out ../src/mul_core.sv && ./mul_core.out

yosys -p "synth_intel -family max10 -top mul_core -vqm mul_core.vqm" \
    ../src/mul_core.sv > yosys_mul_core.out

TODO: get rid of unnecessary flags
*/
module mul_core #(
        parameter N = 8,
        parameter S = $clog2(N),
        parameter ES = 0
    )(
        input           p1_is_zero,
        input           p1_is_inf,
        input           p1_sign,
        input           p1_reg_s,
        input  [N-1:0]  p1_regime_bits,
        input  [S-1:0]  p1_reg_len,
        input  [N-1:0]  p1_k,
`ifndef NO_ES_FIELD
        input  [ES-1:0] p1_exp,
`endif
        input  [N-1:0]  p1_mant,

        input           p2_is_zero,
        input           p2_is_inf,
        input           p2_sign,
        input           p2_reg_s,
        input  [N-1:0]  p2_regime_bits,
        input  [S-1:0]  p2_reg_len,
        input  [N-1:0]  p2_k,
`ifndef NO_ES_FIELD        
        input  [ES-1:0] p2_exp,
`endif
        input  [N-1:0]  p2_mant,

        output          pout_is_zero,
        output          pout_is_inf,
        output          pout_sign,
        output          pout_reg_s,
        output [N-1:0]  pout_regime_bits,
        output [S-1:0]  pout_reg_len,
        output [N-1:0]  pout_k,
`ifndef NO_ES_FIELD
        output [ES-1:0] pout_exp,
`endif
        output [N-1:0]  pout_mant
    );

    function [N-1:0] min(
            input [N-1:0] a, b
        );
        min = a <= b ? a : b;
    endfunction

    function [N-1:0] max(
            input [N-1:0] a, b
        );
        max = a >= b ? a : b;
    endfunction

    parameter MSB = 1 << (N - 1);

    assign pout_is_zero = p1_is_zero || p2_is_zero;
    assign pout_is_inf = (!p1_is_zero && p2_is_inf) || (p1_is_inf && !p2_is_zero);      // ...missing something?

    wire [N-1:0] k, k_adjusted_I, k_adjusted_II, k_adjusted_III;
    assign k = p1_k + p2_k;

    wire [N-1:0] exp, exp_adjusted_I, exp_adjusted_II, exp_adjusted_III;                          // fix size later

`ifndef NO_ES_FIELD
    assign exp = p1_exp + p2_exp;
`else
    assign exp = 0;
`endif

    
    wire [S-1:0] F1, F2; // mantissae field size
    assign F1 = N - 1 - p1_reg_len - ES;
    assign F2 = N - 1 - p2_reg_len - ES;
    
    wire [N-1:0] f1, f2; // mantissae fields, left aligned (N bits)
    assign f1 = MSB | p1_mant << (N - 1 - F1);
    assign f2 = MSB | p2_mant << (N - 1 - F2);



    wire [2*N-1:0] prod_mantissae, prod_mantissae_adjusted;
    assign prod_mantissae = f1 * f2;

    wire mant_carry;
    assign mant_carry = prod_mantissae[2*N-1];

    wire exp_carry, exp_carry_I;

`ifndef NO_ES_FIELD
    assign exp_carry = exp[ES];
`else
    assign exp_carry = 0;
`endif

    assign k_adjusted_I = exp_carry == 1 ? k + 1 : k;

    assign exp_adjusted_I = exp_carry == 1 ? 
`ifndef NO_ES_FIELD
    exp & {ES{1'b1}} 
`else
    exp
`endif 
    : exp;

    assign exp_adjusted_II = mant_carry == 1 ? exp_adjusted_I + 1 : exp_adjusted_I;
    
    assign exp_carry_I = 
`ifndef NO_ES_FIELD
    exp_adjusted_II[ES];
`else
    0;
`endif

    assign k_adjusted_II = exp_carry_I == 1 ? k_adjusted_I + 1 : k_adjusted_I;
    assign exp_adjusted_III = exp_carry_I == 1 ? 
`ifndef NO_ES_FIELD
    exp_adjusted_II & {ES{1'b1}} 
`else
    exp_adjusted_II
`endif
    : exp_adjusted_II;

    assign prod_mantissae_adjusted = mant_carry == 1 ? prod_mantissae >> 1 : prod_mantissae;


    // adjust k based of whether it (over|under)flows or not.
    assign k_adjusted_III = k_adjusted_II >= 0 ? min(k_adjusted_II,  (N - 2)) : 
                                                 max(k_adjusted_II, -(N - 2)) ;

    
    wire [S-1:0] reg_len;
    assign reg_len = k_adjusted_III >= 0 ? k_adjusted_III + 2 : -k_adjusted_III + 1; // not bound checked

    wire [N-1:0] mant_len;
    assign mant_len = N - 1 - ES - reg_len;

    wire [(2*N)-1:0] mant_fraction_only;
    assign mant_fraction_only = prod_mantissae_adjusted & {2*N-2{1'b1}};
    
    wire [N-1:0] final_mant;
    assign final_mant = mant_fraction_only >> (2*N - mant_len - 2);

    assign pout_sign = p1_sign ^ p2_sign;
    assign pout_reg_s = 0; /* dontcare */
    assign pout_regime_bits = 0; /* dontcare */
    assign pout_reg_len = 0; /* dontcare */
    assign pout_k = k_adjusted_III;
`ifndef NO_ES_FIELD
    assign pout_exp = exp_adjusted_III;
`endif
    assign pout_mant = final_mant;

endmodule





`ifdef TEST_BENCH_MUL_CORE
module tb_mul_core;


`ifdef N
    parameter N = `N;
`else
    parameter N = 8;
`endif

    parameter S = $clog2(N);

`ifdef ES
    parameter ES = `ES;
`else
    parameter ES = 0;
`endif  

    reg            p1_is_zero;
    reg            p1_is_inf;
    reg            p1_sign;
    reg            p1_reg_s;
    reg   [N-1:0]  p1_regime_bits;
    reg   [S-1:0]  p1_reg_len;
    reg   [N-1:0]  p1_k;
`ifndef NO_ES_FIELD        
    reg   [ES-1:0] p1_exp;
`endif
    reg   [N-1:0]  p1_mant;

    reg            p2_is_zero;
    reg            p2_is_inf;
    reg            p2_sign;
    reg            p2_reg_s;
    reg   [N-1:0]  p2_regime_bits;
    reg   [S-1:0]  p2_reg_len;
    reg   [N-1:0]  p2_k;
`ifndef NO_ES_FIELD    
    reg   [ES-1:0] p2_exp;
`endif
    reg   [N-1:0]  p2_mant;

    wire           pout_is_zero;
    wire           pout_is_inf;
    wire           pout_sign;
    wire           pout_reg_s;
    wire  [N-1:0]  pout_regime_bits;
    wire  [S-1:0]  pout_reg_len;
    wire  [N-1:0]  pout_k;
`ifndef NO_ES_FIELD    
    wire  [ES-1:0] pout_exp;
`endif
    wire  [N-1:0]  pout_mant;

    reg            pout_is_zero_expected;
    reg            pout_is_inf_expected;
    reg            pout_sign_expected;
    reg            pout_reg_s_expected;
    reg   [N-1:0]  pout_regime_bits_expected;
    reg   [S-1:0]  pout_reg_len_expected;
    reg   [N-1:0]  pout_k_expected;
`ifndef NO_ES_FIELD    
    reg   [ES-1:0] pout_exp_expected;
`endif
    reg   [N-1:0]  pout_mant_expected;

    reg [N:0] test_no;

    reg [N-1:0] p1_hex, p2_hex, pout_hex;

    reg diff_pout_is_zero;
    reg diff_pout_is_inf;
    reg diff_pout_sign;
    reg diff_pout_reg_s;
    reg diff_pout_regime_bits;
    reg diff_pout_reg_len;
    reg diff_pout_k;
`ifndef NO_ES_FIELD
    reg diff_pout_exp;
`endif
    reg diff_pout_mant;


    mul_core #(
        .N                  (N),
        .S                  (S),
        .ES                 (ES)
    ) mul_core_inst (
        /************ inputs ************/
        .p1_is_zero         (p1_is_zero),   
        .p1_is_inf          (p1_is_inf), 
        .p1_sign            (p1_sign), 
        .p1_reg_s           (p1_reg_s),
        .p1_regime_bits     (p1_regime_bits),
        .p1_reg_len         (p1_reg_len),
        .p1_k               (p1_k),
`ifndef NO_ES_FIELD    
        .p1_exp             (p1_exp),
`endif
        .p1_mant            (p1_mant),
    

        .p2_is_zero         (p2_is_zero), 
        .p2_is_inf          (p2_is_inf),   
        .p2_sign            (p2_sign),   
        .p2_reg_s           (p2_reg_s),
        .p2_regime_bits     (p2_regime_bits),
        .p2_reg_len         (p2_reg_len),
        .p2_k               (p2_k),
`ifndef NO_ES_FIELD    
        .p2_exp             (p2_exp),
`endif
        .p2_mant            (p2_mant),
        
        /************ outputs ************/
        .pout_is_zero       (pout_is_zero),
        .pout_is_inf        (pout_is_inf),
        .pout_sign          (pout_sign),
        .pout_reg_s         (pout_reg_s),
        .pout_regime_bits   (pout_regime_bits),
        .pout_reg_len       (pout_reg_len),
        .pout_k             (pout_k),
`ifndef NO_ES_FIELD
        .pout_exp           (pout_exp),
`endif
        .pout_mant          (pout_mant)
    );


    always @(*) begin
        diff_pout_is_zero = pout_is_zero === pout_is_zero_expected ? 0 : 1'bx;
        diff_pout_is_inf = pout_is_inf === pout_is_inf_expected ? 0 : 1'bx;
        diff_pout_sign = pout_sign === pout_sign_expected ? 0 : 1'bx;
        diff_pout_reg_s = pout_reg_s === pout_reg_s_expected ? 0 : 1'bx;
        diff_pout_regime_bits = pout_regime_bits === pout_regime_bits_expected ? 0 : 1'bx;
        diff_pout_reg_len = pout_reg_len === pout_reg_len_expected ? 0 : 1'bx;
        diff_pout_k = pout_k === pout_k_expected ? 0 : 1'bx;
`ifndef NO_ES_FIELD
        diff_pout_exp = pout_exp === pout_exp_expected ? 0 : 1'bx;
`endif
        diff_pout_mant = pout_mant === pout_mant_expected ? 0 : 1'bx;
        
    end


    initial begin
        
             if (N == 8 && ES == 0) $dumpfile("tb_mul_core_P8E0.vcd");
        else if (N == 5 && ES == 1) $dumpfile("tb_mul_core_P5E1.vcd");
        else if (N == 16 && ES == 1)$dumpfile("tb_mul_core_P16E1.vcd");
        else                        $dumpfile("tb_mul_core.vcd");

        $dumpvars(0, tb_mul_core);                        
            
        if (N == 8 && ES == 0) begin
            `include "../src/tb_posit_mul_core_P8E0.sv"
        end

        if (N == 16 && ES == 1) begin
            `include "../src/tb_posit_mul_core_P16E1.sv"
        end

        #10;
    end

endmodule
`endif

waveforms/tb_mul_core_P16E1.vcd
$date
	Sun Dec 19 20:06:21 2021
$end
$version
	Icarus Verilog
$end
$timescale
	1s
$end
$scope module tb_mul_core $end
$var wire 4 ! pout_reg_len [3:0] $end
$var wire 1 " pout_reg_s $end
$var wire 16 # pout_regime_bits [15:0] $end
$var wire 1 $ pout_sign $end
$var wire 16 % pout_mant [15:0] $end
$var wire 16 & pout_k [15:0] $end
$var wire 1 ' pout_is_zero $end
$var wire 1 ( pout_is_inf $end
$var wire 1 ) pout_exp $end
$var reg 1 * diff_pout_exp $end
$var reg 1 + diff_pout_is_inf $end
$var reg 1 , diff_pout_is_zero $end
$var reg 1 - diff_pout_k $end
$var reg 1 . diff_pout_mant $end
$var reg 1 / diff_pout_reg_len $end
$var reg 1 0 diff_pout_reg_s $end
$var reg 1 1 diff_pout_regime_bits $end
$var reg 1 2 diff_pout_sign $end
$var reg 1 3 p1_exp $end
$var reg 16 4 p1_hex [15:0] $end
$var reg 1 5 p1_is_inf $end
$var reg 1 6 p1_is_zero $end
$var reg 16 7 p1_k [15:0] $end
$var reg 16 8 p1_mant [15:0] $end
$var reg 4 9 p1_reg_len [3:0] $end
$var reg 1 : p1_reg_s $end
$var reg 16 ; p1_regime_bits [15:0] $end
$var reg 1 < p1_sign $end
$var reg 1 = p2_exp $end
$var reg 16 > p2_hex [15:0] $end
$var reg 1 ? p2_is_inf $end
$var reg 1 @ p2_is_zero $end
$var reg 16 A p2_k [15:0] $end
$var reg 16 B p2_mant [15:0] $end
$var reg 4 C p2_reg_len [3:0] $end
$var reg 1 D p2_reg_s $end
$var reg 16 E p2_regime_bits [15:0] $end
$var reg 1 F p2_sign $end
$var reg 1 G pout_exp_expected $end
$var reg 16 H pout_hex [15:0] $end
$var reg 1 I pout_is_inf_expected $end
$var reg 1 J pout_is_zero_expected $end
$var reg 16 K pout_k_expected [15:0] $end
$var reg 16 L pout_mant_expected [15:0] $end
$var reg 4 M pout_reg_len_expected [3:0] $end
$var reg 1 N pout_reg_s_expected $end
$var reg 16 O pout_regime_bits_expected [15:0] $end
$var reg 1 P pout_sign_expected $end
$var reg 17 Q test_no [16:0] $end
$scope module mul_core_inst $end
$var wire 32 R mant_fraction_only [31:0] $end
$var wire 1 3 p1_exp $end
$var wire 1 5 p1_is_inf $end
$var wire 1 6 p1_is_zero $end
$var wire 16 S p1_k [15:0] $end
$var wire 16 T p1_mant [15:0] $end
$var wire 4 U p1_reg_len [3:0] $end
$var wire 1 : p1_reg_s $end
$var wire 16 V p1_regime_bits [15:0] $end
$var wire 1 < p1_sign $end
$var wire 1 = p2_exp $end
$var wire 1 ? p2_is_inf $end
$var wire 1 @ p2_is_zero $end
$var wire 16 W p2_k [15:0] $end
$var wire 16 X p2_mant [15:0] $end
$var wire 4 Y p2_reg_len [3:0] $end
$var wire 1 D p2_reg_s $end
$var wire 16 Z p2_regime_bits [15:0] $end
$var wire 1 F p2_sign $end
$var wire 1 ( pout_is_inf $end
$var wire 1 ' pout_is_zero $end
$var wire 16 [ pout_k [15:0] $end
$var wire 16 \ pout_mant [15:0] $end
$var wire 4 ] pout_reg_len [3:0] $end
$var wire 1 " pout_reg_s $end
$var wire 16 ^ pout_regime_bits [15:0] $end
$var wire 1 $ pout_sign $end
$var wire 4 _ reg_len [3:0] $end
$var wire 32 ` prod_mantissae_adjusted [31:0] $end
$var wire 32 a prod_mantissae [31:0] $end
$var wire 1 ) pout_exp $end
$var wire 16 b mant_len [15:0] $end
$var wire 1 c mant_carry $end
$var wire 16 d k_adjusted_III [15:0] $end
$var wire 16 e k_adjusted_II [15:0] $end
$var wire 16 f k_adjusted_I [15:0] $end
$var wire 16 g k [15:0] $end
$var wire 16 h final_mant [15:0] $end
$var wire 16 i f2 [15:0] $end
$var wire 16 j f1 [15:0] $end
$var wire 1 k exp_carry_I $end
$var wire 1 l exp_carry $end
$var wire 16 m exp_adjusted_III [15:0] $end
$var wire 16 n exp_adjusted_II [15:0] $end
$var wire 16 o exp_adjusted_I [15:0] $end
$var wire 16 p exp [15:0] $end
$var wire 4 q F2 [3:0] $end
$var wire 4 r F1 [3:0] $end
$scope function max $end
$var reg 16 s a [15:0] $end
$var reg 16 t b [15:0] $end
$upscope $end
$scope function min $end
$var reg 16 u a [15:0] $end
$var reg 16 v b [15:0] $end
$upscope $end
$upscope $end
$upscope $end
$enddefinitions $end
#0
$dumpvars
b1110 v
b0 u
b1111111111110010 t
b0 s
b1100 r
b1100 q
b10 p
b0 o
b1 n
b1 m
1l
0k
b1110001101101000 j
b1011111010101000 i
b10100101011 h
b1111111111111111 g
b0 f
b0 e
b0 d
1c
b1100 b
b10101001010111000110110001000000 a
b1010100101011100011011000100000 `
b10 _
b0 ^
b0 ]
b10100101011 \
b0 [
b10 Z
b10 Y
b11111010101 X
b0 W
b1 V
b10 U
b110001101101 T
b1111111111111111 S
b10100101011100011011000100000 R
b1 Q
1P
b10 O
1N
b10 M
b10100101100 L
b0 K
0J
0I
b1010101011010100 H
1G
1F
b10 E
1D
b10 C
b11111010101 B
b0 A
0@
0?
b1010100000101011 >
1=
0<
b1 ;
0:
b10 9
b110001101101 8
b1111111111111111 7
06
05
b11110001101101 4
13
02
x1
x0
x/
x.
0-
0,
0+
0*
1)
0(
0'
b0 &
b10100101011 %
1$
b0 #
0"
b0 !
$end
#10
0.
b1001 b
b1110000 %
b1110000 \
b1110000 h
b101 _
b1110000010011100100000000000 R
b1001110000010011100100000000000 `
b11 &
b11 [
b11 d
b11 u
b11 s
b1010100010000000 i
b10011100000100111001000000000000 a
b1110110100100000 j
b11 e
0-
b1001 q
0$
0l
b11 f
b1110000 L
b11110 O
b11 K
b101 M
0P
b111101001110000 H
b10100010 B
b10100010 X
0=
b11110 E
b11110 Z
b11 A
b11 W
b101 C
b101 Y
0F
b111100010100010 >
b110110100100 8
b110110100100 T
b0 p
03
b10 ;
b10 V
b11 g
b0 7
b0 S
1:
b100110110100100 4
b10 Q
#20
b1110 b
0)
b10010010011010 %
b10010010011010 \
b10010010011010 h
b0 _
b100100100110101011101000000000 R
b1100100100110101011101000000000 `
b1110 &
b1110 [
b1110 d
0c
0k
b0 m
b1111111111111110 u
b1111111111111110 s
b1001101010100000 i
b1100100100110101011101000000000 a
b1010011010010000 j
b0 n
b1111111111111110 e
x.
0*
x-
00
1l
b1100 q
1$
b0 o
b1111111111111110 f
b1011 r
b10010010011 L
0G
b1 O
b1111111111111110 K
b11 M
0N
1P
b1110101101101101 H
b1101010100 B
b1101010100 X
1=
b1 E
b1 Z
b1111111111111111 A
b1111111111111111 W
b10 C
b10 Y
0D
1F
b1100110010101100 >
b1001101001 8
b1001101001 T
b10 p
13
b1 ;
b1 V
b1111111111111101 g
b1111111111111110 7
b1111111111111110 S
b11 9
b11 U
0:
b1101001101001 4
b11 Q
#30
b10111000011001 %
b10111000011001 \
b10111000011001 h
1)
b101110000110011000101000000000 R
b1 m
b1101110000110011000101000000000 `
b1 n
b1111111111111110 u
b1111111111111110 s
b1001011011000000 i
b1101110000110011000101000000000 a
b1011101011111000 j
b1 o
b1111111111111110 e
0*
b1011 q
0l
b1111111111111110 f
b1100 r
0$
b10111000011 L
1G
0P
b1110111000011 H
b101101100 B
b101101100 X
b1111111111111110 A
b1111111111111110 W
b11 C
b11 Y
b1110011010010100 >
b11101011111 8
b11101011111 T
b1 p
03
b10 ;
b10 V
b1111111111111110 g
b0 7
b0 S
b10 9
b10 U
1:
1<
b1011100010100001 4
b100 Q
#40
0.
0-
b1010 b
0)
b100 _
1k
b0 m
b111000010 %
b111000010 \
b111000010 h
b10 n
b11100001000111001011000000000 R
b10 &
b10 [
b10 d
1c
b1011100001000111001011000000000 `
b10 u
b10 s
b1101110000110000 i
b10111000010001110010110000000000 a
b1101011001000000 j
b10 e
0*
x0
b1100 q
b1 f
b1011 r
1$
b111000010 L
0G
b1110 O
b10 K
b100 M
1N
1P
b1000111000111110 H
b101110000110 B
b101110000110 X
b10 E
b10 Z
b0 A
b0 W
b10 C
b10 Y
1D
b1010010001111010 >
b10101100100 8
b10101100100 T
b110 ;
b110 V
b1 g
b1 7
b1 S
b11 9
b11 U
0<
b110010101100100 4
b101 Q
#50
b1000 b
b1011000 %
b1011000 \
b1011000 h
0*
b110 _
b10110001110111101010000000000 R
0)
b1010110001110111101010000000000 `
0k
b0 m
b100 &
b100 [
b100 d
0c
b100 u
b100 s
b1000010100110000 i
b1010110001110111101010000000000 a
b1010010111000000 j
b0 n
b100 e
x.
0-
0$
1l
b0 o
b100 f
b1001 r
b1011001 L
b111110 O
b100 K
b110 M
0P
b111110001011001 H
b10100110 B
b10100110 X
0F
b101000010100110 >
b10010111 8
b10010111 T
b10 p
13
b11110 ;
b11110 V
b11 g
b11 7
b11 S
b101 9
b101 U
b111101010010111 4
b110 Q
#60
b1110 b
1)
b0 _
b1 m
b1110011101110 %
b1110011101110 \
b1110011101110 h
b1 n
b11100111011100011110000000000 R
b1110 &
b1110 [
b1110 d
1c
b1011100111011100011110000000000 `
b1111111111111110 u
b1111111111111110 s
b1111101101000000 i
b10111001110111000111100000000000 a
b1011110101100000 j
b1111111111111110 e
0*
x-
00
1$
0l
b1111111111111110 f
b1100 r
b1110011110 L
1G
b1 O
b1111111111111110 K
b11 M
0N
1P
b1110010001100010 H
b111101101000 B
b111101101000 X
0=
b1 E
b1 Z
b1111111111111111 A
b1111111111111111 W
0D
1F
b1101000010011000 >
b11110101100 8
b11110101100 T
b0 p
03
b1 ;
b1 V
b1111111111111110 g
b1111111111111111 7
b1111111111111111 S
b10 9
b10 U
0:
b10011110101100 4
b111 Q
#70
b1100 b
b10 _
0-
b0 &
b0 [
b0 d
b10110101110 %
b10110101110 \
b10110101110 h
b10110101110100010000000000000 R
0)
b1010110101110100010000000000000 `
1k
b0 m
b0 u
b0 s
b1011100001000000 i
b10 n
b10101101011101000100000000000000 a
b1111000100000000 j
b0 e
0*
x0
b1 o
b1011 q
0$
b1111111111111111 f
b1011 r
b10110101111 L
0G
b10 O
b0 K
b10 M
1N
0P
b100010110101111 H
b1110000100 B
b1110000100 X
b1 p
1=
b110 E
b110 Z
b1 A
b1 W
b11 C
b11 Y
1D
0F
b110101110000100 >
b11100010000 8
b11100010000 T
b1111111111111111 g
b1111111111111110 7
b1111111111111110 S
b11 9
b11 U
b1011100010000 4
b1000 Q
#80
b1011 b
b11 _
b10011000011 %
b10011000011 \
b10011000011 h
b100110000111110011000000000000 R
b1 &
b1 [
b1 d
b1100110000111110011000000000000 `
0k
b1 u
b1 s
0c
b1011010100000000 i
b0 n
b1 e
b1100110000111110011000000000000 a
b1001000001110000 j
0-
b0 o
b1 f
b1001 q
1$
b10011000100 L
b110 O
b1 K
b11 M
1P
b1001101100111100 H
b11010100 B
b11010100 X
b0 p
0=
b11110 E
b11110 Z
b1 g
b11 A
b11 W
b101 C
b101 Y
1F
b1000011100101100 >
b100000111 8
b100000111 T
b1000100000111 4
b1001 Q
#90
b1110 b
b0 _
1k
b11011101010 %
b11011101010 \
b11011101010 h
0*
0)
b110111010101100001000000000 R
b1110 &
b1110 [
b1110 d
b0 m
1c
b1000110111010101100001000000000 `
b1111111111111100 u
b1111111111111100 s
b1011100011001000 i
b10 n
b10001101110101011000010000000000 a
b1100010010000000 j
b1111111111111100 e
x-
00
b1 o
b1100 q
0$
b1111111111111011 f
b1001 r
b110111 L
b1 O
b1111111111111100 K
b101 M
0N
0P
b10000110111 H
b11100011001 B
b11100011001 X
b1 p
1=
b1 E
b1 Z
b1111111111111111 A
b1111111111111111 W
b10 C
b10 Y
0D
0F
b11011100011001 >
b100010010 8
b100010010 T
b1111111111111011 g
b1111111111111100 7
b1111111111111100 S
b101 9
b101 U
b10100010010 4
b1010 Q
#100
0.
b1010 b
b110100100 %
b110100100 \
b110100100 h
b100 _
b11010010001100001111000000000 R
0-
b1011010010001100001111000000000 `
b10 &
b10 [
b10 d
b10 u
b10 s
b1100001100100000 i
b10110100100011000011110000000000 a
b1110110011100000 j
b10 e
x0
1$
b1 f
b1011 r
b110100100 L
b1110 O
b10 K
b100 M
1N
1P
b1000111001011100 H
b100001100100 B
b100001100100 X
b10 E
b10 Z
b0 A
b0 W
1D
1F
b1010011110011100 >
b11011001110 8
b11011001110 T
b110 ;
b110 V
b1 g
b1 7
b1 S
b11 9
b11 U
1:
b110011011001110 4
b1011 Q
#110
b1010100 %
b1010100 \
b1010100 h
b101010011010110010000000000 R
b1000101010011010110010000000000 `
b1001011011000000 i
b10001010100110101100100000000000 a
b1110101101100000 j
x.
b1010 r
0$
b1010101 L
0P
b111000001010101 H
b1011011000 B
b1011011000 X
b1 E
b1 Z
b1111111111111111 A
b1111111111111111 W
0D
b1100110100101000 >
b1101011011 8
b1101011011 T
b1110 ;
b1110 V
b1 g
b10 7
b10 S
b100 9
b100 U
1<
b1000110010100101 4
b1100 Q
#120
1)
b1110 b
b1 m
b10101010011000 %
b10101010011000 \
b10101010011000 h
b0 _
0k
b101010100110001011001010000000 R
b1 n
b1101010100110001011001010000000 `
b1110 &
b1110 [
b1110 d
0c
b1111111111111110 u
b1111111111111110 s
b1000001100101000 i
b1101010100110001011001010000000 a
b1101000000010000 j
b1111111111111110 e
0*
x-
00
b1111111111111110 f
b1011 r
b10101010011 L
1G
b1 O
b1111111111111110 K
b11 M
0N
b1110101010011 H
b1100101 B
b1100101 X
b10 E
b10 Z
b0 A
b0 W
1D
b1010111110011011 >
b10100000001 8
b10100000001 T
b1 ;
b1 V
b1111111111111110 g
b1111111111111110 7
b1111111111111110 S
b11 9
b11 U
0:
b1110101011111111 4
b1101 Q
#130
b11101101010110 %
b11101101010110 \
b11101101010110 h
b111011010101100001011100000000 R
b1111011010101100001011100000000 `
b1111111111111111 u
b1111111111111111 s
b1001011101011000 i
b1111011010101100001011100000000 a
b1101000010100000 j
b1111111111111111 e
b1111111111111111 f
b1100 r
1$
b111011010110 L
b1111111111111111 K
b10 M
1P
b1100000100101010 H
b1011101011 B
b1011101011 X
b1 E
b1 Z
b1111111111111111 A
b1111111111111111 W
0D
b1100110100010101 >
b101000010100 8
b101000010100 T
b10 ;
b10 V
b1111111111111111 g
b0 7
b0 S
b10 9
b10 U
1:
0<
b100101000010100 4
b1110 Q
#140
b10001010110001 %
b10001010110001 \
b10001010110001 h
b100010101100010000001010000000 R
b1100010101100010000001010000000 `
b1010010101111000 i
b1100010101100010000001010000000 a
b1001100010110000 j
b100010101100 L
b1100011101010100 H
b10010101111 B
b10010101111 X
0=
b10 E
b10 Z
b0 A
b0 W
1D
0F
b100010010101111 >
b1100010110 8
b1100010110 T
b1 p
13
b1 ;
b1 V
b1111111111111111 g
b1111111111111111 7
b1111111111111111 S
0:
1<
b1100110011101010 4
b1111 Q
#150
0)
1k
b0 m
b11001110101 %
b11001110101 \
b11001110101 h
b10 n
b110011101010111110000000000 R
1c
b1000110011101010111110000000000 `
b1111111111111100 u
b1111111111111100 s
b1011010101001000 i
b10001100111010101111100000000000 a
b1100011100000000 j
b1111111111111100 e
0*
b1111111111111011 f
b1000 r
b110100 L
0G
b1111111111111100 K
b101 M
b1111101111001100 H
b11010101001 B
b11010101001 X
1=
b101011010101001 >
b10001110 8
b10001110 T
b1 p
03
b1111111111111011 g
b1111111111111011 7
b1111111111111011 S
b110 9
b110 U
b1111110101110010 4
b10000 Q
#160
b1001010110111 %
b1001010110111 \
b1001010110111 h
b10010101101110010111100000000 R
b1010010101101110010111100000000 `
b1111111111111110 u
b1111111111111110 s
b1011110001000000 i
b10100101011011100101111000000000 a
b1110000011111000 j
b1111111111111110 e
b1011 q
0$
b1111111111111101 f
b1100 r
b1001010111 L
b1111111111111110 K
b11 M
0P
b1001001010111 H
b1111000100 B
b1111000100 X
0=
b1 E
b1 Z
b1111111111111110 A
b1111111111111110 W
b11 C
b11 Y
0D
1F
b1110110000111100 >
b110000011111 8
b110000011111 T
b1 p
13
b1111111111111101 g
b1111111111111111 7
b1111111111111111 S
b10 9
b10 U
b1100001111100001 4
b10001 Q
#170
b1011110010000 %
b1011110010000 \
b1011110010000 h
b10111100100000110000000000000 R
b1010111100100000110000000000000 `
b1111111111111111 u
b1111111111111111 s
b1100011001100000 i
b10101111001000001100000000000000 a
b1110001000000000 j
b1111111111111111 e
b1111111111111110 f
b1010 r
b10111100100 L
b1111111111111111 K
b10 M
b10010111100100 H
b10001100110 B
b10001100110 X
b110 E
b110 Z
b1 A
b1 W
1D
0F
b110010001100110 >
b1100010000 8
b1100010000 T
b1111111111111110 g
b1111111111111101 7
b1111111111111101 S
b100 9
b100 U
0<
b111100010000 4
b10010 Q
#180
b1100101000100 %
b1100101000100 \
b1100101000100 h
b11001010001000101000000000000 R
b1011001010001000101000000000000 `
b1111111111111101 u
b1111111111111101 s
b1110011001000000 i
b10110010100010001010000000000000 a
b1100011010000000 j
b1111111111111101 e
b1010 q
1$
b1111111111111100 f
b1100 r
b110010100 L
b1111111111111101 K
b100 M
1P
b1111011001101100 H
b1100110010 B
b1100110010 X
b1 E
b1 Z
b1111111111111101 A
b1111111111111101 W
b100 C
b100 Y
0D
1F
b1111010011001110 >
b100011010000 8
b100011010000 T
b1111111111111100 g
b1111111111111111 7
b1111111111111111 S
b10 9
b10 U
b11100011010000 4
b10011 Q
#190
0-
1)
b11 b
b1 m
b110 %
b110 \
b110 h
b1011 _
0k
b110100000100100000000000000000 R
b1 n
b1110100000100100000000000000000 `
b1001 &
b1001 [
b1001 d
0c
b1001 u
b1001 s
b1010011000000000 i
b1110100000100100000000000000000 a
b1011001100000000 j
b1001 e
0*
x0
b110 q
b1001 f
b1001 r
b111 L
1G
b11111111110 O
b1001 K
b1011 M
1N
b1000000000010001 H
b10011 B
b10011 X
b11111110 E
b11111110 Z
b110 A
b110 W
b1000 C
b1000 Y
1D
0F
b111111100010011 >
b11001100 8
b11001100 T
b11110 ;
b11110 V
b1001 g
b11 7
b11 S
b101 9
b101 U
1:
1<
b1000010100110100 4
b10100 Q
#200
0.
b1011 b
0)
b11 _
1k
b0 m
b100100000 %
b100100000 \
b100100000 h
b10 n
b1001000000010010001000000000 R
b1 &
b1 [
b1 d
1c
b1001001000000010010001000000000 `
b1 u
b1 s
b1011000010100000 i
b10010010000000100100010000000000 a
b1101001110100000 j
b1 e
0*
0-
b1011 q
b0 f
b1010 r
b100100000 L
0G
b110 O
b1 K
b11 M
b1001111011100000 H
b1100001010 B
b1100001010 X
b1 E
b1 Z
b1111111111111110 A
b1111111111111110 W
b11 C
b11 Y
0D
b1001100001010 >
b1010011101 8
b1010011101 T
b1110 ;
b1110 V
b0 g
b10 7
b10 S
b100 9
b100 U
b1000100101100011 4
b10101 Q
#210
b1100 b
b111010000 %
b111010000 \
b111010000 h
b10 _
b111010000100110101101100000 R
b1000111010000100110101101100000 `
b0 &
b0 [
b0 d
b0 u
b0 s
b1010000110011000 i
b10001110100001001101011011000000 a
b1110000111001000 j
b0 e
x.
0-
b1100 q
b1111111111111111 f
b1100 r
b111010001 L
b10 O
b0 K
b10 M
b1011111000101111 H
b10000110011 B
b10000110011 X
b1111111111111111 A
b1111111111111111 W
b10 C
b10 Y
1F
b1101101111001101 >
b110000111001 8
b110000111001 T
b10 ;
b10 V
b1111111111111111 g
b0 7
b0 S
b10 9
b10 U
0<
b101110000111001 4
b10110 Q
#220
b1110 b
b0 _
b110110101011 %
b110110101011 \
b110110101011 h
b1101101010110100110000000000 R
b1110 &
b1110 [
b1110 d
b1001101101010110100110000000000 `
b1111111111111101 u
b1111111111111101 s
b1101100111000000 i
b1111111111111101 e
b10011011010101101001100000000000 a
b1011011010100000 j
x-
00
b1111111111111100 f
b1001 q
b11011011 L
b1 O
b1111111111111101 K
b100 M
0N
b1111011100100101 H
b101100111 B
b101100111 X
1=
b1111111111111100 g
b1111111111111100 A
b1111111111111100 W
b101 C
b101 Y
b1111100010011001 >
b11011010100 8
b11011010100 T
b1 p
03
b100011011010100 4
b10111 Q
