src/posit_encode.sv
/*

Description:
    Posit encoder.

Usage:
    cd $PROJECT_ROOT/waveforms
    
    iverilog -DTEST_BENCH_ENCODE -DNO_ES_FIELD -DN=8 -DES=0 -o posit_encode.out ../src/posit_encode.sv && ./posit_encode.out

    iverilog -DTEST_BENCH_ENCODE               -DN=16 -DES=1 -o posit_encode.out ../src/posit_encode.sv && ./posit_encode.out

    yosys -p "synth_intel -family max10 -top posit_encode -vqm posit_encode.vqm" ../src/posit_encode.sv > yosys_posit_encode.out

*/
module posit_encode #(
        parameter N = 8,
        parameter S = $clog2(N),
        parameter ES = 0
    )(
        input          is_zero,
        input          is_inf,
        input          sign,
        input [S:0]    reg_len,
        input [S:0]    k,
`ifndef NO_ES_FIELD
        input [ES-1:0] exp,
`endif
        input [N-1:0]  mant,
        output [N-1:0] posit
    );
    
    function [N-1:0] c2(input [N-1:0] a);
        c2 = ~a + 1'b1;
    endfunction

    function is_negative(input [S:0] k);
        is_negative = k[S];
    endfunction

    
    function [N-1:0] shl (
            input [N-1:0] bits,
            input [N-1:0] rhs
        );
        shl = rhs[N-1] == 0 ? bits << rhs : bits >> c2(rhs);
    endfunction

    wire [N-1:0] bits_assembled;

    wire [N:0] regime_bits; // 1 bit longer than it could regularly fit in.
    
    assign regime_bits = is_negative(k) ? 1 : (shl(1, (k + 1)) - 1) << 1;

    assign bits_assembled = ( 
          shl(sign, N-1)
        + shl(regime_bits, N-1-reg_len)
`ifndef NO_ES_FIELD
        + shl(exp, N-1-reg_len-ES)
`endif
        + mant
    );

    wire [N-1:0] bits;
    assign bits = 
        sign == 0 ? bits_assembled : 
                    c2(bits_assembled & ~(1 << (N-1)));

    /*
    ~(1'b1 << (N-1)) === {1'b0, {N-1{1'b1}}}
    */

    assign posit = 
        is_zero === 1 ? 0 : 
        is_inf  === 1 ? (1 << (N-1)) :
                        bits;
            /*  ^^^ 3 equal signs needed to compare against 1'bx, 
                otherwise if `is_zero` or `is_inf` == 1'bx, also 
                `posit` would be 'bX, regardless. */
endmodule


`ifdef TEST_BENCH_ENCODE 

// defaulted to P<8,0> unless specified via some `-D`efine.

module tb_posit_encode;
    function [N-1:0] c2(input [N-1:0] a);
        c2 = ~a + 1'b1;
    endfunction
    function [N-1:0] abs(input [N-1:0] in);
        abs = in[N-1] == 0 ? in : c2(in);
    endfunction

`ifdef N
    parameter N = `N;
`else
    parameter N = 8;
`endif

    parameter S = $clog2(N);

`ifdef ES
    parameter ES = `ES;
`else
    parameter ES = 0;
`endif

    /* inputs */
    reg            is_zero;
    reg            is_inf;
    reg            sign;
    reg [S:0]      reg_len;
    reg [S:0]      k;
`ifndef NO_ES_FIELD
    reg [ES-1:0]   exp;
`endif
    reg [N-1:0]    mant;
    /* output */
    wire [N-1:0]   posit;
    /*************************/

    reg [N-1:0]   posit_expected;
    reg err;
    
    reg [N:0] test_no;

    posit_encode #(
        .N(N),
        .S(S),
        .ES(ES)
    ) posit_encode_inst (
        .is_zero        (is_zero),
        .is_inf         (is_inf),
        .sign           (sign),
        .reg_len        (reg_len),
        .k              (k),
`ifndef NO_ES_FIELD
        .exp            (exp),
`endif
        .mant           (mant),
        .posit          (posit)
    );

    always @(*) begin
        err = posit == posit_expected ? 0 : 1'bx;
    end

    initial begin
             if (N == 8 && ES == 0) $dumpfile("tb_posit_encode_P8E0.vcd");
        else if (N == 5 && ES == 1) $dumpfile("tb_posit_encode_P5E1.vcd");
        else if (N == 16 && ES == 1) $dumpfile("tb_posit_encode_P16E1.vcd");
        else                        $dumpfile("tb_posit_encode.vcd");

	    $dumpvars(0, tb_posit_encode);                        
            
        if (N == 8 && ES == 0) begin
            `include "../src/tb_posit_encode_P8E0.sv"
        end

        if (N == 16 && ES == 1) begin
            `include "../src/tb_posit_encode_P16E1.sv"
        end
       

        #10;
		$finish;
    end

endmodule
`endif

waveforms/tb_posit_encode_P16E1.vcd
$date
	Tue Dec 21 19:53:59 2021
$end
$version
	Icarus Verilog
$end
$timescale
	1s
$end
$scope module tb_posit_encode $end
$var wire 16 ! posit [15:0] $end
$var reg 1 " err $end
$var reg 1 # exp $end
$var reg 1 $ is_inf $end
$var reg 1 % is_zero $end
$var reg 5 & k [4:0] $end
$var reg 16 ' mant [15:0] $end
$var reg 16 ( posit_expected [15:0] $end
$var reg 5 ) reg_len [4:0] $end
$var reg 1 * sign $end
$var reg 17 + test_no [16:0] $end
$scope function abs $end
$var reg 16 , in [15:0] $end
$upscope $end
$scope function c2 $end
$var reg 16 - a [15:0] $end
$upscope $end
$scope module posit_encode_inst $end
$var wire 1 # exp $end
$var wire 1 $ is_inf $end
$var wire 1 % is_zero $end
$var wire 5 . k [4:0] $end
$var wire 16 / mant [15:0] $end
$var wire 5 0 reg_len [4:0] $end
$var wire 1 * sign $end
$var wire 17 1 regime_bits [16:0] $end
$var wire 16 2 posit [15:0] $end
$var wire 16 3 bits_assembled [15:0] $end
$var wire 16 4 bits [15:0] $end
$scope function c2 $end
$var reg 16 5 a [15:0] $end
$upscope $end
$scope function is_negative $end
$var reg 5 6 k [4:0] $end
$upscope $end
$scope function shl $end
$var reg 16 7 bits [15:0] $end
$var reg 16 8 rhs [15:0] $end
$upscope $end
$upscope $end
$upscope $end
$enddefinitions $end
#0
$dumpvars
b1101 8
b1 7
b11111 6
b11110001101101 5
b11110001101101 4
b11110001101101 3
b11110001101101 2
b1 1
b10 0
b110001101101 /
b11111 .
bx -
bx ,
b1 +
0*
b10 )
b11110001101101 (
b110001101101 '
b11111 &
0%
0$
1#
0"
b11110001101101 !
$end
#10
b100110110100100 !
b100110110100100 2
b100110110100100 5
b10 1
b100110110100100 4
b10 7
b0 6
b1101 8
0"
b100110110100100 3
b110110100100 '
b110110100100 /
0#
b0 &
b0 .
b100110110100100 (
b10 +
#20
b1101001101001 !
b1101001101001 2
b1101001101001 5
b1 1
b1101001101001 4
b11110 6
b1100 8
b1 7
0"
b1101001101001 3
b1001101001 '
b1001101001 /
1#
b11110 &
b11110 .
b11 )
b11 0
b1101001101001 (
b11 +
#30
b1011100010100001 !
b1011100010100001 2
b100011101011111 5
b10 1
b10 7
b0 6
b1101 8
b1011100010100001 4
0"
b1100011101011111 3
b11101011111 '
b11101011111 /
0#
b0 &
b0 .
b10 )
b10 0
1*
b1011100010100001 (
b100 +
#40
b110 1
b110010101100100 !
b110010101100100 2
b110010101100100 5
b1 6
b1100 8
b110 7
b110010101100100 4
0"
b110010101100100 3
b10101100100 '
b10101100100 /
b1 &
b1 .
b11 )
b11 0
0*
b110010101100100 (
b101 +
#50
b111101010010111 !
b111101010010111 2
b11110 1
b111101010010111 5
b111101010010111 4
b11 6
b1010 8
b11110 7
0"
b111101010010111 3
b10010111 '
b10010111 /
1#
b11 &
b11 .
b101 )
b101 0
b111101010010111 (
b110 +
#60
b10011110101100 !
b10011110101100 2
b10011110101100 5
b1 1
b10011110101100 4
b11111 6
b1101 8
b1 7
0"
b10011110101100 3
b11110101100 '
b11110101100 /
0#
b11111 &
b11111 .
b10 )
b10 0
b10011110101100 (
b111 +
#70
b1011100010000 !
b1011100010000 2
b1011100010000 5
b1 7
b1011100010000 4
b11110 6
b1100 8
0"
b1011100010000 3
b11100010000 '
b11100010000 /
b11110 &
b11110 .
b11 )
b11 0
b1011100010000 (
b1000 +
#80
b1000100000111 !
b1000100000111 2
b1000100000111 5
b1000100000111 4
0"
b1000100000111 3
b100000111 '
b100000111 /
b1000100000111 (
b1001 +
#90
bx 1
bx 7
b0 !
b0 2
bx 4
bx 6
bx 5
bx 8
0"
1%
bx 3
b0 '
b0 /
bx &
bx .
bx )
bx 0
b0 (
b1010 +
#100
b110011011001110 5
b110011011001110 4
b110011011001110 3
b110 1
b110011011001110 !
b110011011001110 2
b1 6
b1100 8
b110 7
0"
0%
b11011001110 '
b11011001110 /
b1 &
b1 .
b11 )
b11 0
b110011011001110 (
b1011 +
#110
b1110 1
b1000110010100101 !
b1000110010100101 2
b111001101011011 5
b10 6
b1011 8
b1110 7
b1000110010100101 4
0"
b1111001101011011 3
b1101011011 '
b1101011011 /
b10 &
b10 .
b100 )
b100 0
1*
b1000110010100101 (
b1100 +
#120
bx 4
b1000000000000000 !
b1000000000000000 2
bx 1
bx 6
bx 5
bx 8
bx 7
0"
1$
bx 3
b0 '
b0 /
bx &
bx .
bx )
bx 0
b1000000000000000 (
b1101 +
#130
b100101000010100 5
b100101000010100 4
b100101000010100 3
b100101000010100 !
b100101000010100 2
b10 1
b0 6
b1101 8
b10 7
0"
0$
b101000010100 '
b101000010100 /
b0 &
b0 .
b10 )
b10 0
0*
b100101000010100 (
b1110 +
#140
b1100110011101010 !
b1100110011101010 2
b11001100010110 5
b1 1
b11111 6
b1101 8
b1 7
b1100110011101010 4
0"
b1011001100010110 3
b1100010110 '
b1100010110 /
1#
b11111 &
b11111 .
1*
b1100110011101010 (
b1111 +
#150
b1111110101110010 !
b1111110101110010 2
b1111110101110010 4
b1010001110 5
b1 7
b11011 6
b1001 8
0"
b1000001010001110 3
b10001110 '
b10001110 /
0#
b11011 &
b11011 .
b110 )
b110 0
b1111110101110010 (
b10000 +
#160
b1100001111100001 !
b1100001111100001 2
b1100001111100001 4
b11110000011111 5
b11111 6
b1101 8
0"
b1011110000011111 3
b110000011111 '
b110000011111 /
1#
b11111 &
b11111 .
b10 )
b10 0
b1100001111100001 (
b10001 +
#170
b111100010000 !
b111100010000 2
b111100010000 5
b11101 6
b1011 8
b1 7
b111100010000 4
0"
b111100010000 3
b1100010000 '
b1100010000 /
b11101 &
b11101 .
b100 )
b100 0
0*
b111100010000 (
b10010 +
#180
b11100011010000 !
b11100011010000 2
b11100011010000 5
b11100011010000 4
b11111 6
b1101 8
0"
b11100011010000 3
b100011010000 '
b100011010000 /
b11111 &
b11111 .
b10 )
b10 0
b11100011010000 (
b10011 +
#190
b11110 7
b1000010100110100 !
b1000010100110100 2
b111101011001100 5
b11110 1
b11 6
b1010 8
b1000010100110100 4
0"
b1111101011001100 3
b11001100 '
b11001100 /
b11 &
b11 .
b101 )
b101 0
1*
b1000010100110100 (
b10100 +
#200
b1000100101100011 !
b1000100101100011 2
b1000100101100011 4
b1110 1
b111011010011101 5
b10 6
b1011 8
b1110 7
0"
b1111011010011101 3
b1010011101 '
b1010011101 /
b10 &
b10 .
b100 )
b100 0
b1000100101100011 (
b10101 +
#210
b10 1
b101110000111001 !
b101110000111001 2
b101110000111001 5
b0 6
b1101 8
b10 7
b101110000111001 4
0"
b101110000111001 3
b110000111001 '
b110000111001 /
b0 &
b0 .
b10 )
b10 0
0*
b101110000111001 (
b10110 +
#220
b100011011010100 !
b100011011010100 2
b100011011010100 5
b100011011010100 4
b1100 8
b0 7
0"
b100011011010100 3
b11011010100 '
b11011010100 /
0#
b100011011010100 (
b10111 +
#230
b1100011110011101 !
b1100011110011101 2
b11100001100011 5
b1 1
b11111 6
b1101 8
b1 7
b1100011110011101 4
0"
b1011100001100011 3
b100001100011 '
b100001100011 /
1#
b11111 &
b11111 .
1*
b1100011110011101 (
b11000 +
#240
b10110000110011 !
b10110000110011 2
b10110000110011 5
b1100 8
b0 7
b10110000110011 4
0"
b10110000110011 3
b110000110011 '
b110000110011 /
0#
0*
b10110000110011 (
b11001 +
#250
b1101001110101101 !
b1101001110101101 2
b10110001010011 5
b1111 8
b1 7
b1101001110101101 4
0"
b1010110001010011 3
b110001010011 '
b110001010011 /
1*
b1101001110101101 (
b11010 +
#260
b1101100101110 !
b1101100101110 2
b1101100101110 5
b11110 6
b1100 8
b1 7
b1101100101110 4
0"
b1101100101110 3
b1100101110 '
b1100101110 /
1#
b11110 &
b11110 .
b11 )
b11 0
0*
b1101100101110 (
b11011 +
#270
b100001100000000 !
b100001100000000 2
b100001100000000 5
b10 1
b100001100000000 4
b10 7
b0 6
b1101 8
0"
b100001100000000 3
b1100000000 '
b1100000000 /
0#
b0 &
b0 .
b10 )
b10 0
b100001100000000 (
b11100 +
#280
b11011011100010 !
b11011011100010 2
b11011011100010 5
b1 1
b11011011100010 4
b11111 6
b1101 8
b1 7
0"
b11011011100010 3
b11011100010 '
b11011100010 /
1#
b11111 &
b11111 .
b11011011100010 (
b11101 +
#290
b1111000101100101 !
b1111000101100101 2
b111010011011 5
b11101 6
b1011 8
b1111000101100101 4
0"
b1000111010011011 3
b1010011011 '
b1010011011 /
b11101 &
b11101 .
b100 )
b100 0
1*
b1111000101100101 (
b11110 +
#300
b1110110101101111 !
b1110110101101111 2
b1110110101101111 4
b1001010010001 5
b1 7
b11110 6
b1100 8
0"
b1001001010010001 3
b1010010001 '
b1010010001 /
0#
b11110 &
b11110 .
b11 )
b11 0
b1110110101101111 (
b11111 +
#310
b11010010000 !
b11010010000 2
b11010010000 5
b11100 6
b1010 8
b1 7
b11010010000 4
0"
b11010010000 3
b10010000 '
b10010000 /
1#
b11100 &
b11100 .
b101 )
b101 0
0*
b11010010000 (
b100000 +
#320
b1101010000110100 !
b1101010000110100 2
b10101111001100 5
b1 7
b11111 6
b1101 8
b1101010000110100 4
0"
b1010101111001100 3
b101111001100 '
b101111001100 /
0#
b11111 &
b11111 .
b10 )
b10 0
1*
b1101010000110100 (
b100001 +
#330
b1010010000000100 !
b1010010000000100 2
b10 7
b1010010000000100 4
b101101111111100 5
b10 1
b0 6
b1101 8
0"
b1101101111111100 3
b101111111100 '
b101111111100 /
1#
b0 &
b0 .
b1010010000000100 (
b100010 +
#340
b1100111010000000 !
b1100111010000000 2
b1100111010000000 4
b11000110000000 5
b1 1
b11111 6
b1101 8
b1 7
0"
b1011000110000000 3
b110000000 '
b110000000 /
b11111 &
b11111 .
b1100111010000000 (
b100011 +
#350
b100001010100000 !
b100001010100000 2
b100001010100000 5
b10 1
b0 6
b1101 8
b10 7
b100001010100000 4
0"
b100001010100000 3
b1010100000 '
b1010100000 /
0#
b0 &
b0 .
0*
b100001010100000 (
b100100 +
#360
b100010110010001 !
b100010110010001 2
b100010110010001 5
b100010110010001 4
0"
b100010110010001 3
b10110010001 '
b10110010001 /
b100010110010001 (
b100101 +
#370
b11000110000100 !
b11000110000100 2
b11000110000100 5
b1 1
b11000110000100 4
b11111 6
b1101 8
b1 7
0"
b11000110000100 3
b110000100 '
b110000100 /
1#
b11111 &
b11111 .
b11000110000100 (
b100110 +
#380
b10101000110001 !
b10101000110001 2
b10101000110001 5
b10101000110001 4
b1100 8
b0 7
0"
b10101000110001 3
b101000110001 '
b101000110001 /
0#
b10101000110001 (
b100111 +
#390
b100111101010010 !
b100111101010010 2
b100111101010010 5
b10 1
b100111101010010 4
b0 6
b1101 8
b10 7
0"
b100111101010010 3
b111101010010 '
b111101010010 /
b0 &
b0 .
b100111101010010 (
b101000 +
#400
b100101000100101 !
b100101000100101 2
b100101000100101 5
b100101000100101 4
0"
b100101000100101 3
b101000100101 '
b101000100101 /
b100101000100101 (
b101001 +
#410
b1010000010000001 !
b1010000010000001 2
b101111101111111 5
b1100 8
b1 7
b1010000010000001 4
0"
b1101111101111111 3
b111101111111 '
b111101111111 /
1#
1*
b1010000010000001 (
b101010 +
#420
b1101111000001000 !
b1101111000001000 2
b1101111000001000 4
b10000111111000 5
b1 1
b1 7
b11111 6
b1101 8
0"
b1010000111111000 3
b111111000 '
b111111000 /
0#
b11111 &
b11111 .
b1101111000001000 (
b101011 +
#430
b1011101101011101 !
b1011101101011101 2
b10 7
b1011101101011101 4
b100010010100011 5
b10 1
b0 6
b1101 8
0"
b1100010010100011 3
b10010100011 '
b10010100011 /
b0 &
b0 .
b1011101101011101 (
b101100 +
#440
b1111010111111111 !
b1111010111111111 2
b1111010111111111 4
b101000000001 5
b1 1
b11101 6
b1011 8
b1 7
0"
b1000101000000001 3
b1000000001 '
b1000000001 /
b11101 &
b11101 .
b100 )
b100 0
b1111010111111111 (
b101101 +
#450
b1101101011001010 !
b1101101011001010 2
b1101101011001010 4
b10010100110110 5
b1 7
b11111 6
b1101 8
0"
b1010010100110110 3
b10100110110 '
b10100110110 /
b11111 &
b11111 .
b10 )
b10 0
b1101101011001010 (
b101110 +
#460
b1101100100111001 !
b1101100100111001 2
b1101100100111001 4
b10011011000111 5
0"
b1010011011000111 3
b11011000111 '
b11011000111 /
b1101100100111001 (
b101111 +
#470
b1110000101001011 !
b1110000101001011 2
b1110000101001011 4
b1111010110101 5
b11110 6
b1100 8
0"
b1001111010110101 3
b11010110101 '
b11010110101 /
1#
b11110 &
b11110 .
b11 )
b11 0
b1110000101001011 (
b110000 +
#480
b101111101010101 !
b101111101010101 2
b101111101010101 5
b10 1
b0 6
b1101 8
b10 7
b101111101010101 4
0"
b101111101010101 3
b111101010101 '
b111101010101 /
b0 &
b0 .
b10 )
b10 0
0*
b101111101010101 (
b110001 +
#490
b1011000110011 !
b1011000110011 2
b1011000110011 5
b1 1
b1011000110011 4
b11110 6
b1100 8
b1 7
0"
b1011000110011 3
b11000110011 '
b11000110011 /
0#
b11110 &
b11110 .
b11 )
b11 0
b1011000110011 (
b110010 +
#500
b1101100001000100 !
b1101100001000100 2
b10011110111100 5
b1 7
b11111 6
b1101 8
b1101100001000100 4
0"
b1010011110111100 3
b11110111100 '
b11110111100 /
b11111 &
b11111 .
b10 )
b10 0
1*
b1101100001000100 (
b110011 +
#510
b1001101100011001 !
b1001101100011001 2
b1001101100011001 4
b110010011100111 5
b110 1
b110 7
b1 6
b1100 8
0"
b1110010011100111 3
b10011100111 '
b10011100111 /
b1 &
b1 .
b11 )
b11 0
b1001101100011001 (
b110100 +
#520
b10 1
b101011001100000 !
b101011001100000 2
b101011001100000 5
b0 6
b1101 8
b10 7
b101011001100000 4
0"
b101011001100000 3
b11001100000 '
b11001100000 /
1#
b0 &
b0 .
b10 )
b10 0
0*
b101011001100000 (
b110101 +
#530
b1010101111110100 !
b1010101111110100 2
b101010000001100 5
b1111 8
b1 7
b1010101111110100 4
0"
b1101010000001100 3
b10000001100 '
b10000001100 /
1*
b1010101111110100 (
b110110 +
#540
b110 1
b110001101001111 !
b110001101001111 2
b110001101001111 5
b1 6
b1100 8
b110 7
b110001101001111 4
0"
b110001101001111 3
b1101001111 '
b1101001111 /
0#
b1 &
b1 .
b11 )
b11 0
0*
b110001101001111 (
b110111 +
#550
b1111110 1
b1000000110000110 !
b1000000110000110 2
b111111001111010 5
b101 6
b1000 8
b1111110 7
b1000000110000110 4
0"
b1111111001111010 3
b1111010 '
b1111010 /
b101 &
b101 .
b111 )
b111 0
1*
b1000000110000110 (
b111000 +
#560
b11111110110110 !
b11111110110110 2
b11111110110110 5
b1 1
b11111 6
b1101 8
b1 7
b11111110110110 4
0"
b11111110110110 3
b111110110110 '
b111110110110 /
1#
b11111 &
b11111 .
b10 )
b10 0
0*
b11111110110110 (
b111001 +
#570
b10110110000011 !
b10110110000011 2
b10110110000011 5
b10110110000011 4
b1100 8
b0 7
0"
b10110110000011 3
b110110000011 '
b110110000011 /
0#
b10110110000011 (
b111010 +
#580
b11111101010000 !
b11111101010000 2
b11111101010000 5
b11111101010000 4
b1 7
0"
b11111101010000 3
b111101010000 '
b111101010000 /
1#
b11111101010000 (
b111011 +
#590
b111100100111101 !
b111100100111101 2
b111100100111101 5
b11110 1
b111100100111101 4
b11110 7
b11 6
b1010 8
0"
b111100100111101 3
b100111101 '
b100111101 /
0#
b11 &
b11 .
b101 )
b101 0
b111100100111101 (
b111100 +
#600
b100011110101101 !
b100011110101101 2
b10 1
b100011110101101 5
b100011110101101 4
b0 6
b1101 8
b10 7
0"
b100011110101101 3
b11110101101 '
b11110101101 /
b0 &
b0 .
b10 )
b10 0
b100011110101101 (
b111101 +
#610
b1011011011111 !
b1011011011111 2
b1011011011111 5
b1 1
b1011011011111 4
b11110 6
b1100 8
b1 7
0"
b1011011011111 3
b11011011111 '
b11011011111 /
b11110 &
b11110 .
b11 )
b11 0
b1011011011111 (
b111110 +
#620
b1111000111001111 !
b1111000111001111 2
b111000110001 5
b11101 6
b1011 8
b1111000111001111 4
0"
b1000111000110001 3
b1000110001 '
b1000110001 /
1#
b11101 &
b11101 .
b100 )
b100 0
1*
b1111000111001111 (
b111111 +
#630
b1110111101000001 !
b1110111101000001 2
b1110111101000001 4
b1000010111111 5
b1 7
b11110 6
b1100 8
0"
b1001000010111111 3
b10111111 '
b10111111 /
0#
b11110 &
b11110 .
b11 )
b11 0
b1110111101000001 (
b1000000 +
#640
b1101000101100000 !
b1101000101100000 2
b1101000101100000 4
b10111010100000 5
b1 7
b11111 6
b1101 8
0"
b1010111010100000 3
b111010100000 '
b111010100000 /
b11111 &
b11111 .
b10 )
b10 0
b1101000101100000 (
b1000001 +
#650
b1101110110010000 !
b1101110110010000 2
b1101110110010000 4
b10001001110000 5
0"
b1010001001110000 3
b1001110000 '
b1001110000 /
b1101110110010000 (
b1000010 +
#660
b1111000100110100 !
b1111000100110100 2
b1111000100110100 4
b111011001100 5
b11101 6
b1011 8
0"
b1000111011001100 3
b1011001100 '
b1011001100 /
1#
b11101 &
b11101 .
b100 )
b100 0
b1111000100110100 (
b1000011 +
#670
b1000110000110010 !
b1000110000110010 2
b1000110000110010 4
b111001111001110 5
b1110 1
b1110 7
b10 6
b1011 8
0"
b1111001111001110 3
b1111001110 '
b1111001110 /
0#
b10 &
b10 .
b1000110000110010 (
b1000100 +
#680
b1101011100101000 !
b1101011100101000 2
b1101011100101000 4
b10100011011000 5
b1 1
b11111 6
b1101 8
b1 7
0"
b1010100011011000 3
b100011011000 '
b100011011000 /
b11111 &
b11111 .
b10 )
b10 0
b1101011100101000 (
b1000101 +
#690
b100110011011100 !
b100110011011100 2
b100110011011100 5
b10 1
b0 6
b1101 8
b10 7
b100110011011100 4
0"
b100110011011100 3
b110011011100 '
b110011011100 /
b0 &
b0 .
0*
b100110011011100 (
b1000110 +
#700
b111011000 !
b111011000 2
b111011000 5
b1 1
b111011000 4
b11010 6
b1000 8
b1 7
0"
b111011000 3
b1011000 '
b1011000 /
1#
b11010 &
b11010 .
b111 )
b111 0
b111011000 (
b1000111 +
#710
b1110100010101011 !
b1110100010101011 2
b1011101010101 5
b1 7
b11110 6
b1100 8
b1110100010101011 4
0"
b1001011101010101 3
b11101010101 '
b11101010101 /
0#
b11110 &
b11110 .
b11 )
b11 0
1*
b1110100010101011 (
b1001000 +
#720
b100101010111100 !
b100101010111100 2
b100101010111100 5
b10 1
b0 6
b1101 8
b10 7
b100101010111100 4
0"
b100101010111100 3
b101010111100 '
b101010111100 /
b0 &
b0 .
b10 )
b10 0
0*
b100101010111100 (
b1001001 +
#730
b110 1
b1001001010000110 !
b1001001010000110 2
b110110101111010 5
b1 6
b1100 8
b110 7
b1001001010000110 4
0"
b1110110101111010 3
b10101111010 '
b10101111010 /
1#
b1 &
b1 .
b11 )
b11 0
1*
b1001001010000110 (
b1001010 +
#740
b1011010001110100 !
b1011010001110100 2
b1011010001110100 4
b10 1
b100101110001100 5
b0 6
b1101 8
b10 7
0"
b1100101110001100 3
b101110001100 '
b101110001100 /
0#
b0 &
b0 .
b10 )
b10 0
b1011010001110100 (
b1001011 +
#750
b1110000111011111 !
b1110000111011111 2
b1110000111011111 4
b1111000100001 5
b1 1
b11110 6
b1100 8
b1 7
0"
b1001111000100001 3
b11000100001 '
b11000100001 /
1#
b11110 &
b11110 .
b11 )
b11 0
b1110000111011111 (
b1001100 +
#760
b100111111001111 !
b100111111001111 2
b100111111001111 5
b10 1
b0 6
b1101 8
b10 7
b100111111001111 4
0"
b100111111001111 3
b111111001111 '
b111111001111 /
0#
b0 &
b0 .
b10 )
b10 0
0*
b100111111001111 (
b1001101 +
#770
b1101100100011001 !
b1101100100011001 2
b10011011100111 5
b1 1
b11111 6
b1101 8
b1 7
b1101100100011001 4
0"
b1010011011100111 3
b11011100111 '
b11011100111 /
b11111 &
b11111 .
1*
b1101100100011001 (
b1001110 +
#780
b1100001111100100 !
b1100001111100100 2
b1100001111100100 4
b11110000011100 5
b1100 8
0"
b1011110000011100 3
b110000011100 '
b110000011100 /
1#
b1100001111100100 (
b1001111 +
#790
b1000001000100100 !
b1000001000100100 2
b111110 7
b1000001000100100 4
b111110111011100 5
b111110 1
b100 6
b1001 8
0"
b1111110111011100 3
b11011100 '
b11011100 /
b100 &
b100 .
b110 )
b110 0
b1000001000100100 (
b1010000 +
#800
b11000111110011 !
b11000111110011 2
b11000111110011 5
b1 1
b11111 6
b1101 8
b1 7
b11000111110011 4
0"
b11000111110011 3
b111110011 '
b111110011 /
b11111 &
b11111 .
b10 )
b10 0
0*
b11000111110011 (
b1010001 +
#810
b110 7
b110100111111000 !
b110100111111000 2
b110100111111000 5
b110 1
b110100111111000 4
b1 6
b1100 8
0"
b110100111111000 3
b111111000 '
b111111000 /
b1 &
b1 .
b11 )
b11 0
b110100111111000 (
b1010010 +
#820
b110110001111001 !
b110110001111001 2
b110110001111001 5
b110110001111001 4
0"
b110110001111001 3
b10001111001 '
b10001111001 /
b110110001111001 (
b1010011 +
#830
b1001100101010010 !
b1001100101010010 2
b110011010101110 5
b1011 8
b0 7
b1001100101010010 4
0"
b1110011010101110 3
b11010101110 '
b11010101110 /
0#
1*
b1001100101010010 (
b1010100 +
#840
b10 1
b100100111000111 !
b100100111000111 2
b100100111000111 5
b0 6
b10 7
b1101 8
b100100111000111 4
0"
b100100111000111 3
b100111000111 '
b100111000111 /
b0 &
b0 .
b10 )
b10 0
0*
b100100111000111 (
b1010101 +
#850
b110111001011000 !
b110111001011000 2
b110 1
b110111001011000 5
b110111001011000 4
b1 6
b1100 8
b110 7
0"
b110111001011000 3
b11001011000 '
b11001011000 /
1#
b1 &
b1 .
b11 )
b11 0
b110111001011000 (
b1010110 +
#860
b111001110001101 !
b111001110001101 2
b1110 1
b111001110001101 5
b111001110001101 4
b10 6
b1011 8
b1110 7
0"
b111001110001101 3
b1110001101 '
b1110001101 /
0#
b10 &
b10 .
b100 )
b100 0
b111001110001101 (
b1010111 +
#870
b10100101001100 !
b10100101001100 2
b10100101001100 5
b1 1
b10100101001100 4
b11111 6
b1101 8
b1 7
0"
b10100101001100 3
b100101001100 '
b100101001100 /
b11111 &
b11111 .
b10 )
b10 0
b10100101001100 (
b1011000 +
#880
b11101110110100 !
b11101110110100 2
b11101110110100 5
b11101110110100 4
b1100 8
0"
b11101110110100 3
b101110110100 '
b101110110100 /
1#
b11101110110100 (
b1011001 +
#890
b100111000011011 !
b100111000011011 2
b100111000011011 5
b10 1
b100111000011011 4
b10 7
b0 6
b1101 8
0"
b100111000011011 3
b111000011011 '
b111000011011 /
0#
b0 &
b0 .
b100111000011011 (
b1011010 +
#900
b100001001111000 !
b100001001111000 2
b100001001111000 5
b100001001111000 4
0"
b100001001111000 3
b1001111000 '
b1001111000 /
b100001001111000 (
b1011011 +
#910
b1101000000000110 !
b1101000000000110 2
b10111111111010 5
b1 1
b11111 6
b1101 8
b1 7
b1101000000000110 4
0"
b1010111111111010 3
b111111111010 '
b111111111010 /
b11111 &
b11111 .
1*
b1101000000000110 (
b1011100 +
#920
b1100110000100001 !
b1100110000100001 2
b1100110000100001 4
b11001111011111 5
b1100 8
0"
b1011001111011111 3
b1111011111 '
b1111011111 /
1#
b1100110000100001 (
b1011101 +
#930
b101100010001 !
b101100010001 2
b101100010001 5
b11101 6
b1011 8
b1 7
b101100010001 4
0"
b101100010001 3
b1100010001 '
b1100010001 /
0#
b11101 &
b11101 .
b100 )
b100 0
0*
b101100010001 (
b1011110 +
#940
b1010011000001 !
b1010011000001 2
b1010011000001 5
b1 7
b1010011000001 4
b11110 6
b1100 8
0"
b1010011000001 3
b10011000001 '
b10011000001 /
b11110 &
b11110 .
b11 )
b11 0
b1010011000001 (
b1011111 +
#950
b101111011011 !
b101111011011 2
b101111011011 5
b1 7
b101111011011 4
b11101 6
b1011 8
0"
b101111011011 3
b1111011011 '
b1111011011 /
b11101 &
b11101 .
b100 )
b100 0
b101111011011 (
b1100000 +
#960
b1110 7
b111011001110001 !
b111011001110001 2
b111011001110001 5
b1110 1
b111011001110001 4
b10 6
b1011 8
0"
b111011001110001 3
b1001110001 '
b1001110001 /
1#
b10 &
b10 .
b111011001110001 (
b1100001 +
#970
b10 1
b1010000001011000 !
b1010000001011000 2
b101111110101000 5
b0 6
b1101 8
b10 7
b1010000001011000 4
0"
b1101111110101000 3
b111110101000 '
b111110101000 /
b0 &
b0 .
b10 )
b10 0
1*
b1010000001011000 (
b1100010 +
#980
b1111111101011010 !
b1111111101011010 2
b1111111101011010 4
b10100110 5
b1 1
b11001 6
b111 8
b1 7
0"
b1000000010100110 3
b100110 '
b100110 /
0#
b11001 &
b11001 .
b1000 )
b1000 0
b1111111101011010 (
b1100011 +
#990
b100011111001010 !
b100011111001010 2
b100011111001010 5
b10 1
b0 6
b1101 8
b10 7
b100011111001010 4
0"
b100011111001010 3
b11111001010 '
b11111001010 /
b0 &
b0 .
b10 )
b10 0
0*
b100011111001010 (
b1100100 +
#1000
b11110 1
b1000010011010100 !
b1000010011010100 2
b111101100101100 5
b11 6
b1010 8
b11110 7
b1000010011010100 4
0"
b1111101100101100 3
b100101100 '
b100101100 /
1#
b11 &
b11 .
b101 )
b101 0
1*
b1000010011010100 (
b1100101 +
#1010
b1000100011011100 !
b1000100011011100 2
b1000100011011100 4
b1110 1
b111011100100100 5
b10 6
b1011 8
b1110 7
0"
b1111011100100100 3
b1100100100 '
b1100100100 /
b10 &
b10 .
b100 )
b100 0
b1000100011011100 (
b1100110 +
#1020
b1010010111100011 !
b1010010111100011 2
b1010010111100011 4
b10 1
b101101000011101 5
b0 6
b1101 8
b10 7
0"
b1101101000011101 3
b101000011101 '
b101000011101 /
b0 &
b0 .
b10 )
b10 0
b1010010111100011 (
b1100111 +
