src/highest_set.sv
/*

Description:
    [FIX:outdated] Given a sequence of bits returns the highest index of said bits such that the bit is `VAL`.
    e.g.:
        bits = 8b00001001 -> 3

Usage:
    cd $PROJECT_ROOT/waveforms
    iverilog -g2012 -DN=8 -DHIGHEST_SET_TB -o highest_set.out ../src/highest_set.sv ../src/utils.sv && ./highest_set.out

    sv2v -DN=8 ../src/highest_set.sv ../src/utils.sv > highest_set.v

    ~/Documents/dev/yosys/yosys0.9_1979e0b1f -DN=16 -p "synth_intel -family max10 -top highest_set_v1b -vqm highest_set.vqm" ../src/highest_set.sv > yosys_intel_highest_set_v1.out
    yosys -p "synth_intel -family max10 -top highest_set_v2 -vqm highest_set.vqm" ../src/highest_set.sv > yosys_intel_highest_set_v2.out
*/


/**
 *  `highest_set_v1` requires less LE than `highest_set_v3` but longer path (O(size) growth)
 */


module highest_set_v1 #(
        parameter N = `N,
        parameter VAL = 1
    )(
        input logic[N-1:0] bits,
        output wire [$clog2(N)-1:0] index
    );
    
    wire [S-1:0] out_stage [0:N];
    assign out_stage[0] = {S{1'b1}}; // desired default output if no bits set

    generate genvar i;
        for (i=0; i<N; i=i+1) begin: _gen
            assign out_stage[i+1] = (bits[i] == VAL) ? i : out_stage[i]; 
        end
    endgenerate

    assign index = out_stage[N];
endmodule

module highest_set_v1b #(
        parameter SIZE = 2
    )(
        input logic[SIZE-1:0] bits,
        input val,
        output wire [$clog2(SIZE)-1:0] index
    );
    
    wire [$clog2(SIZE)-1:0] out_stage [0:SIZE];
    assign out_stage[0] = ~0; // desired default output if no bits set

    generate genvar i;
        for (i=0; i<SIZE; i=i+1) begin: _gen
            assign out_stage[i+1] = (bits[i] == val) ? i : out_stage[i]; 
        end
    endgenerate

    assign index = out_stage[SIZE];
endmodule






/*
ref: http://www.ece.ualberta.ca/~jhan8/publications/1570528628.pdf
*/
module highest_set_v2 #(
        parameter N = `N,
        parameter VAL = 1
    )(
        input logic [N-1:0] bits,
        output wire [N-1:0] index_bit,
        output wire [$clog2(N)-1:0] index
    );

    wire [N-1:0] _wire;
    
    generate genvar i;
        for (i=0; i<N-1; i=i+1) begin
            mux mux_inst (
                .a      (_wire[i+1]),
                .sel    (bits[i+1]),
                .and_in (bits[i]),
                .mux_out(_wire[i]),
                .and_out(index_bit[i])
            );
        end
    endgenerate

    assign _wire[N-1] = 1;
    assign index_bit[N-1] = bits[N-1];

    /// assign index = $clog2(index_bit); //// achtung, fails to synthesize.

    decoder #(
        .N(N)
    ) decoder_inst (
        .in(index_bit),
        .out(index)
    );
endmodule

module decoder #(
        parameter N = `N
    )(
        input [N-1:0] in,
        output [$clog2(N)-1:0] out
    );
    
    generate genvar i;
        for (i=0; i<N; i=i+1) begin
            assign out = in == (1 << i) ? i : 'bz;
        end
    endgenerate
endmodule

/**
 * mux + and gate actually. 
 * only instantiated by `highest_set_v2`. maybe unnecessary later on.
 */
module mux (
        input a,
        /* input b, */
        input sel,
        input and_in,
        output mux_out,
        output and_out
    );
    wire b = 0;
    assign mux_out = sel == 0 ? a : b;
    assign and_out = and_in & mux_out; 
endmodule





/**
 *  `highest_set_v3` requires more LE than `highest_set_v1` but shorter path (O(1))
 */
module highest_set_v3 #(
        parameter N = `N,
        parameter VAL = 1
    )(
        input logic [N-1:0] bits,
        output wire [N-1:0] index_bit,
        output wire [$clog2(N)-1:0] index
    );

    wire [N-1:0] bits_reversed;
    wire [N-1:0] _index_bit_tmp;

    genvar i;
    generate
        for (i=0; i<N; i=i+1) begin: _gen1
            assign bits_reversed[i] = bits[N-1-i];
        end
    endgenerate
    
    
    /// detect the rightmost bit-set index: 10'b0011001000 
    ///                                               ^
    ///                                  -> 10'b0000001000
    assign _index_bit_tmp = bits_reversed & c2(bits_reversed);

    generate
        for (i=0; i<N; i=i+1) begin: _gen2
            assign index_bit[i] = _index_bit_tmp[N-1-i];
        end
    endgenerate

endmodule


`ifdef HIGHEST_SET_TB
module tb_highest_set;
    parameter VAL = 1;

    reg [N-1:0] posit;
    wire [S-1:0] index_v1, index_v1b, index_v2, index_v3;
    wire [N-1:0] index_bit_v3;

    reg diff;

    highest_set_v1 #(
        .N      (N),
        .VAL    (VAL)
    )
    highest_set_inst1 (
        .bits   (posit),
        .index  (index_v1)
    );

    highest_set_v1b #(
        .N      (N)
    )
    highest_set_inst1b (
        .bits   (posit),
        .val    (1'b1),
        .index  (index_v1b)
    );

    highest_set_v2 #(
        .N      (N),
        .VAL    (VAL)
    )
    highest_set_inst2 (
        .bits   (posit),
        .index  (index_v2)
    );

    highest_set_v3 #(
        .N      (N),
        .VAL    (VAL)
    )
    highest_set_inst3 (
        .bits   (posit),
        .index_bit (index_bit_v3),
        .index  (index_v3)
    );

    always @(*) begin
        diff = index_v1 == index_v2 ? 0 : 1'bx;
    end

    initial begin
        $dumpfile("tb_highest_set.vcd");
        $dumpvars(0, tb_highest_set);

                posit = 8'b0000_0001;
        #10     posit = 8'b0000_0011;
        #10     posit = 8'b0000_1000;
        #10     posit = 8'b0011_0000;
        #10     posit = 8'b0101_0101;
        #10     posit = 8'b1100_0000;
        #10     posit = 8'b1111_1111;

        #10;
        $finish;
    end
endmodule
`endif

src/cls.sv
/*

Description:
    cls: count leading ones.
    It wraps the `highest_set` module; returns the number of ones starting from the left:

    e.g:
        bits = 0b11010000 -> 2
        bits = 0b01111000 -> 0
        bits = 0b11100000 -> 3

Usage:
    cd $PROJECT_ROOT/waveforms
    
    iverilog -DTEST_BENCH_CLS -o cls.out ../src/cls.sv ../src/highest_set.sv && ./cls.out
*/


module cls #(
        parameter N = 8,
        parameter S = $clog2(N)
    )(
        input [N-1:0] bits,
        output [S-1:0] leading_ones,
        output [S-1:0] index_highest_set
    );

    highest_set_v1 #(
        .SIZE   (N),
        .VAL    (0)
    )
    highest_set_inst(
        .bits   (bits),
        .index  (index_highest_set)
    );

    assign leading_ones = (N - 1) - index_highest_set;
endmodule




`ifdef TEST_BENCH_CLS
module tb_cls;

    parameter N = 8;
    parameter S = $clog2(N);

    reg [N-1:0] bits;
    wire [S-1:0] leading_ones, leading_zeros;
    wire [S-1:0] index_highest_set_1, index_highest_set_2;

    /* count leading set (ones) */
    cls #(
        .N              (N),
        .S              (S)
    ) count_leading_ones (
        .bits           (bits),
        .leading_ones   (leading_ones),
        .index_highest_set(index_highest_set_1)
    );

    /* count leading set (zeros), inputs bits are flipped */
    cls #(
        .N              (N),
        .S              (S)
    ) count_leading_zeros (
        .bits           (~bits),
        .leading_ones   (leading_zeros),
        .index_highest_set(index_highest_set_2)
    );



    initial begin
        $dumpfile("tb_cls.vcd");
        $dumpvars(0, tb_cls);

                bits = 8'b0000_0001;
        #10     bits = 8'b1000_0011;
        #10     bits = 8'b1100_1000;
        #10     bits = 8'b0011_0000;
        #10     bits = 8'b0101_0101;
        #10     bits = 8'b1100_0000;
        #10     bits = 8'b1111_1110;

        #10;
        $finish;
    end

endmodule
`endif

src/posit_decode.sv
/*
Description:
    Posit decoder.

Usage:
    cd $PROJECT_ROOT/waveforms

    iverilog -DTEST_BENCH_DECODE -DNO_ES_FIELD -DN=8 -DES=0 -o posit_decode.out \
    ../src/posit_decode.sv \
    ../src/highest_set.sv \
    ../src/cls.sv \
    && ./posit_decode.out

    iverilog -DTEST_BENCH_DECODE               -DN=16 -DES=1 -o posit_decode.out \
    ../src/posit_decode.sv \
    ../src/highest_set.sv \
    ../src/cls.sv \
    && ./posit_decode.out

    iverilog -DTEST_BENCH_DECODE               -DN=32 -DES=2 -o posit_decode.out \
    ../src/posit_decode.sv \
    ../src/highest_set.sv \
    ../src/cls.sv \
    && ./posit_decode.out


    yosys -p "synth_intel -family max10 -top posit_decode -vqm posit_decode.vqm" \
    ../src/posit_decode.sv \
    ../src/highest_set.sv \
    ../src/cls.sv > yosys_posit_decode.out

*/
module posit_decode #(
        parameter N = 8,
        parameter S = $clog2(N),
        parameter ES = 0
    )(
        input [N-1:0]   bits,
        output          is_zero,
        output          is_inf,
        output          sign,
        output          reg_s,

        output [S:0]    reg_len,
        output [S:0]    k,
`ifndef NO_ES_FIELD
        output [ES-1:0] exp,
`endif
        output [N-1:0]  mant
    );

    function [N-1:0] c2(input [N-1:0] a);
        c2 = ~a + 1'b1;
    endfunction

    // function [N-1:0] min(input [N-1:0] a, b);
    //     min = a < b ? a : b;
    // endfunction

    assign is_zero = bits == {N{1'b0}};
    assign is_inf = bits == {1'b1, {N-1{1'b0}}};
    assign sign = bits[N-1];
    
    wire [N-1:0] u_bits;
    assign u_bits = sign == 0 ? bits : c2(bits);

    wire [S-1:0] leading_ones, leading_zeros;

    // regime sign
    assign reg_s = u_bits[N-2];

    assign k = reg_s == 1 ? leading_ones - 1 : c2(leading_zeros);
    
    assign reg_len = reg_s == 1 ? k + 2 : c2(k) + 1;

    // // not useful but anyway

`ifndef NO_ES_FIELD
    assign exp = (u_bits << (1 + reg_len)) >> (N - ES);
`endif

    wire [S:0] mant_len;
    assign mant_len = N - 1 - reg_len - ES;


    assign mant = (u_bits << (N - mant_len)) >> (N - mant_len);
    
    
    // count leading X
    cls #(
        .N(N),
        .S(S)
    ) clo_inst_o (
        .bits               (u_bits << 1), // strip sign bit and count ones from the left
        .leading_ones       (leading_ones),
        .index_highest_set  ()
    );
    cls #(
        .N(N),
        .S(S)
    ) clo_inst_z (
        .bits               (~u_bits << 1), // flip bits, strip sign bit and count zeros from the left
        .leading_ones       (leading_zeros),
        .index_highest_set  ()
    );

endmodule



`ifdef TEST_BENCH_DECODE
module tb_posit_decode;
    function [N-1:0] c2(input [N-1:0] a);
        c2 = ~a + 1'b1;
    endfunction
    function [N-1:0] abs(input [N-1:0] in);
        abs = in[N-1] == 0 ? in : c2(in);
    endfunction

`ifdef N
    parameter N = `N;
`else
    parameter N = 8;
`endif

    parameter S = $clog2(N);

`ifdef ES
    parameter ES = `ES;
`else
    parameter ES = 0;
`endif  

    /* input */
    reg [N-1:0]     bits;
    /* outputs */
    wire            is_zero;
    wire            is_inf;
    wire            sign;
    wire            reg_s;
    wire [S  :0]    reg_len;
    wire [S  :0]    k;
`ifndef NO_ES_FIELD
    wire [ES-1:0]   exp;
`endif
    wire [N-1:0]    mant;
    /*************************/

    reg sign_expected, reg_s_expected;
    reg [S  :0] reg_len_expected, k_expected;
    reg [ES-1:0] exp_expected;
    reg [N-1:0] mant_expected;
    reg [S-1:0] mant_len_expected;
    reg is_zero_expected, is_inf_expected;
    reg err;

    reg [N:0] test_no;

`ifndef NO_ES_FIELD
    reg diff_exp;
`endif    
    reg diff_k, diff_mant, diff_is_zero, diff_is_inf;
    
    reg k_is_pos;
    
    always @(*) begin
`ifndef NO_ES_FIELD
        diff_exp = (exp === exp_expected ? 0 : 'bx);
`endif
        diff_mant = (mant === mant_expected ? 0 : 'bx);
        diff_k = (k === k_expected ? 0 : 'bx);
        diff_is_zero = (is_zero === is_zero_expected ? 0 : 'bx);
        diff_is_inf = (is_inf === is_inf_expected ? 0 : 'bx);
        
        if (
            diff_mant == 0
`ifndef NO_ES_FIELD
            && diff_exp == 0 
`endif
            && diff_k == 0 
            && diff_is_zero == 0 
            && diff_is_inf == 0
        ) err = 0;
        else err = 1'bx;
    end

    posit_decode #(
        .N(N),
        .S(S),
        .ES(ES)
    ) posit_decode_inst (
        .bits           (bits),
        .is_zero        (is_zero),
        .is_inf         (is_inf),
        .sign           (sign),
        .reg_s          (reg_s),

        .reg_len        (reg_len),
        .k              (k),
`ifndef NO_ES_FIELD
        .exp            (exp),
`endif
        .mant           (mant)
    );

    initial begin
             if (N == 8 && ES == 0) $dumpfile("tb_posit_decode_P8E0.vcd");
        else if (N == 5 && ES == 1) $dumpfile("tb_posit_decode_P5E1.vcd");
        else if (N == 16 && ES == 1)$dumpfile("tb_posit_decode_P16E1.vcd");
        else if (N == 32 && ES == 2)$dumpfile("tb_posit_decode_P32E2.vcd");
        else                        $dumpfile("tb_posit_decode.vcd");

	    $dumpvars(0, tb_posit_decode);                        
            
        if (N == 8 && ES == 0) begin
            `include "../src/tb_posit_decode_P8E0.sv"
        end

        if (N == 5 && ES == 1) begin
            `include "../src/tb_posit_decode_P5E1.sv"
        end

        if (N == 16 && ES == 1) begin
            `include "../src/tb_posit_decode_P16E1.sv"
        end

        if (N == 32 && ES == 2) begin
            `include "../src/tb_posit_decode_P32E2.sv"
        end


        
        #10;
		$finish;
    end

endmodule
`endif

waveforms/tb_posit_decode_P16E1.vcd
$date
	Mon Dec 20 19:38:29 2021
$end
$version
	Icarus Verilog
$end
$timescale
	1s
$end
$scope module tb_posit_decode $end
$var wire 1 ! sign $end
$var wire 1 " reg_s $end
$var wire 5 # reg_len [4:0] $end
$var wire 16 $ mant [15:0] $end
$var wire 5 % k [4:0] $end
$var wire 1 & is_zero $end
$var wire 1 ' is_inf $end
$var wire 1 ( exp $end
$var reg 16 ) bits [15:0] $end
$var reg 1 * diff_exp $end
$var reg 1 + diff_is_inf $end
$var reg 1 , diff_is_zero $end
$var reg 1 - diff_k $end
$var reg 1 . diff_mant $end
$var reg 1 / err $end
$var reg 1 0 exp_expected $end
$var reg 1 1 is_inf_expected $end
$var reg 1 2 is_zero_expected $end
$var reg 5 3 k_expected [4:0] $end
$var reg 1 4 k_is_pos $end
$var reg 16 5 mant_expected [15:0] $end
$var reg 4 6 mant_len_expected [3:0] $end
$var reg 5 7 reg_len_expected [4:0] $end
$var reg 1 8 reg_s_expected $end
$var reg 1 9 sign_expected $end
$var reg 17 : test_no [16:0] $end
$scope function abs $end
$var reg 16 ; in [15:0] $end
$upscope $end
$scope function c2 $end
$var reg 16 < a [15:0] $end
$upscope $end
$scope module posit_decode_inst $end
$var wire 16 = bits [15:0] $end
$var wire 16 > u_bits [15:0] $end
$var wire 1 ! sign $end
$var wire 1 " reg_s $end
$var wire 5 ? reg_len [4:0] $end
$var wire 5 @ mant_len [4:0] $end
$var wire 16 A mant [15:0] $end
$var wire 4 B leading_zeros [3:0] $end
$var wire 4 C leading_ones [3:0] $end
$var wire 5 D k [4:0] $end
$var wire 1 & is_zero $end
$var wire 1 ' is_inf $end
$var wire 1 ( exp $end
$scope function c2 $end
$var reg 16 E a [15:0] $end
$upscope $end
$scope module clo_inst_o $end
$var wire 16 F bits [15:0] $end
$var wire 4 G leading_ones [3:0] $end
$var wire 4 H index_highest_set [3:0] $end
$scope module highest_set_inst $end
$var wire 16 I bits [15:0] $end
$var wire 4 J index [3:0] $end
$scope begin _gen[0] $end
$upscope $end
$scope begin _gen[1] $end
$upscope $end
$scope begin _gen[2] $end
$upscope $end
$scope begin _gen[3] $end
$upscope $end
$scope begin _gen[4] $end
$upscope $end
$scope begin _gen[5] $end
$upscope $end
$scope begin _gen[6] $end
$upscope $end
$scope begin _gen[7] $end
$upscope $end
$scope begin _gen[8] $end
$upscope $end
$scope begin _gen[9] $end
$upscope $end
$scope begin _gen[10] $end
$upscope $end
$scope begin _gen[11] $end
$upscope $end
$scope begin _gen[12] $end
$upscope $end
$scope begin _gen[13] $end
$upscope $end
$scope begin _gen[14] $end
$upscope $end
$scope begin _gen[15] $end
$upscope $end
$upscope $end
$upscope $end
$scope module clo_inst_z $end
$var wire 16 K bits [15:0] $end
$var wire 4 L leading_ones [3:0] $end
$var wire 4 M index_highest_set [3:0] $end
$scope module highest_set_inst $end
$var wire 16 N bits [15:0] $end
$var wire 4 O index [3:0] $end
$scope begin _gen[0] $end
$upscope $end
$scope begin _gen[1] $end
$upscope $end
$scope begin _gen[2] $end
$upscope $end
$scope begin _gen[3] $end
$upscope $end
$scope begin _gen[4] $end
$upscope $end
$scope begin _gen[5] $end
$upscope $end
$scope begin _gen[6] $end
$upscope $end
$scope begin _gen[7] $end
$upscope $end
$scope begin _gen[8] $end
$upscope $end
$scope begin _gen[9] $end
$upscope $end
$scope begin _gen[10] $end
$upscope $end
$scope begin _gen[11] $end
$upscope $end
$scope begin _gen[12] $end
$upscope $end
$scope begin _gen[13] $end
$upscope $end
$scope begin _gen[14] $end
$upscope $end
$scope begin _gen[15] $end
$upscope $end
$upscope $end
$upscope $end
$upscope $end
$upscope $end
$enddefinitions $end
#0
$dumpvars
b1110 O
b1000011100100100 N
b1110 M
b1 L
b1000011100100100 K
b1111 J
b111100011011010 I
b1111 H
b0 G
b111100011011010 F
b11111 E
b11111 D
b0 C
b1 B
b110001101101 A
b1100 @
b10 ?
b11110001101101 >
b11110001101101 =
bx <
bx ;
b1 :
09
08
b10 7
b1100 6
b110001101101 5
04
b11111 3
02
01
10
0/
0.
0-
0,
0+
0*
b11110001101101 )
1(
0'
0&
b11111 %
b110001101101 $
b10 #
0"
0!
$end
#10
0.
b0 %
b0 D
b0 B
b0 L
b1 C
b1 G
b1111 M
b1111 O
b1100 @
b1110 H
b1110 J
b10 #
b10 ?
0(
b110010010110110 K
b110010010110110 N
1"
b1001101101001000 F
b1001101101001000 I
0/
0-
0*
b0 E
b110110100100 $
b110110100100 A
b100110110100100 >
b110110100100 5
00
b0 3
18
b100110110100100 )
b100110110100100 =
b10 :
#20
b11110 %
b11110 D
b10 B
b10 L
b0 C
b0 G
b1101 M
b1101 O
b1011 @
b1111 H
b1111 J
b11 #
b11 ?
1(
b1100101100101100 K
b1100101100101100 N
0"
b11010011010010 F
b11010011010010 I
0/
0-
0.
0*
b11110 E
b1001101001 $
b1001101001 A
b1101001101001 >
b1011 6
b1001101001 5
10
b11110 3
b11 7
08
b1101001101001 )
b1101001101001 =
b11 :
#30
b0 B
b0 L
b1 C
b1 G
b1111 M
b1111 O
b1100 @
b1110 H
b1110 J
b0 %
b0 D
b10 #
b10 ?
0(
1"
b111000101000000 K
b111000101000000 N
b1000111010111110 F
b1000111010111110 I
0/
0-
0.
0*
1!
b0 E
b11101011111 $
b11101011111 A
b100011101011111 >
b1100 6
b11101011111 5
00
b0 3
b10 7
18
19
b1011100010100001 )
b1011100010100001 =
b100 :
#40
b1011 @
b11 #
b11 ?
b1 %
b1 D
b10 C
b10 G
b1101 H
b1101 J
b11010100110110 K
b11010100110110 N
b1100101011001000 F
b1100101011001000 I
b10101100100 $
b10101100100 A
b110010101100100 >
0/
0-
0.
0!
b1 E
b1011 6
b10101100100 5
14
b1 3
b11 7
09
b110010101100100 )
b110010101100100 =
b101 :
#50
b1001 @
b101 #
b101 ?
b11 %
b11 D
b100 C
b100 G
b1011 H
b1011 J
1(
b101011010000 K
b101011010000 N
b1111010100101110 F
b1111010100101110 I
0/
0-
0.
0*
b11 E
b10010111 $
b10010111 A
b111101010010111 >
b1001 6
b10010111 5
10
b11 3
b101 7
b111101010010111 )
b111101010010111 =
b110 :
#60
b1 B
b1 L
0(
b0 C
b0 G
b1110 M
b1110 O
b1100 @
b1111 H
b1111 J
b11111 %
b11111 D
b10 #
b10 ?
b1011000010100110 K
b1011000010100110 N
0"
b100111101011000 F
b100111101011000 I
0/
0-
0.
0*
b11111 E
b11110101100 $
b11110101100 A
b10011110101100 >
b1100 6
b11110101100 5
00
04
b11111 3
b10 7
08
b10011110101100 )
b10011110101100 =
b111 :
#70
0.
b1011 @
b11 #
b11 ?
b11110 %
b11110 D
b10 B
b10 L
b1101 M
b1101 O
0*
0(
b1101000111011110 K
b1101000111011110 N
b10111000100000 F
b10111000100000 I
0/
0-
b11110 E
b11100010000 $
b11100010000 A
b1011100010000 >
b1011 6
b11100010000 5
b11110 3
b11 7
b1011100010000 )
b1011100010000 =
b1000 :
#80
b1101110111110000 K
b1101110111110000 N
b10001000001110 F
b10001000001110 I
b1000100000111 E
b100000111 $
b100000111 A
b1000100000111 >
b100000111 5
b1000100000111 )
b1000100000111 =
b1001 :
#90
b11110 @
b10000 #
b10000 ?
b10001 %
b10001 D
b1111 B
b1111 L
b0 M
b0 O
b1111111111111110 K
b1111111111111110 N
b0 F
b0 I
x/
x-
b10001 E
b0 $
b0 A
b0 >
12
b0x 6
b0 5
bx 3
bx 7
x8
1&
b0 )
b0 =
b1010 :
#100
0/
0-
0*
0(
b11011001110 $
b11011001110 A
b0 B
b0 L
b10 C
b10 G
b1111 M
b1111 O
b1011 @
b1101 H
b1101 J
b1 %
b1 D
b11 #
b11 ?
b11001001100010 K
b11001001100010 N
1"
b1100110110011100 F
b1100110110011100 I
0.
b1 E
b110011011001110 >
02
b1011 6
b11011001110 5
14
b1 3
b11 7
18
0&
b110011011001110 )
b110011011001110 =
b1011 :
#110
b0 B
b0 L
b11 C
b11 G
b1111 M
b1111 O
b1010 @
b1100 H
b1100 J
b10 %
b10 D
b100 #
b100 ?
0*
0(
b1100101001000 K
b1100101001000 N
1"
b1110011010110110 F
b1110011010110110 I
0/
0-
0.
1!
b10 E
b1101011011 $
b1101011011 A
b111001101011011 >
b1010 6
b1101011011 5
b10 3
b100 7
19
b1000110010100101 )
b1000110010100101 =
b1100 :
#120
b1111 B
b1111 L
b0 C
b0 G
b0 M
b0 O
b11110 @
b1111 H
b1111 J
b10001 %
b10001 D
b10000 #
b10000 ?
b1111111111111110 K
b1111111111111110 N
0"
b0 F
b0 I
b0 $
b0 A
b1000000000000000 >
x/
x-
0.
b10001 E
11
b0x 6
b0 5
bx 3
bx 7
x8
1'
b1000000000000000 )
b1000000000000000 =
b1101 :
#130
0/
0-
b101000010100 $
b101000010100 A
b0 B
b0 L
b1 C
b1 G
b1111 M
b1111 O
b1100 @
b1110 H
b1110 J
b0 %
b0 D
b10 #
b10 ?
b110101111010110 K
b110101111010110 N
1"
b1001010000101000 F
b1001010000101000 I
b100101000010100 >
0.
0!
b0 E
01
b1100 6
b101000010100 5
04
b0 3
b10 7
18
09
0'
b100101000010100 )
b100101000010100 =
b1110 :
#140
b11111 %
b11111 D
b1 B
b1 L
b0 C
b0 G
b1110 M
b1110 O
b1100 @
b1111 H
b1111 J
b10 #
b10 ?
1(
0"
b1001100111010010 K
b1001100111010010 N
b110011000101100 F
b110011000101100 I
0/
0-
0.
0*
1!
b11111 E
b1100010110 $
b1100010110 A
b11001100010110 >
b1100010110 5
10
b11111 3
08
19
b1100110011101010 )
b1100110011101010 =
b1111 :
#150
b1000 @
b110 #
b110 ?
b11011 %
b11011 D
b101 B
b101 L
b1010 M
b1010 O
0(
b1111101011100010 K
b1111101011100010 N
b10100011100 F
b10100011100 I
b10001110 $
b10001110 A
b1010001110 >
0/
0-
0.
0*
b11011 E
b1000 6
b10001110 5
00
b11011 3
b110 7
b1111110101110010 )
b1111110101110010 =
b10000 :
#160
1(
b1100 @
b10 #
b10 ?
b11111 %
b11111 D
b1 B
b1 L
b1110 M
b1110 O
b1000011111000000 K
b1000011111000000 N
b111100000111110 F
b111100000111110 I
b110000011111 $
b110000011111 A
b11110000011111 >
0/
0-
0.
0*
b11111 E
b1100 6
b110000011111 5
10
b11111 3
b10 7
b1100001111100001 )
b1100001111100001 =
b10001 :
#170
b1010 @
b100 #
b100 ?
b11101 %
b11101 D
b11 B
b11 L
b1100 M
b1100 O
0*
1(
b1110000111011110 K
b1110000111011110 N
b1111000100000 F
b1111000100000 I
b1100010000 $
b1100010000 A
b111100010000 >
0/
0-
0.
0!
b11101 E
b1010 6
b1100010000 5
b11101 3
b100 7
09
b111100010000 )
b111100010000 =
b10010 :
#180
b1100 @
b10 #
b10 ?
b11111 %
b11111 D
b1 B
b1 L
b1110 M
b1110 O
0*
1(
b1000111001011110 K
b1000111001011110 N
b111000110100000 F
b111000110100000 I
0/
0-
0.
b11111 E
b100011010000 $
b100011010000 A
b11100011010000 >
b1100 6
b100011010000 5
b11111 3
b10 7
b11100011010000 )
b11100011010000 =
b10011 :
#190
b11 %
b11 D
b0 B
b0 L
b100 C
b100 G
b1111 M
b1111 O
b1001 @
b1011 H
b1011 J
b101 #
b101 ?
1"
0*
1(
b101001100110 K
b101001100110 N
b1111010110011000 F
b1111010110011000 I
0/
0-
0.
1!
b11 E
b11001100 $
b11001100 A
b111101011001100 >
b1001 6
b11001100 5
14
b11 3
b101 7
18
19
b1000010100110100 )
b1000010100110100 =
b10100 :
#200
b1010 @
b100 #
b100 ?
b10 %
b10 D
b11 C
b11 G
b1100 H
b1100 J
b1001011000100 K
b1001011000100 N
b1110110100111010 F
b1110110100111010 I
b1010011101 $
b1010011101 A
b111011010011101 >
0/
0-
0.
b10 E
b1010 6
b1010011101 5
b10 3
b100 7
b1000100101100011 )
b1000100101100011 =
b10101 :
#210
b1100 @
b10 #
b10 ?
b0 %
b0 D
b1 C
b1 G
b1110 H
b1110 J
b100011110001100 K
b100011110001100 N
b1011100001110010 F
b1011100001110010 I
b110000111001 $
b110000111001 A
b101110000111001 >
0/
0-
0.
0!
b0 E
b1100 6
b110000111001 5
04
b0 3
b10 7
09
b101110000111001 )
b101110000111001 =
b10110 :
#220
0(
b111001001010110 K
b111001001010110 N
b1000110110101000 F
b1000110110101000 I
0/
0*
b100011011010100 E
b11011010100 $
b11011010100 A
b100011011010100 >
b11011010100 5
00
b100011011010100 )
b100011011010100 =
b10111 :
#230
b11111 %
b11111 D
b1 B
b1 L
b0 C
b0 G
b1110 M
b1110 O
b1100 @
b1111 H
b1111 J
b10 #
b10 ?
1(
0"
b1000111100111000 K
b1000111100111000 N
b111000011000110 F
b111000011000110 I
0/
0-
0.
0*
1!
b11111 E
b100001100011 $
b100001100011 A
b11100001100011 >
b100001100011 5
10
b11111 3
08
19
b1100011110011101 )
b1100011110011101 =
b11000 :
#240
0(
b1010011110011000 K
b1010011110011000 N
b101100001100110 F
b101100001100110 I
b110000110011 $
b110000110011 A
b10110000110011 >
0/
0.
0*
0!
b10110000110011 E
b110000110011 5
00
09
b10110000110011 )
b10110000110011 =
b11001 :
#250
0-
b11111 %
b11111 D
b1 B
b1 L
b0 C
b0 G
b1110 M
b1110 O
b1100 @
b1111 H
b1111 J
b10 #
b10 ?
0*
0(
b1010011101011000 K
b1010011101011000 N
0"
b101100010100110 F
b101100010100110 I
0/
0.
1!
b11111 E
b110001010011 $
b110001010011 A
b10110001010011 >
b110001010011 5
19
b1101001110101101 )
b1101001110101101 =
b11010 :
#260
b1011 @
b11 #
b11 ?
b11110 %
b11110 D
b10 B
b10 L
b1101 M
b1101 O
1(
b1100100110100010 K
b1100100110100010 N
b11011001011100 F
b11011001011100 I
b1100101110 $
b1100101110 A
b1101100101110 >
0/
0-
0.
0*
0!
b11110 E
b1011 6
b1100101110 5
10
b11110 3
b11 7
09
b1101100101110 )
b1101100101110 =
b11011 :
#270
b0 B
b0 L
b1 C
b1 G
b1111 M
b1111 O
b1100 @
b1110 H
b1110 J
b0 %
b0 D
b10 #
b10 ?
0(
b111100111111110 K
b111100111111110 N
1"
b1000011000000000 F
b1000011000000000 I
0/
0-
0*
b0 E
b1100000000 $
b1100000000 A
b100001100000000 >
b1100 6
b1100000000 5
00
b0 3
b10 7
18
b100001100000000 )
b100001100000000 =
b11100 :
#280
b11111 %
b11111 D
b1 B
b1 L
0.
b0 C
b0 G
b1110 M
b1110 O
b1100 @
b1111 H
b1111 J
b10 #
b10 ?
1(
b1001001000111010 K
b1001001000111010 N
0"
b110110111000100 F
b110110111000100 I
0/
0-
0*
b11111 E
b11011100010 $
b11011100010 A
b11011011100010 >
b11011100010 5
10
b11111 3
08
b11011011100010 )
b11011011100010 =
b11101 :
#290
b11101 %
b11101 D
b11 B
b11 L
b0 C
b0 G
b1100 M
b1100 O
0*
b1010 @
b1111 H
b1111 J
1(
b100 #
b100 ?
b1110001011001000 K
b1110001011001000 N
0"
b1110100110110 F
b1110100110110 I
0/
0-
0.
1!
b11101 E
b1010011011 $
b1010011011 A
b111010011011 >
b1010 6
b1010011011 5
b11101 3
b100 7
19
b1111000101100101 )
b1111000101100101 =
b11110 :
#300
b1011 @
b11 #
b11 ?
b11110 %
b11110 D
b10 B
b10 L
b1101 M
b1101 O
0(
b1101101011011100 K
b1101101011011100 N
b10010100100010 F
b10010100100010 I
b1010010001 $
b1010010001 A
b1001010010001 >
0/
0-
0.
0*
b11110 E
b1011 6
b1010010001 5
00
b11110 3
b11 7
b1110110101101111 )
b1110110101101111 =
b11111 :
#310
1(
b1001 @
b101 #
b101 ?
b11100 %
b11100 D
b100 B
b100 L
b1011 M
b1011 O
b1111001011011110 K
b1111001011011110 N
b110100100000 F
b110100100000 I
b10010000 $
b10010000 A
b11010010000 >
0/
0-
0.
0*
0!
b11100 E
b1001 6
b10010000 5
10
b11100 3
b101 7
09
b11010010000 )
b11010010000 =
b100000 :
#320
b1 B
b1 L
b0 C
b0 G
b1110 M
b1110 O
b1100 @
b1111 H
b1111 J
b11111 %
b11111 D
b10 #
b10 ?
0(
b1010100001100110 K
b1010100001100110 N
0"
b101011110011000 F
b101011110011000 I
0/
0-
0.
0*
1!
b11111 E
b101111001100 $
b101111001100 A
b10101111001100 >
b1100 6
b101111001100 5
00
b11111 3
b10 7
19
b1101010000110100 )
b1101010000110100 =
b100001 :
#330
b0 %
b0 D
b0 B
b0 L
b1 C
b1 G
b1111 M
b1111 O
b1100 @
b1110 H
b1110 J
b10 #
b10 ?
1(
b100100000000110 K
b100100000000110 N
1"
b1011011111111000 F
b1011011111111000 I
b101111111100 $
b101111111100 A
b101101111111100 >
0/
0-
0.
0*
b0 E
b101111111100 5
10
b0 3
18
b1010010000000100 )
b1010010000000100 =
b100010 :
#340
0*
1(
b11111 %
b11111 D
b1 B
b1 L
b0 C
b0 G
b1110 M
b1110 O
b1100 @
b1111 H
b1111 J
b10 #
b10 ?
b1001110011111110 K
b1001110011111110 N
0"
b110001100000000 F
b110001100000000 I
b110000000 $
b110000000 A
b11000110000000 >
0/
0-
0.
b11111 E
b110000000 5
b11111 3
08
b1100111010000000 )
b1100111010000000 =
b100011 :
