src/highest_set.sv
/*

Description:
    [FIX:outdated] Given a sequence of bits returns the highest index of said bits such that the bit is `VAL`.
    e.g.:
        bits = 8b00001001 -> 3

Usage:
    cd $PROJECT_ROOT/waveforms
    iverilog -g2012 -DN=8 -DHIGHEST_SET_TB -o highest_set.out ../src/highest_set.sv ../src/utils.sv && ./highest_set.out

    sv2v -DN=8 ../src/highest_set.sv ../src/utils.sv > highest_set.v

    ~/Documents/dev/yosys/yosys0.9_1979e0b1f -DN=16 -p "synth_intel -family max10 -top highest_set_v1b -vqm highest_set.vqm" ../src/highest_set.sv > yosys_intel_highest_set_v1.out
    yosys -p "synth_intel -family max10 -top highest_set_v2 -vqm highest_set.vqm" ../src/highest_set.sv > yosys_intel_highest_set_v2.out
*/


/**
 *  `highest_set_v1` requires less LE than `highest_set_v3` but longer path (O(size) growth)
 */


module highest_set_v1 #(
        parameter N = `N,
        parameter VAL = 1
    )(
        input logic[N-1:0] bits,
        output wire [$clog2(N)-1:0] index
    );
    
    wire [S-1:0] out_stage [0:N];
    assign out_stage[0] = {S{1'b1}}; // desired default output if no bits set

    generate genvar i;
        for (i=0; i<N; i=i+1) begin: _gen
            assign out_stage[i+1] = (bits[i] == VAL) ? i : out_stage[i]; 
        end
    endgenerate

    assign index = out_stage[N];
endmodule

module highest_set_v1b #(
        parameter SIZE = 2
    )(
        input logic[SIZE-1:0] bits,
        input val,
        output wire [$clog2(SIZE)-1:0] index
    );
    
    wire [$clog2(SIZE)-1:0] out_stage [0:SIZE];
    assign out_stage[0] = ~0; // desired default output if no bits set

    generate genvar i;
        for (i=0; i<SIZE; i=i+1) begin: _gen
            assign out_stage[i+1] = (bits[i] == val) ? i : out_stage[i]; 
        end
    endgenerate

    assign index = out_stage[SIZE];
endmodule






/*
ref: http://www.ece.ualberta.ca/~jhan8/publications/1570528628.pdf
*/
module highest_set_v2 #(
        parameter N = `N,
        parameter VAL = 1
    )(
        input logic [N-1:0] bits,
        output wire [N-1:0] index_bit,
        output wire [$clog2(N)-1:0] index
    );

    wire [N-1:0] _wire;
    
    generate genvar i;
        for (i=0; i<N-1; i=i+1) begin
            mux mux_inst (
                .a      (_wire[i+1]),
                .sel    (bits[i+1]),
                .and_in (bits[i]),
                .mux_out(_wire[i]),
                .and_out(index_bit[i])
            );
        end
    endgenerate

    assign _wire[N-1] = 1;
    assign index_bit[N-1] = bits[N-1];

    /// assign index = $clog2(index_bit); //// achtung, fails to synthesize.

    decoder #(
        .N(N)
    ) decoder_inst (
        .in(index_bit),
        .out(index)
    );
endmodule

module decoder #(
        parameter N = `N
    )(
        input [N-1:0] in,
        output [$clog2(N)-1:0] out
    );
    
    generate genvar i;
        for (i=0; i<N; i=i+1) begin
            assign out = in == (1 << i) ? i : 'bz;
        end
    endgenerate
endmodule

/**
 * mux + and gate actually. 
 * only instantiated by `highest_set_v2`. maybe unnecessary later on.
 */
module mux (
        input a,
        /* input b, */
        input sel,
        input and_in,
        output mux_out,
        output and_out
    );
    wire b = 0;
    assign mux_out = sel == 0 ? a : b;
    assign and_out = and_in & mux_out; 
endmodule





/**
 *  `highest_set_v3` requires more LE than `highest_set_v1` but shorter path (O(1))
 */
module highest_set_v3 #(
        parameter N = `N,
        parameter VAL = 1
    )(
        input logic [N-1:0] bits,
        output wire [N-1:0] index_bit,
        output wire [$clog2(N)-1:0] index
    );

    wire [N-1:0] bits_reversed;
    wire [N-1:0] _index_bit_tmp;

    genvar i;
    generate
        for (i=0; i<N; i=i+1) begin: _gen1
            assign bits_reversed[i] = bits[N-1-i];
        end
    endgenerate
    
    
    /// detect the rightmost bit-set index: 10'b0011001000 
    ///                                               ^
    ///                                  -> 10'b0000001000
    assign _index_bit_tmp = bits_reversed & c2(bits_reversed);

    generate
        for (i=0; i<N; i=i+1) begin: _gen2
            assign index_bit[i] = _index_bit_tmp[N-1-i];
        end
    endgenerate

endmodule


`ifdef HIGHEST_SET_TB
module tb_highest_set;
    parameter VAL = 1;

    reg [N-1:0] posit;
    wire [S-1:0] index_v1, index_v1b, index_v2, index_v3;
    wire [N-1:0] index_bit_v3;

    reg diff;

    highest_set_v1 #(
        .N      (N),
        .VAL    (VAL)
    )
    highest_set_inst1 (
        .bits   (posit),
        .index  (index_v1)
    );

    highest_set_v1b #(
        .N      (N)
    )
    highest_set_inst1b (
        .bits   (posit),
        .val    (1'b1),
        .index  (index_v1b)
    );

    highest_set_v2 #(
        .N      (N),
        .VAL    (VAL)
    )
    highest_set_inst2 (
        .bits   (posit),
        .index  (index_v2)
    );

    highest_set_v3 #(
        .N      (N),
        .VAL    (VAL)
    )
    highest_set_inst3 (
        .bits   (posit),
        .index_bit (index_bit_v3),
        .index  (index_v3)
    );

    always @(*) begin
        diff = index_v1 == index_v2 ? 0 : 1'bx;
    end

    initial begin
        $dumpfile("tb_highest_set.vcd");
        $dumpvars(0, tb_highest_set);

                posit = 8'b0000_0001;
        #10     posit = 8'b0000_0011;
        #10     posit = 8'b0000_1000;
        #10     posit = 8'b0011_0000;
        #10     posit = 8'b0101_0101;
        #10     posit = 8'b1100_0000;
        #10     posit = 8'b1111_1111;

        #10;
        $finish;
    end
endmodule
`endif

src/cls.sv
/*

Description:
    cls: count leading ones.
    It wraps the `highest_set` module; returns the number of ones starting from the left:

    e.g:
        bits = 0b11010000 -> 2
        bits = 0b01111000 -> 0
        bits = 0b11100000 -> 3

Usage:
    cd $PROJECT_ROOT/waveforms
    
    iverilog -DTEST_BENCH_CLS -o cls.out ../src/cls.sv ../src/highest_set.sv && ./cls.out
*/


module cls #(
        parameter N = 8,
        parameter S = $clog2(N)
    )(
        input [N-1:0] bits,
        output [S-1:0] leading_ones,
        output [S-1:0] index_highest_set
    );

    highest_set_v1 #(
        .SIZE   (N),
        .VAL    (0)
    )
    highest_set_inst(
        .bits   (bits),
        .index  (index_highest_set)
    );

    assign leading_ones = (N - 1) - index_highest_set;
endmodule




`ifdef TEST_BENCH_CLS
module tb_cls;

    parameter N = 8;
    parameter S = $clog2(N);

    reg [N-1:0] bits;
    wire [S-1:0] leading_ones, leading_zeros;
    wire [S-1:0] index_highest_set_1, index_highest_set_2;

    /* count leading set (ones) */
    cls #(
        .N              (N),
        .S              (S)
    ) count_leading_ones (
        .bits           (bits),
        .leading_ones   (leading_ones),
        .index_highest_set(index_highest_set_1)
    );

    /* count leading set (zeros), inputs bits are flipped */
    cls #(
        .N              (N),
        .S              (S)
    ) count_leading_zeros (
        .bits           (~bits),
        .leading_ones   (leading_zeros),
        .index_highest_set(index_highest_set_2)
    );



    initial begin
        $dumpfile("tb_cls.vcd");
        $dumpvars(0, tb_cls);

                bits = 8'b0000_0001;
        #10     bits = 8'b1000_0011;
        #10     bits = 8'b1100_1000;
        #10     bits = 8'b0011_0000;
        #10     bits = 8'b0101_0101;
        #10     bits = 8'b1100_0000;
        #10     bits = 8'b1111_1110;

        #10;
        $finish;
    end

endmodule
`endif

src/posit_decode.sv
/*
Description:
    Posit decoder.

Usage:
    cd $PROJECT_ROOT/waveforms

    iverilog -DTEST_BENCH_DECODE -DNO_ES_FIELD -DN=8 -DES=0 -o posit_decode.out \
    ../src/posit_decode.sv \
    ../src/highest_set.sv \
    ../src/cls.sv \
    && ./posit_decode.out

    iverilog -DTEST_BENCH_DECODE               -DN=16 -DES=1 -o posit_decode.out \
    ../src/posit_decode.sv \
    ../src/highest_set.sv \
    ../src/cls.sv \
    && ./posit_decode.out

    iverilog -DTEST_BENCH_DECODE               -DN=32 -DES=2 -o posit_decode.out \
    ../src/posit_decode.sv \
    ../src/highest_set.sv \
    ../src/cls.sv \
    && ./posit_decode.out


    yosys -p "synth_intel -family max10 -top posit_decode -vqm posit_decode.vqm" \
    ../src/posit_decode.sv \
    ../src/highest_set.sv \
    ../src/cls.sv > yosys_posit_decode.out

*/
module posit_decode #(
        parameter N = 8,
        parameter S = $clog2(N),
        parameter ES = 0
    )(
        input [N-1:0]   bits,
        output          is_zero,
        output          is_inf,
        output          sign,
        output          reg_s,

        output [S:0]    reg_len,
        output [S:0]    k,
`ifndef NO_ES_FIELD
        output [ES-1:0] exp,
`endif
        output [N-1:0]  mant
    );

    function [N-1:0] c2(input [N-1:0] a);
        c2 = ~a + 1'b1;
    endfunction

    // function [N-1:0] min(input [N-1:0] a, b);
    //     min = a < b ? a : b;
    // endfunction

    assign is_zero = bits == {N{1'b0}};
    assign is_inf = bits == {1'b1, {N-1{1'b0}}};
    assign sign = bits[N-1];
    
    wire [N-1:0] u_bits;
    assign u_bits = sign == 0 ? bits : c2(bits);

    wire [S-1:0] leading_ones, leading_zeros;

    // regime sign
    assign reg_s = u_bits[N-2];

    assign k = reg_s == 1 ? leading_ones - 1 : c2(leading_zeros);
    
    assign reg_len = reg_s == 1 ? k + 2 : c2(k) + 1;

    // // not useful but anyway

`ifndef NO_ES_FIELD
    assign exp = (u_bits << (1 + reg_len)) >> (N - ES);
`endif

    wire [S:0] mant_len;
    assign mant_len = N - 1 - reg_len - ES;


    assign mant = (u_bits << (N - mant_len)) >> (N - mant_len);
    
    
    // count leading X
    cls #(
        .N(N),
        .S(S)
    ) clo_inst_o (
        .bits               (u_bits << 1), // strip sign bit and count ones from the left
        .leading_ones       (leading_ones),
        .index_highest_set  ()
    );
    cls #(
        .N(N),
        .S(S)
    ) clo_inst_z (
        .bits               (~u_bits << 1), // flip bits, strip sign bit and count zeros from the left
        .leading_ones       (leading_zeros),
        .index_highest_set  ()
    );

endmodule



`ifdef TEST_BENCH_DECODE
module tb_posit_decode;
    function [N-1:0] c2(input [N-1:0] a);
        c2 = ~a + 1'b1;
    endfunction
    function [N-1:0] abs(input [N-1:0] in);
        abs = in[N-1] == 0 ? in : c2(in);
    endfunction

`ifdef N
    parameter N = `N;
`else
    parameter N = 8;
`endif

    parameter S = $clog2(N);

`ifdef ES
    parameter ES = `ES;
`else
    parameter ES = 0;
`endif  

    /* input */
    reg [N-1:0]     bits;
    /* outputs */
    wire            is_zero;
    wire            is_inf;
    wire            sign;
    wire            reg_s;
    wire [S  :0]    reg_len;
    wire [S  :0]    k;
`ifndef NO_ES_FIELD
    wire [ES-1:0]   exp;
`endif
    wire [N-1:0]    mant;
    /*************************/

    reg sign_expected, reg_s_expected;
    reg [S  :0] reg_len_expected, k_expected;
    reg [ES-1:0] exp_expected;
    reg [N-1:0] mant_expected;
    reg [S-1:0] mant_len_expected;
    reg is_zero_expected, is_inf_expected;
    reg err;

    reg [N:0] test_no;

`ifndef NO_ES_FIELD
    reg diff_exp;
`endif    
    reg diff_k, diff_mant, diff_is_zero, diff_is_inf;
    
    reg k_is_pos;
    
    always @(*) begin
`ifndef NO_ES_FIELD
        diff_exp = (exp === exp_expected ? 0 : 'bx);
`endif
        diff_mant = (mant === mant_expected ? 0 : 'bx);
        diff_k = (k === k_expected ? 0 : 'bx);
        diff_is_zero = (is_zero === is_zero_expected ? 0 : 'bx);
        diff_is_inf = (is_inf === is_inf_expected ? 0 : 'bx);
        
        if (
            diff_mant == 0
`ifndef NO_ES_FIELD
            && diff_exp == 0 
`endif
            && diff_k == 0 
            && diff_is_zero == 0 
            && diff_is_inf == 0
        ) err = 0;
        else err = 1'bx;
    end

    posit_decode #(
        .N(N),
        .S(S),
        .ES(ES)
    ) posit_decode_inst (
        .bits           (bits),
        .is_zero        (is_zero),
        .is_inf         (is_inf),
        .sign           (sign),
        .reg_s          (reg_s),

        .reg_len        (reg_len),
        .k              (k),
`ifndef NO_ES_FIELD
        .exp            (exp),
`endif
        .mant           (mant)
    );

    initial begin
             if (N == 8 && ES == 0) $dumpfile("tb_posit_decode_P8E0.vcd");
        else if (N == 5 && ES == 1) $dumpfile("tb_posit_decode_P5E1.vcd");
        else if (N == 16 && ES == 1)$dumpfile("tb_posit_decode_P16E1.vcd");
        else if (N == 32 && ES == 2)$dumpfile("tb_posit_decode_P32E2.vcd");
        else                        $dumpfile("tb_posit_decode.vcd");

	    $dumpvars(0, tb_posit_decode);                        
            
        if (N == 8 && ES == 0) begin
            `include "../src/tb_posit_decode_P8E0.sv"
        end

        if (N == 5 && ES == 1) begin
            `include "../src/tb_posit_decode_P5E1.sv"
        end

        if (N == 16 && ES == 1) begin
            `include "../src/tb_posit_decode_P16E1.sv"
        end

        if (N == 32 && ES == 2) begin
            `include "../src/tb_posit_decode_P32E2.sv"
        end


        
        #10;
		$finish;
    end

endmodule
`endif

waveforms/tb_posit_decode_P32E2.vcd
$date
	Mon Dec 20 19:39:08 2021
$end
$version
	Icarus Verilog
$end
$timescale
	1s
$end
$scope module tb_posit_decode $end
$var wire 1 ! sign $end
$var wire 1 " reg_s $end
$var wire 6 # reg_len [5:0] $end
$var wire 32 $ mant [31:0] $end
$var wire 6 % k [5:0] $end
$var wire 1 & is_zero $end
$var wire 1 ' is_inf $end
$var wire 2 ( exp [1:0] $end
$var reg 32 ) bits [31:0] $end
$var reg 1 * diff_exp $end
$var reg 1 + diff_is_inf $end
$var reg 1 , diff_is_zero $end
$var reg 1 - diff_k $end
$var reg 1 . diff_mant $end
$var reg 1 / err $end
$var reg 2 0 exp_expected [1:0] $end
$var reg 1 1 is_inf_expected $end
$var reg 1 2 is_zero_expected $end
$var reg 6 3 k_expected [5:0] $end
$var reg 1 4 k_is_pos $end
$var reg 32 5 mant_expected [31:0] $end
$var reg 5 6 mant_len_expected [4:0] $end
$var reg 6 7 reg_len_expected [5:0] $end
$var reg 1 8 reg_s_expected $end
$var reg 1 9 sign_expected $end
$var reg 33 : test_no [32:0] $end
$scope function abs $end
$var reg 32 ; in [31:0] $end
$upscope $end
$scope function c2 $end
$var reg 32 < a [31:0] $end
$upscope $end
$scope module posit_decode_inst $end
$var wire 32 = bits [31:0] $end
$var wire 32 > u_bits [31:0] $end
$var wire 1 ! sign $end
$var wire 1 " reg_s $end
$var wire 6 ? reg_len [5:0] $end
$var wire 6 @ mant_len [5:0] $end
$var wire 32 A mant [31:0] $end
$var wire 5 B leading_zeros [4:0] $end
$var wire 5 C leading_ones [4:0] $end
$var wire 6 D k [5:0] $end
$var wire 1 & is_zero $end
$var wire 1 ' is_inf $end
$var wire 2 E exp [1:0] $end
$scope function c2 $end
$var reg 32 F a [31:0] $end
$upscope $end
$scope module clo_inst_o $end
$var wire 32 G bits [31:0] $end
$var wire 5 H leading_ones [4:0] $end
$var wire 5 I index_highest_set [4:0] $end
$scope module highest_set_inst $end
$var wire 32 J bits [31:0] $end
$var wire 5 K index [4:0] $end
$scope begin _gen[0] $end
$upscope $end
$scope begin _gen[1] $end
$upscope $end
$scope begin _gen[2] $end
$upscope $end
$scope begin _gen[3] $end
$upscope $end
$scope begin _gen[4] $end
$upscope $end
$scope begin _gen[5] $end
$upscope $end
$scope begin _gen[6] $end
$upscope $end
$scope begin _gen[7] $end
$upscope $end
$scope begin _gen[8] $end
$upscope $end
$scope begin _gen[9] $end
$upscope $end
$scope begin _gen[10] $end
$upscope $end
$scope begin _gen[11] $end
$upscope $end
$scope begin _gen[12] $end
$upscope $end
$scope begin _gen[13] $end
$upscope $end
$scope begin _gen[14] $end
$upscope $end
$scope begin _gen[15] $end
$upscope $end
$scope begin _gen[16] $end
$upscope $end
$scope begin _gen[17] $end
$upscope $end
$scope begin _gen[18] $end
$upscope $end
$scope begin _gen[19] $end
$upscope $end
$scope begin _gen[20] $end
$upscope $end
$scope begin _gen[21] $end
$upscope $end
$scope begin _gen[22] $end
$upscope $end
$scope begin _gen[23] $end
$upscope $end
$scope begin _gen[24] $end
$upscope $end
$scope begin _gen[25] $end
$upscope $end
$scope begin _gen[26] $end
$upscope $end
$scope begin _gen[27] $end
$upscope $end
$scope begin _gen[28] $end
$upscope $end
$scope begin _gen[29] $end
$upscope $end
$scope begin _gen[30] $end
$upscope $end
$scope begin _gen[31] $end
$upscope $end
$upscope $end
$upscope $end
$scope module clo_inst_z $end
$var wire 32 L bits [31:0] $end
$var wire 5 M leading_ones [4:0] $end
$var wire 5 N index_highest_set [4:0] $end
$scope module highest_set_inst $end
$var wire 32 O bits [31:0] $end
$var wire 5 P index [4:0] $end
$scope begin _gen[0] $end
$upscope $end
$scope begin _gen[1] $end
$upscope $end
$scope begin _gen[2] $end
$upscope $end
$scope begin _gen[3] $end
$upscope $end
$scope begin _gen[4] $end
$upscope $end
$scope begin _gen[5] $end
$upscope $end
$scope begin _gen[6] $end
$upscope $end
$scope begin _gen[7] $end
$upscope $end
$scope begin _gen[8] $end
$upscope $end
$scope begin _gen[9] $end
$upscope $end
$scope begin _gen[10] $end
$upscope $end
$scope begin _gen[11] $end
$upscope $end
$scope begin _gen[12] $end
$upscope $end
$scope begin _gen[13] $end
$upscope $end
$scope begin _gen[14] $end
$upscope $end
$scope begin _gen[15] $end
$upscope $end
$scope begin _gen[16] $end
$upscope $end
$scope begin _gen[17] $end
$upscope $end
$scope begin _gen[18] $end
$upscope $end
$scope begin _gen[19] $end
$upscope $end
$scope begin _gen[20] $end
$upscope $end
$scope begin _gen[21] $end
$upscope $end
$scope begin _gen[22] $end
$upscope $end
$scope begin _gen[23] $end
$upscope $end
$scope begin _gen[24] $end
$upscope $end
$scope begin _gen[25] $end
$upscope $end
$scope begin _gen[26] $end
$upscope $end
$scope begin _gen[27] $end
$upscope $end
$scope begin _gen[28] $end
$upscope $end
$scope begin _gen[29] $end
$upscope $end
$scope begin _gen[30] $end
$upscope $end
$scope begin _gen[31] $end
$upscope $end
$upscope $end
$upscope $end
$upscope $end
$upscope $end
$enddefinitions $end
#0
$dumpvars
b11110 P
b10000111001001001011010001010000 O
b11110 N
b1 M
b10000111001001001011010001010000 L
b11111 K
b1111000110110110100101110101110 J
b11111 I
b0 H
b1111000110110110100101110101110 G
b111111 F
b11 E
b111111 D
b0 C
b1 B
b100011011011010010111010111 A
b11011 @
b10 ?
b111100011011011010010111010111 >
b111100011011011010010111010111 =
bx <
bx ;
b1 :
09
08
b10 7
b11011 6
b100011011011010010111010111 5
04
b111111 3
02
01
b11 0
0/
0.
0-
0,
0+
0*
b111100011011011010010111010111 )
b11 (
0'
0&
b111111 %
b100011011011010010111010111 $
b10 #
0"
0!
$end
#10
b0 %
b0 D
b0 B
b0 M
0.
b1 C
b1 H
b11111 N
b11111 P
b11011 @
b11110 I
b11110 K
b10 #
b10 ?
b1 (
b1 E
b1100100101101100000110000000110 L
b1100100101101100000110000000110 O
1"
b10011011010010011111001111111000 G
b10011011010010011111001111111000 J
0/
0-
0*
b0 F
b101101001001111100111111100 $
b101101001001111100111111100 A
b1001101101001001111100111111100 >
b101101001001111100111111100 5
b1 0
b0 3
18
b1001101101001001111100111111100 )
b1001101101001001111100111111100 =
b10 :
#20
b111110 %
b111110 D
b10 B
b10 M
0.
b0 C
b0 H
b11101 N
b11101 P
b11010 @
b11111 I
b11111 K
b11 #
b11 ?
b10 (
b10 E
b11001011001011011101001001110000 L
b11001011001011011101001001110000 O
0"
b110100110100100010110110001110 G
b110100110100100010110110001110 J
0/
0-
0*
b111110 F
b10011010010001011011000111 $
b10011010010001011011000111 A
b11010011010010001011011000111 >
b11010 6
b10011010010001011011000111 5
b10 0
b111110 3
b11 7
08
b11010011010010001011011000111 )
b11010011010010001011011000111 =
b11 :
#30
b0 B
b0 M
b1 C
b1 H
b11111 N
b11111 P
b11011 @
b11110 I
b11110 K
b0 %
b0 D
b10 #
b10 ?
b0 (
b0 E
1"
b1110001010000110101011110011000 L
b1110001010000110101011110011000 O
b10001110101111001010100001100110 G
b10001110101111001010100001100110 J
0/
0-
0.
0*
1!
b0 F
b111010111100101010000110011 $
b111010111100101010000110011 A
b1000111010111100101010000110011 >
b11011 6
b111010111100101010000110011 5
b0 0
b0 3
b10 7
18
19
b10111000101000011010101111001101 )
b10111000101000011010101111001101 =
b100 :
#40
b1 (
b1 E
b11010 @
b11 #
b11 ?
b1 %
b1 D
b10 C
b10 H
b11101 I
b11101 K
b110101001101111101101010101100 L
b110101001101111101101010101100 O
b11001010110010000010010101010010 G
b11001010110010000010010101010010 J
b1011001000001001010101001 $
b1011001000001001010101001 A
b1100101011001000001001010101001 >
0/
0-
0.
0*
0!
b1 F
b11010 6
b1011001000001001010101001 5
b1 0
14
b1 3
b11 7
09
b1100101011001000001001010101001 )
b1100101011001000001001010101001 =
b101 :
#50
b11000 @
b101 #
b101 ?
b11 %
b11 D
b100 C
b100 H
b11011 I
b11011 K
b10 (
b10 E
b1010110100000111001101111000 L
b1010110100000111001101111000 O
b11110101001011111000110010000110 G
b11110101001011111000110010000110 J
0/
0-
0.
0*
b11 F
b100101111100011001000011 $
b100101111100011001000011 A
b1111010100101111100011001000011 >
b11000 6
b100101111100011001000011 5
b10 0
b11 3
b101 7
b1111010100101111100011001000011 )
b1111010100101111100011001000011 =
b110 :
#60
b1 B
b1 M
b0 C
b0 H
b11110 N
b11110 P
b11011 @
b11111 I
b11111 K
b111111 %
b111111 D
b10 #
b10 ?
b0 (
b0 E
b10110000101001110111100101001010 L
b10110000101001110111100101001010 O
0"
b1001111010110001000011010110100 G
b1001111010110001000011010110100 J
0/
0-
0.
0*
b111111 F
b111101011000100001101011010 $
b111101011000100001101011010 A
b100111101011000100001101011010 >
b11011 6
b111101011000100001101011010 5
b0 0
04
b111111 3
b10 7
08
b100111101011000100001101011010 )
b100111101011000100001101011010 =
b111 :
#70
b11010 @
b11 #
b11 ?
b111110 %
b111110 D
b10 B
b10 M
b11101 N
b11101 P
b1 (
b1 E
b11010001110111100110000101011000 L
b11010001110111100110000101011000 O
b101110001000011001111010100110 G
b101110001000011001111010100110 J
0/
0-
0.
0*
b111110 F
b11000100001100111101010011 $
b11000100001100111101010011 A
b10111000100001100111101010011 >
b11010 6
b11000100001100111101010011 5
b1 0
b111110 3
b11 7
b10111000100001100111101010011 )
b10111000100001100111101010011 =
b1000 :
#80
b0 (
b0 E
b11011101111100011011101110011100 L
b11011101111100011011101110011100 O
b100010000011100100010001100010 G
b100010000011100100010001100010 J
0/
0*
b10001000001110010001000110001 F
b1000001110010001000110001 $
b1000001110010001000110001 A
b10001000001110010001000110001 >
b1000001110010001000110001 5
b0 0
b10001000001110010001000110001 )
b10001000001110010001000110001 =
b1001 :
#90
b11000 @
b101 #
b101 ?
b111100 %
b111100 D
b100 B
b100 M
b11011 N
b11011 P
b1 (
b1 E
b11110101110110101000010111011000 L
b11110101110110101000010111011000 O
b1010001001010111101000100110 G
b1010001001010111101000100110 J
0/
0-
0.
0*
b111100 F
b100101011110100010011 $
b100101011110100010011 A
b101000100101011110100010011 >
b11000 6
b100101011110100010011 5
b1 0
b111100 3
b101 7
b101000100101011110100010011 )
b101000100101011110100010011 =
b1010 :
#100
b0 B
b0 M
b10 C
b10 H
b11111 N
b11111 P
b11010 @
b11101 I
b11101 K
b1 %
b1 D
b11 #
b11 ?
0*
b1 (
b1 E
b110010011000101010100110010010 L
b110010011000101010100110010010 O
1"
b11001101100111010101011001101100 G
b11001101100111010101011001101100 J
0/
0-
0.
b1 F
b10110011101010101100110110 $
b10110011101010101100110110 A
b1100110110011101010101100110110 >
b11010 6
b10110011101010101100110110 5
14
b1 3
b11 7
18
b1100110110011101010101100110110 )
b1100110110011101010101100110110 =
b1011 :
#110
b0 B
b0 M
b11 C
b11 H
b11111 N
b11111 P
b11001 @
b11100 I
b11100 K
b10 %
b10 D
b100 #
b100 ?
0*
b1 (
b1 E
b11001010010110011001011001010 L
b11001010010110011001011001010 O
1"
b11100110101101001100110100110100 G
b11100110101101001100110100110100 J
0/
0-
0.
1!
b10 F
b1010110100110011010011010 $
b1010110100110011010011010 A
b1110011010110100110011010011010 >
b11001 6
b1010110100110011010011010 5
b10 3
b100 7
19
b10001100101001011001100101100110 )
b10001100101001011001100101100110 =
b1100 :
#120
b10 B
b10 M
b0 C
b0 H
b11101 N
b11101 P
b11010 @
b11111 I
b11111 K
b111110 %
b111110 D
b11 #
b11 ?
0*
b1 (
b1 E
b11010101111111100011010000010000 L
b11010101111111100011010000010000 O
0"
b101010000000011100101111101110 G
b101010000000011100101111101110 J
b1000000001110010111110111 $
b1000000001110010111110111 A
b10101000000001110010111110111 >
0/
0-
0.
b111110 F
b11010 6
b1000000001110010111110111 5
04
b111110 3
b11 7
08
b11101010111111110001101000001001 )
b11101010111111110001101000001001 =
b1101 :
#130
b0 B
b0 M
b1 C
b1 H
b11111 N
b11111 P
b11011 @
b11110 I
b11110 K
b0 %
b0 D
b10 #
b10 ?
0*
b1 (
b1 E
b1101011110101101111000100101010 L
b1101011110101101111000100101010 O
1"
b10010100001010010000111011010100 G
b10010100001010010000111011010100 J
b10000101001000011101101010 $
b10000101001000011101101010 A
b1001010000101001000011101101010 >
0/
0-
0.
0!
b0 F
b11011 6
b10000101001000011101101010 5
b0 3
b10 7
18
09
b1001010000101001000011101101010 )
b1001010000101001000011101101010 =
b1110 :
#140
b100001 %
b100001 D
b100001 F
b11111 B
b11111 M
b0 C
b0 H
b0 N
b0 P
b111101 @
b11111 I
b11111 K
b100000 #
b100000 ?
b0 (
b0 E
b11111111111111111111111111111110 L
b11111111111111111111111111111110 O
0"
b0 G
b0 J
x/
x-
0*
b0 $
b0 A
b0 >
12
b0x 6
b0 5
b0 0
bx 3
bx 7
x8
1&
b0 )
b0 =
b1111 :
#150
0/
0-
b1 (
b1 E
b11011011101110101110 $
b11011011101110101110 A
b101 B
b101 M
b0 C
b0 H
b11010 N
b11010 P
b10111 @
b11111 I
b11111 K
b111011 %
b111011 D
b110 #
b110 ?
b11111010111001001000100010100010 L
b11111010111001001000100010100010 O
0"
b101000110110111011101011100 G
b101000110110111011101011100 J
0.
0*
1!
b111011 F
b10100011011011101110101110 >
02
b10111 6
b11011011101110101110 5
b1 0
b111011 3
b110 7
08
19
0&
b11111101011100100100010001010010 )
b11111101011100100100010001010010 =
b10000 :
#160
b11011 @
b10 #
b10 ?
b111111 %
b111111 D
b1 B
b1 M
b11110 N
b11110 P
b11 (
b11 E
b10000111110000110110010010101110 L
b10000111110000110110010010101110 O
b1111000001111001001101101010000 G
b1111000001111001001101101010000 J
b100000111100100110110101000 $
b100000111100100110110101000 A
b111100000111100100110110101000 >
0/
0-
0.
0*
b111111 F
b11011 6
b100000111100100110110101000 5
b11 0
b111111 3
b10 7
b11000011111000011011001001011000 )
b11000011111000011011001001011000 =
b10001 :
#170
b11001 @
b100 #
b100 ?
b111101 %
b111101 D
b11 B
b11 M
b11100 N
b11100 P
0*
b11 (
b11 E
b11100001110111101100110001110010 L
b11100001110111101100110001110010 O
b11110001000010011001110001100 G
b11110001000010011001110001100 J
b1000100001001100111000110 $
b1000100001001100111000110 A
b1111000100001001100111000110 >
0/
0-
0.
0!
b111101 F
b11001 6
b1000100001001100111000110 5
b111101 3
b100 7
09
b1111000100001001100111000110 )
b1111000100001001100111000110 =
b10010 :
#180
b11011 @
b10 #
b10 ?
b111111 %
b111111 D
b1 B
b1 M
b11110 N
b11110 P
0*
b11 (
b11 E
b10001110010111110110111000100110 L
b10001110010111110110111000100110 O
b1110001101000001001000111011000 G
b1110001101000001001000111011000 J
0/
0-
b111111 F
b110100000100100011101100 $
b110100000100100011101100 A
b111000110100000100100011101100 >
b11011 6
b110100000100100011101100 5
b111111 3
b10 7
b111000110100000100100011101100 )
b111000110100000100100011101100 =
b10011 :
#190
b111101 @
b100000 #
b100000 ?
b100001 %
b100001 D
b11111 B
b11111 M
b0 N
b0 P
b0 (
b0 E
b11111111111111111111111111111110 L
b11111111111111111111111111111110 O
b0 G
b0 J
x/
x-
0*
1!
b100001 F
b0 $
b0 A
b10000000000000000000000000000000 >
11
b0x 6
b0 5
b0 0
bx 3
bx 7
x8
19
1'
b10000000000000000000000000000000 )
b10000000000000000000000000000000 =
b10100 :
#200
0/
0-
b11 (
b11 E
b100111000010001110010010 $
b100111000010001110010010 A
b0 B
b0 M
b11 C
b11 H
b11111 N
b11111 P
b11001 @
b11100 I
b11100 K
b10 %
b10 D
b100 #
b100 ?
b10010110001111011100011011010 L
b10010110001111011100011011010 O
1"
b11101101001110000100011100100100 G
b11101101001110000100011100100100 J
b1110110100111000010001110010010 >
0.
0*
b10 F
01
b11001 6
b100111000010001110010010 5
b11 0
14
b10 3
b100 7
18
0'
b10001001011000111101110001101110 )
b10001001011000111101110001101110 =
b10101 :
#210
b11011 @
b10 #
b10 ?
b0 %
b0 D
b1 C
b1 H
b11110 I
b11110 K
0*
b11 (
b11 E
b1000111100011011111101010011000 L
b1000111100011011111101010011000 O
b10111000011100100000010101100110 G
b10111000011100100000010101100110 J
b100001110010000001010110011 $
b100001110010000001010110011 A
b1011100001110010000001010110011 >
0/
0-
0.
0!
b0 F
b11011 6
b100001110010000001010110011 5
04
b0 3
b10 7
09
b1011100001110010000001010110011 )
b1011100001110010000001010110011 =
b10110 :
#220
b0 (
b0 E
b1110010010101101010011100001010 L
b1110010010101101010011100001010 O
b10001101101010010101100011110100 G
b10001101101010010101100011110100 J
0/
0*
b1000110110101001010110001111010 F
b110110101001010110001111010 $
b110110101001010110001111010 A
b1000110110101001010110001111010 >
b110110101001010110001111010 5
b0 0
b1000110110101001010110001111010 )
b1000110110101001010110001111010 =
b10111 :
#230
b111111 %
b111111 D
b1 B
b1 M
b0 C
b0 H
b11110 N
b11110 P
b11011 @
b11111 I
b11111 K
b10 #
b10 ?
b11 (
b11 E
0"
b10001111001110101100111100100100 L
b10001111001110101100111100100100 O
b1110000110001010011000011011010 G
b1110000110001010011000011011010 J
0/
0-
0.
0*
1!
b111111 F
b11000101001100001101101 $
b11000101001100001101101 A
b111000011000101001100001101101 >
b11000101001100001101101 5
b11 0
b111111 3
08
19
b11000111100111010110011110010011 )
b11000111100111010110011110010011 =
b11000 :
