src/posit_encode.sv
/*

Description:
    Posit encoder.

Usage:
    cd $PROJECT_ROOT/waveforms
    
    iverilog -DTEST_BENCH_ENCODE -o posit_encode.out ../src/posit_encode.sv && ./posit_encode.out

    yosys -p "synth_intel -family max10 -top posit_encode -vqm posit_encode.vqm" ../src/posit_encode.sv > yosys_posit_encode.out

*/
module posit_encode #(
        parameter N = 8,
        parameter S = $clog2(N),
        parameter ES = 0
    )(
        input          is_zero,
        input          is_inf,
        input          sign,
        input          reg_s,
        input [N-1:0]  regime_bits,
        input [S-1:0]  reg_len,
        input [N-1:0]  k,
        input [ES-1:0] exp,
        input [N-1:0]  mant,
        output [N-1:0] posit
    );
    
    function [N-1:0] c2(input [N-1:0] a);
        c2 = ~a + 1'b1;
    endfunction
    
    function [N-1:0] shl (
            input [N-1:0] bits,
            input [N-1:0] rhs
        );
        shl = rhs > 0 ? bits << rhs : bits;
    endfunction

    wire [N-1:0] bits, bits_assembled;
    assign bits_assembled = ( 
          shl(sign, N-1)
        + shl(regime_bits, N-1-reg_len)
        + shl(exp, N-1-reg_len-ES)
        + mant
    );

    assign bits = 
        sign == 0 ? bits_assembled : 
                    c2(bits_assembled & ~(1 << (N-1)));

    /*
    ~(1'b1 << (N-1)) === {1'b0, {N-1{1'b1}}}
    */

    assign posit = 
        is_zero === 1 ? 0 : 
        is_inf  === 1 ? (1 << (N-1)) :
                        bits;
            /*  ^^^ 3 equal signs needed to compare against 1'bx, 
                otherwise if `is_zero` or `is_inf` == 1'bx, also 
                `posit` would be 'bX, regardless. */
endmodule


`ifdef TEST_BENCH_ENCODE 

// defaulted to P<8,0> unless specified via some `-D`efine.

module tb_posit_encode;
    function [N-1:0] c2(input [N-1:0] a);
        c2 = ~a + 1'b1;
    endfunction
    function [N-1:0] abs(input [N-1:0] in);
        abs = in[N-1] == 0 ? in : c2(in);
    endfunction

`ifdef N
    parameter N = `N;
`else
    parameter N = 8;
`endif

    parameter S = $clog2(N);

`ifdef ES
    parameter ES = `ES;
`else
    parameter ES = 0;
`endif

    reg            is_zero;
    reg            is_inf;
    reg            sign;
    reg            reg_s;
    reg [N-1:0]    regime_bits;
    reg [S-1:0]    reg_len;
    reg [N-1:0]    k;
    reg [ES-1:0]   exp;
    reg [N-1:0]    mant;
    wire [N-1:0]   posit;

    reg [N-1:0]   posit_expected;
    reg err;

    posit_encode #(
        .N(N),
        .S(S),
        .ES(ES)
    ) posit_encode_inst (
        .is_zero        (is_zero),
        .is_inf         (is_inf),
        .sign           (sign),
        .reg_s          (reg_s),
        .regime_bits    (regime_bits),
        .reg_len        (reg_len),
        .k              (k),
        .exp            (exp),
        .mant           (mant),
        .posit          (posit)
    );

    always @(*) begin
        err = posit == posit_expected ? 0 : 1'bx;
    end

    initial begin
             if (N == 8 && ES == 0) $dumpfile("tb_posit_encode_P8E0.vcd");
        else if (N == 5 && ES == 1) $dumpfile("tb_posit_encode_P5E1.vcd");
        else                        $dumpfile("tb_posit_encode.vcd");

	    $dumpvars(0, tb_posit_encode);                        
            
        if (N == 8 && ES == 0) begin
            `include "../src/tb_posit_encode_P8E0.sv"
        end
       

        #10;
		$finish;
    end

endmodule
`endif

waveforms/tb_posit_encode_P8E0.vcd
$date
	Sat Dec 18 19:23:51 2021
$end
$version
	Icarus Verilog
$end
$timescale
	1s
$end
$scope module tb_posit_encode $end
$var wire 8 ! posit [7:0] $end
$var reg 1 " err $end
$var reg 2 # exp [-1:0] $end
$var reg 1 $ is_inf $end
$var reg 1 % is_zero $end
$var reg 8 & k [7:0] $end
$var reg 8 ' mant [7:0] $end
$var reg 8 ( posit_expected [7:0] $end
$var reg 3 ) reg_len [2:0] $end
$var reg 1 * reg_s $end
$var reg 8 + regime_bits [7:0] $end
$var reg 1 , sign $end
$scope function abs $end
$var reg 8 - in [7:0] $end
$upscope $end
$scope function c2 $end
$var reg 8 . a [7:0] $end
$upscope $end
$scope module posit_encode_inst $end
$var wire 2 / exp [-1:0] $end
$var wire 1 $ is_inf $end
$var wire 1 % is_zero $end
$var wire 8 0 k [7:0] $end
$var wire 8 1 mant [7:0] $end
$var wire 3 2 reg_len [2:0] $end
$var wire 1 * reg_s $end
$var wire 8 3 regime_bits [7:0] $end
$var wire 1 , sign $end
$var wire 8 4 posit [7:0] $end
$var wire 8 5 bits_assembled [7:0] $end
$var wire 8 6 bits [7:0] $end
$scope function c2 $end
$var reg 8 7 a [7:0] $end
$upscope $end
$scope function shl $end
$var reg 8 8 bits [7:0] $end
$var reg 8 9 rhs [7:0] $end
$upscope $end
$upscope $end
$upscope $end
$enddefinitions $end
#0
$dumpvars
b100 9
b110 8
b1100010 7
b1100010 6
b1100010 5
b1100010 4
b110 3
b11 2
b10 1
bx 0
b0 /
bx .
bx -
0,
b110 +
1*
b11 )
b1100010 (
b10 '
bx &
0%
0$
b0 #
0"
b1100010 !
$end
#10
b110100 !
b110100 4
b110100 7
0"
b110100 6
b101 9
b0 8
b110100 (
b110100 5
b10100 '
b10100 1
b1 +
b1 3
b10 )
b10 2
0*
#20
b1110111 !
b1110111 4
b1110111 7
0"
b1110111 6
b11 9
b0 8
b1110111 (
b1110111 5
b111 '
b111 1
b1110 +
b1110 3
b100 )
b100 2
1*
#30
b11011100 !
b11011100 4
b100100 7
0"
b101 9
b0 8
b11011100 6
b11011100 (
b10100100 5
b100 '
b100 1
b1 +
b1 3
b10 )
b10 2
0*
1,
#40
b11110111 !
b11110111 4
b11110111 6
b1001 7
b1 8
b11 9
0"
b11110111 (
b10001001 5
b1 '
b1 1
b100 )
b100 2
#50
b1100100 !
b1100100 4
b1100100 7
0"
b100 9
b0 8
b1100100 6
b1100100 (
b1100100 5
b100 '
b100 1
b110 +
b110 3
b11 )
b11 2
1*
0,
#60
b10000100 !
b10000100 4
b1111100 7
0"
b1 9
b0 8
b10000100 6
b10000100 (
b11111100 5
b0 '
b0 1
b111110 +
b111110 3
b110 )
b110 2
1,
#70
b1110001 !
b1110001 4
b1110001 7
0"
b0 8
b11 9
b1110001 6
b1110001 (
b1110001 5
b1 '
b1 1
b1110 +
b1110 3
b100 )
b100 2
0,
#80
b10010011 !
b10010011 4
b1101101 7
0"
b100 9
b0 8
b10010011 6
b10010011 (
b11101101 5
b1101 '
b1101 1
b110 +
b110 3
b11 )
b11 2
1,
#90
b10010000 !
b10010000 4
b10010000 6
b1110000 7
0"
b11 9
b0 8
b10010000 (
b11110000 5
b0 '
b0 1
b1110 +
b1110 3
b100 )
b100 2
#100
b10111101 !
b10111101 4
b10111101 6
b1000011 7
b101 9
b0 8
0"
b11000011 5
b11 '
b11 1
b10 +
b10 3
b10 )
b10 2
b10111101 (
#110
b10101100 !
b10101100 4
b10101100 6
b1010100 7
0"
b11010100 5
b10100 '
b10100 1
b10101100 (
#120
b11100001 !
b11100001 4
b11100001 6
b11111 7
b100 9
b0 8
0"
b10011111 5
b1111 '
b1111 1
b1 +
b1 3
b11 )
b11 2
0*
b11100001 (
#130
b1011010 !
b1011010 4
b1011010 7
b0 8
b101 9
b1011010 6
0"
b1011010 5
b11010 '
b11010 1
b10 +
b10 3
b10 )
b10 2
1*
0,
b1011010 (
#140
b1011110 !
b1011110 4
b1011110 7
b1011110 6
0"
b1011110 5
b11110 '
b11110 1
b1011110 (
#150
b10001010 !
b10001010 4
b1110110 7
b11 9
b0 8
b10001010 6
0"
b11110110 5
b110 '
b110 1
b1110 +
b1110 3
b100 )
b100 2
1,
b10001010 (
#160
b1101111 !
b1101111 4
b1101111 7
b0 8
b100 9
b1101111 6
0"
b1101111 5
b1111 '
b1111 1
b110 +
b110 3
b11 )
b11 2
0,
b1101111 (
#170
b1100111 !
b1100111 4
b1100111 7
b1100111 6
0"
b1100111 5
b111 '
b111 1
b1100111 (
#180
b11011 !
b11011 4
b11011 7
b11011 6
b1 8
0"
b11011 5
b1011 '
b1011 1
b1 +
b1 3
0*
b11011 (
#190
b11101101 !
b11101101 4
b10011 7
b111 9
b11101101 6
0"
b10010011 5
b11 '
b11 1
1,
b11101101 (
#200
b10010010 !
b10010010 4
b10010010 6
b1101110 7
b100 9
b110 8
0"
b11101110 5
b1110 '
b1110 1
b110 +
b110 3
1*
b10010010 (
#210
b1000 !
b1000 4
b1000 7
b11 9
b0 8
b1000 6
0"
b1000 5
b0 '
b0 1
b1 +
b1 3
b100 )
b100 2
0*
0,
b1000 (
#220
b1101101 !
b1101101 4
b1101101 7
b1101101 6
b100 9
b0 8
0"
b1101101 5
b1101 '
b1101 1
b110 +
b110 3
b11 )
b11 2
1*
b1101101 (
#230
b1111011 !
b1111011 4
b1111011 7
b1111011 6
b10 9
b0 8
0"
b1111011 5
b11 '
b11 1
b11110 +
b11110 3
b101 )
b101 2
b1111011 (
#240
b10010011 !
b10010011 4
b1101101 7
b100 9
b0 8
b10010011 6
0"
b11101101 5
b1101 '
b1101 1
b110 +
b110 3
b11 )
b11 2
1,
b10010011 (
#250
b11 !
b11 4
b11 7
b0 8
b1 9
b11 6
0"
b11 5
b1 '
b1 1
b1 +
b1 3
b110 )
b110 2
0*
0,
b11 (
#260
b110100 !
b110100 4
b110100 7
b1 8
b101 9
b110100 6
0"
b110100 5
b10100 '
b10100 1
b10 )
b10 2
b110100 (
#270
b1110110 !
b1110110 4
b1110110 7
b1110110 6
b11 9
b0 8
0"
b1110110 5
b110 '
b110 1
b1110 +
b1110 3
b100 )
b100 2
1*
b1110110 (
#280
b11010000 !
b11010000 4
b110000 7
b101 9
b0 8
b11010000 6
0"
b10110000 5
b10000 '
b10000 1
b1 +
b1 3
b10 )
b10 2
0*
1,
b11010000 (
#290
b1111101 !
b1111101 4
b1111101 7
b0 8
b1 9
b1111101 6
0"
b1111101 5
b1 '
b1 1
b111110 +
b111110 3
b110 )
b110 2
1*
0,
b1111101 (
#300
b11010010 !
b11010010 4
b101110 7
b101 9
b0 8
b11010010 6
0"
b10101110 5
b1110 '
b1110 1
b1 +
b1 3
b10 )
b10 2
0*
1,
b11010010 (
#310
b1000111 !
b1000111 4
b1000111 7
b10 8
b101 9
b1000111 6
0"
b1000111 5
b111 '
b111 1
b10 +
b10 3
1*
0,
b1000111 (
#320
b10100111 !
b10100111 4
b1011001 7
b111 9
b1 8
b10100111 6
0"
b11011001 5
b11001 '
b11001 1
1,
b10100111 (
#330
b11001111 !
b11001111 4
b11001111 6
b110001 7
b101 9
0"
b10110001 5
b10001 '
b10001 1
b1 +
b1 3
0*
b11001111 (
#340
b101001 !
b101001 4
b101001 7
b111 9
b0 8
b101001 6
0"
b101001 5
b1001 '
b1001 1
0,
b101001 (
#350
b11111101 !
b11111101 4
b11 7
b1 9
b1 8
b11111101 6
0"
b10000011 5
b1 '
b1 1
b110 )
b110 2
1,
b11111101 (
#360
b10000101 !
b10000101 4
b10000101 6
b1111011 7
b10 9
b0 8
0"
b11111011 5
b11 '
b11 1
b11110 +
b11110 3
b101 )
b101 2
1*
b10000101 (
#370
b11110101 !
b11110101 4
b11110101 6
b1011 7
b10001011 5
b11 9
b0 8
0"
b1 +
b1 3
b100 )
b100 2
0*
b11110101 (
#380
b1010011 !
b1010011 4
b1010011 7
b0 8
b101 9
b1010011 6
0"
b1010011 5
b10011 '
b10011 1
b10 +
b10 3
b10 )
b10 2
1*
0,
b1010011 (
#390
b10011 !
b10011 4
b10011 7
b10011 6
b100 9
b0 8
0"
b10011 5
b11 '
b11 1
b1 +
b1 3
b11 )
b11 2
0*
b10011 (
#400
b111111 !
b111111 4
b111111 7
b1 8
b101 9
b111111 6
0"
b111111 5
b11111 '
b11111 1
b10 )
b10 2
b111111 (
#410
b10111110 !
b10111110 4
b1000010 7
b10 8
b101 9
b10111110 6
0"
b11000010 5
b10 '
b10 1
b10 +
b10 3
1*
1,
b10111110 (
#420
b1011100 !
b1011100 4
b1011100 7
b111 9
b0 8
b1011100 6
0"
b1011100 5
b11100 '
b11100 1
0,
b1011100 (
#430
b1011 !
b1011 4
b1011 7
b1011 6
b11 9
b0 8
0"
b1011 5
b11 '
b11 1
b1 +
b1 3
b100 )
b100 2
0*
b1011 (
#440
b1101011 !
b1101011 4
b1101011 7
b1101011 6
b100 9
b0 8
0"
b1101011 5
b1011 '
b1011 1
b110 +
b110 3
b11 )
b11 2
1*
b1101011 (
#450
b11011100 !
b11011100 4
b100100 7
b101 9
b0 8
b11011100 6
0"
b10100100 5
b100 '
b100 1
b1 +
b1 3
b10 )
b10 2
0*
1,
b11011100 (
#460
b100011 !
b100011 4
b100011 7
b111 9
b100011 6
0"
b100011 5
b11 '
b11 1
0,
b100011 (
#470
b10011010 !
b10011010 4
b1100110 7
b100 9
b0 8
b10011010 6
0"
b11100110 5
b110 '
b110 1
b110 +
b110 3
b11 )
b11 2
1*
1,
b10011010 (
#480
b1011010 !
b1011010 4
b1011010 7
b0 8
b101 9
b1011010 6
0"
b1011010 5
b11010 '
b11010 1
b10 +
b10 3
b10 )
b10 2
0,
b1011010 (
#490
b1100001 !
b1100001 4
b1100001 7
b1100001 6
b100 9
b0 8
0"
b1100001 5
b1 '
b1 1
b110 +
b110 3
b11 )
b11 2
b1100001 (
#500
b11100110 !
b11100110 4
b11010 7
b100 9
b1 8
b11100110 6
0"
b10011010 5
b1010 '
b1010 1
b1 +
b1 3
0*
1,
b11100110 (
#510
b1001000 !
b1001000 4
b1001000 7
b101 9
b0 8
b1001000 6
0"
b1001000 5
b1000 '
b1000 1
b10 +
b10 3
b10 )
b10 2
1*
0,
b1001000 (
#520
b11010011 !
b11010011 4
b101101 7
b101 9
b1 8
b11010011 6
0"
b10101101 5
b1101 '
b1101 1
b1 +
b1 3
0*
1,
b11010011 (
#530
b10101100 !
b10101100 4
b10101100 6
b1010100 7
b10 8
0"
b11010100 5
b10100 '
b10100 1
b10 +
b10 3
1*
b10101100 (
#540
b1000011 !
b1000011 4
b1000011 7
b111 9
b0 8
b1000011 6
0"
b1000011 5
b11 '
b11 1
0,
b1000011 (
#550
b1110100 !
b1110100 4
b1110100 7
b1110100 6
b11 9
b0 8
0"
b1110100 5
b100 '
b100 1
b1110 +
b1110 3
b100 )
b100 2
b1110100 (
#560
b101100 !
b101100 4
b101100 7
b101100 6
b101 9
b0 8
0"
b101100 5
b1100 '
b1100 1
b1 +
b1 3
b10 )
b10 2
0*
b101100 (
#570
b10101111 !
b10101111 4
b1010001 7
b101 9
b10 8
b10101111 6
0"
b11010001 5
b10001 '
b10001 1
b10 +
b10 3
1*
1,
b10101111 (
#580
b1001101 !
b1001101 4
b1001101 7
b111 9
b0 8
b1001101 6
0"
b1001101 5
b1101 '
b1101 1
0,
b1001101 (
#590
b10101001 !
b10101001 4
b1010111 7
b1 8
b10101001 6
0"
b11010111 5
b10111 '
b10111 1
1,
b10101001 (
#600
b11101000 !
b11101000 4
b11101000 6
b11000 7
b0 8
b100 9
0"
b10011000 5
b1000 '
b1000 1
b1 +
b1 3
b11 )
b11 2
0*
b11101000 (
#610
b100010 !
b100010 4
b100010 7
b1 8
b101 9
b100010 6
0"
b100010 5
b10 '
b10 1
b10 )
b10 2
0,
b100010 (
#620
b11011011 !
b11011011 4
b100101 7
b111 9
b11011011 6
0"
b10100101 5
b101 '
b101 1
1,
b11011011 (
#630
b11000100 !
b11000100 4
b11000100 6
b111100 7
0"
b10111100 5
b11100 '
b11100 1
b11000100 (
#640
b111101 !
b111101 4
b111101 7
b0 8
b111101 6
0"
b111101 5
b11101 '
b11101 1
0,
b111101 (
#650
b1110000 !
b1110000 4
b1110000 7
b1110000 6
b11 9
b0 8
0"
b1110000 5
b0 '
b0 1
b1110 +
b1110 3
b100 )
b100 2
1*
b1110000 (
#660
b10011101 !
b10011101 4
b1100011 7
b100 9
b0 8
b10011101 6
0"
b11100011 5
b11 '
b11 1
b110 +
b110 3
b11 )
b11 2
1,
b10011101 (
#670
b1100000 !
b1100000 4
b1100000 7
b111 9
b1100000 6
0"
b1100000 5
b0 '
b0 1
0,
b1100000 (
#680
b11100111 !
b11100111 4
b11001 7
b100 9
b1 8
b11100111 6
0"
b10011001 5
b1001 '
b1001 1
b1 +
b1 3
0*
1,
b11100111 (
#690
b10010101 !
b10010101 4
b10010101 6
b1101011 7
b110 8
0"
b11101011 5
b1011 '
b1011 1
b110 +
b110 3
1*
b10010101 (
#700
b1 !
b1 4
b1 7
b0 9
b0 8
b1 6
0"
b1 5
b0 '
b0 1
b1 +
b1 3
b111 )
b111 2
0*
0,
b1 (
#710
b111100 !
b111100 4
b111100 7
b1 8
b101 9
b111100 6
0"
b111100 5
b11100 '
b11100 1
b10 )
b10 2
b111100 (
#720
b11010101 !
b11010101 4
b101011 7
b111 9
b11010101 6
0"
b10101011 5
b1011 '
b1011 1
1,
b11010101 (
#730
b110001 !
b110001 4
b110001 7
b0 8
b110001 6
0"
b110001 5
b10001 '
b10001 1
0,
b110001 (
#740
b11011000 !
b11011000 4
b101000 7
b1 8
b11011000 6
0"
b10101000 5
b1000 '
b1000 1
1,
b11011000 (
#750
b10001001 !
b10001001 4
b10001001 6
b1110111 7
b11 9
b0 8
0"
b11110111 5
b111 '
b111 1
b1110 +
b1110 3
b100 )
b100 2
1*
b10001001 (
#760
b1011101 !
b1011101 4
b1011101 7
b0 8
b101 9
b1011101 6
0"
b1011101 5
b11101 '
b11101 1
b10 +
b10 3
b10 )
b10 2
0,
b1011101 (
#770
b11000101 !
b11000101 4
b111011 7
b101 9
b1 8
b11000101 6
0"
b10111011 5
b11011 '
b11011 1
b1 +
b1 3
0*
1,
b11000101 (
#780
b11110100 !
b11110100 4
b11110100 6
b1100 7
b11 9
b1 8
0"
b10001100 5
b100 '
b100 1
b100 )
b100 2
b11110100 (
#790
b1010000 !
b1010000 4
b1010000 7
b101 9
b0 8
b1010000 6
0"
b1010000 5
b10000 '
b10000 1
b10 +
b10 3
b10 )
b10 2
1*
0,
b1010000 (
#800
b10101010 !
b10101010 4
b1010110 7
b111 9
b1 8
b10101010 6
0"
b11010110 5
b10110 '
b10110 1
1,
b10101010 (
#810
b10001100 !
b10001100 4
b10001100 6
b1110100 7
b11 9
b0 8
0"
b11110100 5
b100 '
b100 1
b1110 +
b1110 3
b100 )
b100 2
b10001100 (
#820
b1110011 !
b1110011 4
b1110011 7
b111 9
b1110011 6
0"
b1110011 5
b11 '
b11 1
0,
b1110011 (
#830
b1101111 !
b1101111 4
b1101111 7
b1101111 6
b100 9
b0 8
0"
b1101111 5
b1111 '
b1111 1
b110 +
b110 3
b11 )
b11 2
b1101111 (
#840
b1111000 !
b1111000 4
b1111000 7
b1111000 6
b10 9
b0 8
0"
b1111000 5
b0 '
b0 1
b11110 +
b11110 3
b101 )
b101 2
b1111000 (
#850
b10000 !
b10000 4
b10000 7
b10000 6
b10000 5
b100 9
b0 8
0"
b1 +
b1 3
b11 )
b11 2
0*
b10000 (
#860
b11110010 !
b11110010 4
b1110 7
b11 9
b1 8
b11110010 6
0"
b10001110 5
b110 '
b110 1
b100 )
b100 2
1,
b11110010 (
#870
b11001101 !
b11001101 4
b11001101 6
b110011 7
b101 9
b1 8
0"
b10110011 5
b10011 '
b10011 1
b10 )
b10 2
b11001101 (
#880
b11101100 !
b11101100 4
b11101100 6
b10100 7
b100 9
b1 8
0"
b10010100 5
b100 '
b100 1
b11 )
b11 2
b11101100 (
#890
b101000 !
b101000 4
b101000 7
b101 9
b1 8
b101000 6
0"
b101000 5
b1000 '
b1000 1
b10 )
b10 2
0,
b101000 (
#900
b111001 !
b111001 4
b111001 7
b111001 6
0"
b111001 5
b11001 '
b11001 1
b111001 (
#910
b1101001 !
b1101001 4
b1101001 7
b1101001 6
b100 9
b0 8
0"
b1101001 5
b1001 '
b1001 1
b110 +
b110 3
b11 )
b11 2
1*
b1101001 (
#920
b11011110 !
b11011110 4
b100010 7
b101 9
b0 8
b11011110 6
0"
b10100010 5
b10 '
b10 1
b1 +
b1 3
b10 )
b10 2
0*
1,
b11011110 (
#930
b1001 !
b1001 4
b1001 7
b1 8
b11 9
b1001 6
0"
b1001 5
b1 '
b1 1
b100 )
b100 2
0,
b1001 (
#940
b10001 7
b11101111 !
b11101111 4
b1 8
b10010001 5
b100 9
b11101111 6
0"
b11 )
b11 2
1,
b11101111 (
#950
b1111111 !
b1111111 4
b1111111 7
b0 9
b0 8
b1111111 6
0"
b1111111 5
b0 '
b0 1
b1111111 +
b1111111 3
b111 )
b111 2
1*
0,
b1111111 (
#960
b11001000 !
b11001000 4
b111000 7
b101 9
b0 8
b11001000 6
0"
b10111000 5
b11000 '
b11000 1
b1 +
b1 3
b10 )
b10 2
0*
1,
b11001000 (
#970
b10011011 !
b10011011 4
b10011011 6
b1100101 7
b100 9
b0 8
0"
b11100101 5
b101 '
b101 1
b110 +
b110 3
b11 )
b11 2
1*
b10011011 (
#980
b10101000 !
b10101000 4
b10101000 6
b1011000 7
b101 9
b0 8
0"
b11011000 5
b11000 '
b11000 1
b10 +
b10 3
b10 )
b10 2
b10101000 (
