src/posit_encode.sv
/*

Description:
    Posit encoder.

Usage:
    cd $PROJECT_ROOT/waveforms
    
    iverilog -DTEST_BENCH_ENCODE -DN=8 -DES=0 -o posit_encode.out ../src/posit_encode.sv && ./posit_encode.out

    yosys -p "synth_intel -family max10 -top posit_encode -vqm posit_encode.vqm" ../src/posit_encode.sv > yosys_posit_encode.out

*/
module posit_encode #(
        parameter N = 8,
        parameter S = $clog2(N),
        parameter ES = 0
    )(
        input          is_zero,
        input          is_inf,
        input          sign,
        input          reg_s,
        input [N-1:0]  regime_bits,
        input [S-1:0]  reg_len,
        input [N-1:0]  k,
        input [ES-1:0] exp,
        input [N-1:0]  mant,
        output [N-1:0] posit
    );
    
    function [N-1:0] c2(input [N-1:0] a);
        c2 = ~a + 1'b1;
    endfunction
    
    function [N-1:0] shl (
            input [N-1:0] bits,
            input [N-1:0] rhs
        );
        shl = rhs > 0 ? bits << rhs : bits;
    endfunction

    wire [N-1:0] bits, bits_assembled;
    assign bits_assembled = ( 
          shl(sign, N-1)
        + shl(regime_bits, N-1-reg_len)
        + shl(exp, N-1-reg_len-ES)
        + mant
    );

    assign bits = 
        sign == 0 ? bits_assembled : 
                    c2(bits_assembled & ~(1 << (N-1)));

    /*
    ~(1'b1 << (N-1)) === {1'b0, {N-1{1'b1}}}
    */

    assign posit = 
        is_zero === 1 ? 0 : 
        is_inf  === 1 ? (1 << (N-1)) :
                        bits;
            /*  ^^^ 3 equal signs needed to compare against 1'bx, 
                otherwise if `is_zero` or `is_inf` == 1'bx, also 
                `posit` would be 'bX, regardless. */
endmodule


`ifdef TEST_BENCH_ENCODE 

// defaulted to P<8,0> unless specified via some `-D`efine.

module tb_posit_encode;
    function [N-1:0] c2(input [N-1:0] a);
        c2 = ~a + 1'b1;
    endfunction
    function [N-1:0] abs(input [N-1:0] in);
        abs = in[N-1] == 0 ? in : c2(in);
    endfunction

`ifdef N
    parameter N = `N;
`else
    parameter N = 8;
`endif

    parameter S = $clog2(N);

`ifdef ES
    parameter ES = `ES;
`else
    parameter ES = 0;
`endif

    /* inputs */
    reg            is_zero;
    reg            is_inf;
    reg            sign;
    reg            reg_s;
    reg [N-1:0]    regime_bits;
    reg [S-1:0]    reg_len;
    reg [N-1:0]    k;
    reg [ES-1:0]   exp;
    reg [N-1:0]    mant;
    /* output */
    wire [N-1:0]   posit;
    /*************************/

    reg [N-1:0]   posit_expected;
    reg err;
    
    reg [N:0] test_no;

    posit_encode #(
        .N(N),
        .S(S),
        .ES(ES)
    ) posit_encode_inst (
        .is_zero        (is_zero),
        .is_inf         (is_inf),
        .sign           (sign),
        .reg_s          (reg_s),
        .regime_bits    (regime_bits),
        .reg_len        (reg_len),
        .k              (k),
        .exp            (exp),
        .mant           (mant),
        .posit          (posit)
    );

    always @(*) begin
        err = posit == posit_expected ? 0 : 1'bx;
    end

    initial begin
             if (N == 8 && ES == 0) $dumpfile("tb_posit_encode_P8E0.vcd");
        else if (N == 5 && ES == 1) $dumpfile("tb_posit_encode_P5E1.vcd");
        else                        $dumpfile("tb_posit_encode.vcd");

	    $dumpvars(0, tb_posit_encode);                        
            
        if (N == 8 && ES == 0) begin
            `include "../src/tb_posit_encode_P8E0.sv"
        end
       

        #10;
		$finish;
    end

endmodule
`endif

waveforms/tb_posit_encode_P8E0.vcd
$date
	Sun Dec 19 11:17:17 2021
$end
$version
	Icarus Verilog
$end
$timescale
	1s
$end
$scope module tb_posit_encode $end
$var wire 8 ! posit [7:0] $end
$var reg 1 " err $end
$var reg 2 # exp [-1:0] $end
$var reg 1 $ is_inf $end
$var reg 1 % is_zero $end
$var reg 8 & k [7:0] $end
$var reg 8 ' mant [7:0] $end
$var reg 8 ( posit_expected [7:0] $end
$var reg 3 ) reg_len [2:0] $end
$var reg 1 * reg_s $end
$var reg 8 + regime_bits [7:0] $end
$var reg 1 , sign $end
$var reg 9 - test_no [8:0] $end
$scope function abs $end
$var reg 8 . in [7:0] $end
$upscope $end
$scope function c2 $end
$var reg 8 / a [7:0] $end
$upscope $end
$scope module posit_encode_inst $end
$var wire 2 0 exp [-1:0] $end
$var wire 1 $ is_inf $end
$var wire 1 % is_zero $end
$var wire 8 1 k [7:0] $end
$var wire 8 2 mant [7:0] $end
$var wire 3 3 reg_len [2:0] $end
$var wire 1 * reg_s $end
$var wire 8 4 regime_bits [7:0] $end
$var wire 1 , sign $end
$var wire 8 5 posit [7:0] $end
$var wire 8 6 bits_assembled [7:0] $end
$var wire 8 7 bits [7:0] $end
$scope function c2 $end
$var reg 8 8 a [7:0] $end
$upscope $end
$scope function shl $end
$var reg 8 9 bits [7:0] $end
$var reg 8 : rhs [7:0] $end
$upscope $end
$upscope $end
$upscope $end
$enddefinitions $end
#0
$dumpvars
b101 :
b1 9
b111100 8
b111100 7
b111100 6
b111100 5
b1 4
b10 3
b11100 2
bx 1
b0 0
bx /
bx .
b1 -
0,
b1 +
0*
b10 )
b111100 (
b11100 '
bx &
0%
0$
b0 #
0"
b111100 !
$end
#10
b1001101 !
b1001101 5
b1001101 8
b1001101 7
b10 9
0"
b1001101 6
b1101 '
b1101 2
b10 +
b10 4
1*
b1001101 (
b10 -
#20
b11010 !
b11010 5
b11010 8
b11010 7
b100 :
b0 9
0"
b11010 6
b1010 '
b1010 2
b1 +
b1 4
b11 )
b11 3
0*
b11010 (
b11 -
#30
b10111000 !
b10111000 5
b1001000 8
b101 :
b0 9
b10111000 7
0"
b11001000 6
b1000 '
b1000 2
b10 +
b10 4
b10 )
b10 3
1*
1,
b10111000 (
b100 -
#40
b1100101 !
b1100101 5
b1100101 8
b0 9
b100 :
b1100101 7
0"
b1100101 6
b101 '
b101 2
b110 +
b110 4
b11 )
b11 3
0,
b1100101 (
b101 -
#50
b1111010 !
b1111010 5
b1111010 8
b1111010 7
b10 :
b0 9
0"
b1111010 6
b10 '
b10 2
b11110 +
b11110 4
b101 )
b101 3
b1111010 (
b110 -
#60
b100111 !
b100111 5
b100111 8
b100111 7
b101 :
b0 9
0"
b100111 6
b111 '
b111 2
b1 +
b1 4
b10 )
b10 3
0*
b100111 (
b111 -
#70
b10111 !
b10111 5
b10111 8
b10111 7
b10111 6
b1 9
b100 :
0"
b11 )
b11 3
b10111 (
b1000 -
#80
b10001 !
b10001 5
b10001 8
b10001 7
0"
b10001 6
b1 '
b1 2
b10001 (
b1001 -
#90
b101 !
b101 5
b101 8
b101 7
b101 6
b10 :
b1 9
0"
b101 )
b101 3
b101 (
b1010 -
#100
b1100110 !
b1100110 5
b1100110 8
b1100110 7
b100 :
b0 9
0"
b1100110 6
b110 '
b110 2
b110 +
b110 4
b11 )
b11 3
1*
b1100110 (
b1011 -
#110
b10001100 !
b10001100 5
b1110100 8
b11 :
b0 9
b10001100 7
0"
b11110100 6
b100 '
b100 2
b1110 +
b1110 4
b100 )
b100 3
1,
b10001100 (
b1100 -
#120
b11101010 !
b11101010 5
b11101010 7
b10110 8
b100 :
b0 9
0"
b10010110 6
b110 '
b110 2
b1 +
b1 4
b11 )
b11 3
0*
b11101010 (
b1101 -
#130
b1001010 !
b1001010 5
b1001010 8
b0 9
b101 :
b1001010 7
0"
b1001010 6
b1010 '
b1010 2
b10 +
b10 4
b10 )
b10 3
1*
0,
b1001010 (
b1110 -
#140
b11001100 !
b11001100 5
b110100 8
b101 :
b1 9
b11001100 7
0"
b10110100 6
b10100 '
b10100 2
b1 +
b1 4
0*
1,
b11001100 (
b1111 -
#150
b11000011 !
b11000011 5
b11000011 7
b111101 8
0"
b10111101 6
b11101 '
b11101 2
b11000011 (
b10000 -
#160
b1111 !
b1111 5
b1111 8
b11 :
b1 9
b1111 7
0"
b1111 6
b111 '
b111 2
b100 )
b100 3
0,
b1111 (
b10001 -
#170
b111000 !
b111000 5
b111000 8
b101 :
b1 9
b111000 7
0"
b111000 6
b11000 '
b11000 2
b10 )
b10 3
b111000 (
b10010 -
#180
b10000101 !
b10000101 5
b1111011 8
b0 9
b10 :
b10000101 7
0"
b11111011 6
b11 '
b11 2
b11110 +
b11110 4
b101 )
b101 3
1*
1,
b10000101 (
b10011 -
#190
b10001001 !
b10001001 5
b10001001 7
b1110111 8
b11 :
b0 9
0"
b11110111 6
b111 '
b111 2
b1110 +
b1110 4
b100 )
b100 3
b10001001 (
b10100 -
#200
b1011100 !
b1011100 5
b1011100 8
b0 9
b101 :
b1011100 7
0"
b1011100 6
b11100 '
b11100 2
b10 +
b10 4
b10 )
b10 3
0,
b1011100 (
b10101 -
#210
b1000110 !
b1000110 5
b1000110 8
b1000110 7
0"
b1000110 6
b110 '
b110 2
b1000110 (
b10110 -
#220
b11000111 !
b11000111 5
b111001 8
b101 :
b1 9
b11000111 7
0"
b10111001 6
b11001 '
b11001 2
b1 +
b1 4
0*
1,
b11000111 (
b10111 -
#230
b101100 !
b101100 5
b101100 8
b111 :
b0 9
b101100 7
0"
b101100 6
b1100 '
b1100 2
0,
b101100 (
b11000 -
#240
b11010011 !
b11010011 5
b101101 8
b1 9
b11010011 7
0"
b10101101 6
b1101 '
b1101 2
1,
b11010011 (
b11001 -
#250
b11011 !
b11011 5
b11011 8
b100 :
b1 9
b11011 7
0"
b11011 6
b1011 '
b1011 2
b11 )
b11 3
0,
b11011 (
b11010 -
#260
b1000011 !
b1000011 5
b1000011 8
b1000011 7
b101 :
b0 9
0"
b1000011 6
b11 '
b11 2
b10 +
b10 4
b10 )
b10 3
1*
b1000011 (
b11011 -
#270
b110110 !
b110110 5
b110110 8
b110110 7
b1 9
0"
b110110 6
b10110 '
b10110 2
b1 +
b1 4
0*
b110110 (
b11100 -
#280
b110 !
b110 5
b110 8
b10 :
b1 9
b110 7
0"
b110 6
b10 '
b10 2
b101 )
b101 3
b110 (
b11101 -
#290
b11010100 !
b11010100 5
b101100 8
b1 9
b101 :
b11010100 7
0"
b10101100 6
b1100 '
b1100 2
b10 )
b10 3
1,
b11010100 (
b11110 -
#300
b10100100 !
b10100100 5
b10100100 7
b1011100 8
b10 9
0"
b11011100 6
b11100 '
b11100 2
b10 +
b10 4
1*
b10100100 (
b11111 -
#310
b11001110 !
b11001110 5
b11001110 7
b110010 8
b1 9
0"
b10110010 6
b10010 '
b10010 2
b1 +
b1 4
0*
b11001110 (
b100000 -
#320
b1000010 !
b1000010 5
b1000010 8
b101 :
b10 9
b1000010 7
0"
b1000010 6
b10 '
b10 2
b10 +
b10 4
1*
0,
b1000010 (
b100001 -
#330
b11110000 !
b11110000 5
b10000 8
b100 :
b0 9
b11110000 7
0"
b10010000 6
b0 '
b0 2
b1 +
b1 4
b11 )
b11 3
0*
1,
b11110000 (
b100010 -
#340
b1000101 !
b1000101 5
b1000101 8
b0 9
b101 :
b1000101 7
0"
b1000101 6
b101 '
b101 2
b10 +
b10 4
b10 )
b10 3
1*
0,
b1000101 (
b100011 -
#350
b110001 !
b110001 5
b110001 8
b110001 7
b1 9
0"
b110001 6
b10001 '
b10001 2
b1 +
b1 4
0*
b110001 (
b100100 -
#360
b101010 !
b101010 5
b101010 8
b101010 7
0"
b101010 6
b1010 '
b1010 2
b101010 (
b100101 -
#370
b1001111 !
b1001111 5
b1001111 8
b1001111 7
b10 9
0"
b1001111 6
b1111 '
b1111 2
b10 +
b10 4
1*
b1001111 (
b100110 -
#380
b11110001 !
b11110001 5
b1111 8
b11 :
b0 9
b11110001 7
0"
b10001111 6
b111 '
b111 2
b1 +
b1 4
b100 )
b100 3
0*
1,
b11110001 (
b100111 -
#390
b10100000 !
b10100000 5
b10100000 7
b1100000 8
b100 :
b0 9
0"
b11100000 6
b0 '
b0 2
b110 +
b110 4
b11 )
b11 3
1*
b10100000 (
b101000 -
#400
b10111011 !
b10111011 5
b10111011 7
b1000101 8
b101 :
b0 9
0"
b11000101 6
b101 '
b101 2
b10 +
b10 4
b10 )
b10 3
b10111011 (
b101001 -
#410
b1011111 !
b1011111 5
b1011111 8
b111 :
b1011111 7
0"
b1011111 6
b11111 '
b11111 2
0,
b1011111 (
b101010 -
#420
b10110 !
b10110 5
b10110 8
b10110 7
b100 :
b0 9
0"
b10110 6
b110 '
b110 2
b1 +
b1 4
b11 )
b11 3
0*
b10110 (
b101011 -
#430
b10011011 !
b10011011 5
b1100101 8
b100 :
b110 9
b10011011 7
0"
b11100101 6
b101 '
b101 2
b110 +
b110 4
1*
1,
b10011011 (
b101100 -
#440
b1010110 !
b1010110 5
b1010110 8
b101 :
b0 9
b1010110 7
0"
b1010110 6
b10110 '
b10110 2
b10 +
b10 4
b10 )
b10 3
0,
b1010110 (
b101101 -
#450
b10101011 !
b10101011 5
b1010101 8
b111 :
b1 9
b10101011 7
0"
b11010101 6
b10101 '
b10101 2
1,
b10101011 (
b101110 -
#460
b1100011 !
b1100011 5
b1100011 8
b100 :
b0 9
b1100011 7
0"
b1100011 6
b11 '
b11 2
b110 +
b110 4
b11 )
b11 3
0,
b1100011 (
b101111 -
#470
b0 !
b0 5
b0 8
b111 :
b0 9
b0 7
x"
b10000000 6
b0 '
b0 2
b11111110 +
b11111110 4
b0 )
b0 3
1,
b10000001 (
b110000 -
#480
0"
b111111 !
b111111 5
b111111 8
b101 :
b0 9
b111111 7
b111111 6
b11111 '
b11111 2
b1 +
b1 4
b10 )
b10 3
0*
0,
b111111 (
b110001 -
#490
b101101 !
b101101 5
b101101 8
b101101 7
0"
b101101 6
b1101 '
b1101 2
b101101 (
b110010 -
#500
b11011111 !
b11011111 5
b100001 8
b111 :
b1 9
b11011111 7
0"
b10100001 6
b1 '
b1 2
1,
b11011111 (
b110011 -
#510
b1111001 8
b1111001 !
b1111001 5
b10 :
b1111001 6
b0 9
b1111001 7
0"
b11110 +
b11110 4
b101 )
b101 3
1*
0,
b1111001 (
b110100 -
#520
b1000111 !
b1000111 5
b1000111 8
b1000111 7
b101 :
b0 9
0"
b1000111 6
b111 '
b111 2
b10 +
b10 4
b10 )
b10 3
b1000111 (
b110101 -
#530
b11100001 !
b11100001 5
b11111 8
b100 :
b0 9
b11100001 7
0"
b10011111 6
b1111 '
b1111 2
b1 +
b1 4
b11 )
b11 3
0*
1,
b11100001 (
b110110 -
#540
b11110011 !
b11110011 5
b11110011 7
b1101 8
b1 9
b11 :
0"
b10001101 6
b101 '
b101 2
b100 )
b100 3
b11110011 (
b110111 -
#550
b1001100 !
b1001100 5
b1001100 8
b101 :
b0 9
b1001100 7
0"
b1001100 6
b1100 '
b1100 2
b10 +
b10 4
b10 )
b10 3
1*
0,
b1001100 (
b111000 -
#560
b1 !
b1 5
b1 8
b1 7
b0 :
b0 9
0"
b1 6
b0 '
b0 2
b1 +
b1 4
b111 )
b111 3
0*
b1 (
b111001 -
#570
b11011000 !
b11011000 5
b101000 8
b101 :
b1 9
b11011000 7
0"
b10101000 6
b1000 '
b1000 2
b10 )
b10 3
1,
b11011000 (
b111010 -
#580
b10010010 !
b10010010 5
b10010010 7
b1101110 8
b100 :
b0 9
0"
b11101110 6
b1110 '
b1110 2
b110 +
b110 4
b11 )
b11 3
1*
b10010010 (
b111011 -
#590
b10110100 !
b10110100 5
b10110100 7
b1001100 8
b101 :
b0 9
0"
b11001100 6
b1100 '
b1100 2
b10 +
b10 4
b10 )
b10 3
b10110100 (
b111100 -
#600
b11011001 !
b11011001 5
b11011001 7
b100111 8
b1 9
0"
b10100111 6
b111 '
b111 2
b1 +
b1 4
0*
b11011001 (
b111101 -
#610
b10000010 !
b10000010 5
b10000010 7
b1111110 8
b0 :
b0 9
0"
b11111110 6
b0 '
b0 2
b1111110 +
b1111110 4
b111 )
b111 3
1*
b10000010 (
b111110 -
#620
b11011011 !
b11011011 5
b11011011 7
b100101 8
b101 :
b0 9
0"
b10100101 6
b101 '
b101 2
b1 +
b1 4
b10 )
b10 3
0*
b11011011 (
b111111 -
#630
b1101001 !
b1101001 5
b1101001 8
b0 9
b100 :
b1101001 7
0"
b1101001 6
b1001 '
b1001 2
b110 +
b110 4
b11 )
b11 3
1*
0,
b1101001 (
b1000000 -
#640
b1101100 !
b1101100 5
b1101100 8
b1101100 7
0"
b1101100 6
b1100 '
b1100 2
b1101100 (
b1000001 -
#650
b10011001 !
b10011001 5
b1100111 8
b111 :
b1 9
b10011001 7
0"
b11100111 6
b111 '
b111 2
1,
b10011001 (
b1000010 -
#660
b1001001 !
b1001001 5
b1001001 8
b101 :
b0 9
b1001001 7
0"
b1001001 6
b1001 '
b1001 2
b10 +
b10 4
b10 )
b10 3
0,
b1001001 (
b1000011 -
#670
b1101110 !
b1101110 5
b1101110 8
b1101110 7
b100 :
b0 9
0"
b1101110 6
b1110 '
b1110 2
b110 +
b110 4
b11 )
b11 3
b1101110 (
b1000100 -
#680
b1110011 !
b1110011 5
b1110011 8
b1110011 7
b11 :
b0 9
0"
b1110011 6
b11 '
b11 2
b1110 +
b1110 4
b100 )
b100 3
b1110011 (
b1000101 -
#690
b101001 !
b101001 5
b101001 8
b101001 7
b101 :
b0 9
0"
b101001 6
b1001 '
b1001 2
b1 +
b1 4
b10 )
b10 3
0*
b101001 (
b1000110 -
#700
b111011 !
b111011 5
b111011 8
b111011 7
0"
b111011 6
b11011 '
b11011 2
b111011 (
b1000111 -
#710
b1001110 !
b1001110 5
b1001110 8
b1001110 7
b10 9
0"
b1001110 6
b1110 '
b1110 2
b10 +
b10 4
1*
b1001110 (
b1001000 -
#720
b11011110 !
b11011110 5
b100010 8
b101 :
b1 9
b11011110 7
0"
b10100010 6
b10 '
b10 2
b1 +
b1 4
0*
1,
b11011110 (
b1001001 -
#730
b1011 !
b1011 5
b1011 8
b11 :
b1 9
b1011 7
0"
b1011 6
b11 '
b11 2
b100 )
b100 3
0,
b1011 (
b1001010 -
#740
b10100 !
b10100 5
b10100 8
b100 :
b1 9
b10100 7
0"
b10100 6
b100 '
b100 2
b11 )
b11 3
b10100 (
b1001011 -
#750
b10110101 !
b10110101 5
b1001011 8
b0 9
b101 :
b10110101 7
0"
b11001011 6
b1011 '
b1011 2
b10 +
b10 4
b10 )
b10 3
1*
1,
b10110101 (
b1001100 -
#760
b1110110 !
b1110110 5
b1110110 8
b0 9
b11 :
b1110110 7
0"
b1110110 6
b110 '
b110 2
b1110 +
b1110 4
b100 )
b100 3
0,
b1110110 (
b1001101 -
#770
b11010111 !
b11010111 5
b101001 8
b101 :
b0 9
b11010111 7
0"
b10101001 6
b1001 '
b1001 2
b1 +
b1 4
b10 )
b10 3
0*
1,
b11010111 (
b1001110 -
#780
b11001010 !
b11001010 5
b11001010 7
b110110 8
0"
b10110110 6
b10110 '
b10110 2
b11001010 (
b1001111 -
#790
b10000100 !
b10000100 5
b10000100 7
b1111100 8
b1 :
b0 9
0"
b11111100 6
b0 '
b0 2
b111110 +
b111110 4
b110 )
b110 3
1*
b10000100 (
b1010000 -
#800
b10001000 !
b10001000 5
b10001000 7
b1111000 8
b11111000 6
b10 :
b0 9
0"
b11110 +
b11110 4
b101 )
b101 3
b10001000 (
b1010001 -
#810
b10100101 !
b10100101 5
b10100101 7
b1011011 8
b101 :
b0 9
0"
b11011011 6
b11011 '
b11011 2
b10 +
b10 4
b10 )
b10 3
b10100101 (
b1010010 -
#820
b1111000 !
b1111000 5
b1111000 8
b0 9
b10 :
b1111000 7
0"
b1111000 6
b0 '
b0 2
b11110 +
b11110 4
b101 )
b101 3
0,
b1111000 (
b1010011 -
#830
b1010111 !
b1010111 5
b1010111 8
b1010111 7
b101 :
b0 9
0"
b1010111 6
b10111 '
b10111 2
b10 +
b10 4
b10 )
b10 3
b1010111 (
b1010100 -
#840
b100101 !
b100101 5
b100101 8
b100101 7
b1 9
0"
b100101 6
b101 '
b101 2
b1 +
b1 4
0*
b100101 (
b1010101 -
#850
b110010 !
b110010 5
b110010 8
b110010 7
0"
b110010 6
b10010 '
b10010 2
b110010 (
b1010110 -
#860
b11110110 !
b11110110 5
b1010 8
b1 9
b11 :
b11110110 7
0"
b10001010 6
b10 '
b10 2
b100 )
b100 3
1,
b11110110 (
b1010111 -
#870
b10111111 !
b10111111 5
b10111111 7
b1000001 8
b101 :
b0 9
0"
b11000001 6
b1 '
b1 2
b10 +
b10 4
b10 )
b10 3
1*
b10111111 (
b1011000 -
#880
b110011 !
b110011 5
b110011 8
b1 9
b101 :
b110011 7
0"
b110011 6
b10011 '
b10011 2
b1 +
b1 4
0*
0,
b110011 (
b1011001 -
#890
b10100010 !
b10100010 5
b1011110 8
b10 9
b101 :
b10100010 7
0"
b11011110 6
b11110 '
b11110 2
b10 +
b10 4
1*
1,
b10100010 (
b1011010 -
#900
b10100001 !
b10100001 5
b10100001 7
b1011111 8
0"
b11011111 6
b11111 '
b11111 2
b10100001 (
b1011011 -
#910
b1110000 !
b1110000 5
b1110000 8
b11 :
b0 9
b1110000 7
0"
b1110000 6
b0 '
b0 2
b1110 +
b1110 4
b100 )
b100 3
0,
b1110000 (
b1011100 -
#920
b11101001 !
b11101001 5
b10111 8
b100 :
b0 9
b11101001 7
0"
b10010111 6
b111 '
b111 2
b1 +
b1 4
b11 )
b11 3
0*
1,
b11101001 (
b1011101 -
#930
b101111 !
b101111 5
b101111 8
b1 9
b101 :
b101111 7
0"
b101111 6
b1111 '
b1111 2
b10 )
b10 3
0,
b101111 (
b1011110 -
#940
b1011011 !
b1011011 5
b1011011 8
b1011011 7
b10 9
0"
b1011011 6
b11011 '
b11011 2
b10 +
b10 4
1*
b1011011 (
b1011111 -
#950
b1101111 !
b1101111 5
b1101111 8
b1101111 7
b100 :
b0 9
0"
b1101111 6
b1111 '
b1111 2
b110 +
b110 4
b11 )
b11 3
b1101111 (
b1100000 -
#960
b10010110 !
b10010110 5
b1101010 8
b111 :
b1 9
b10010110 7
0"
b11101010 6
b1010 '
b1010 2
1,
b10010110 (
b1100001 -
#970
b1010010 !
b1010010 5
b1010010 8
b101 :
b0 9
b1010010 7
0"
b1010010 6
b10010 '
b10010 2
b10 +
b10 4
b10 )
b10 3
0,
b1010010 (
b1100010 -
#980
b10001110 !
b10001110 5
b1110010 8
b11 :
b0 9
b10001110 7
0"
b11110010 6
b10 '
b10 2
b1110 +
b1110 4
b100 )
b100 3
1,
b10001110 (
b1100011 -
#990
b10101001 !
b10101001 5
b10101001 7
b1010111 8
b101 :
b0 9
0"
b11010111 6
b10111 '
b10111 2
b10 +
b10 4
b10 )
b10 3
b10101001 (
b1100100 -
#1000
b10011101 !
b10011101 5
b10011101 7
b1100011 8
b100 :
b0 9
0"
b11100011 6
b11 '
b11 2
b110 +
b110 4
b11 )
b11 3
b10011101 (
b1100101 -
#1010
b11001 !
b11001 5
b11001 8
b1 9
b100 :
b11001 7
0"
b11001 6
b1001 '
b1001 2
b1 +
b1 4
0*
0,
b11001 (
b1100110 -
#1020
b11101110 !
b11101110 5
b10010 8
b111 :
b11101110 7
0"
b10010010 6
b10 '
b10 2
1,
b11101110 (
b1100111 -
#1030
b111010 !
b111010 5
b111010 8
b101 :
b1 9
b111010 7
0"
b111010 6
b11010 '
b11010 2
b10 )
b10 3
0,
b111010 (
b1101000 -
#1040
b10110000 !
b10110000 5
b1010000 8
b10 9
b101 :
b10110000 7
0"
b11010000 6
b10000 '
b10000 2
b10 +
b10 4
1*
1,
b10110000 (
b1101001 -
#1050
b10010101 !
b10010101 5
b10010101 7
b1101011 8
b100 :
b0 9
0"
b11101011 6
b1011 '
b1011 2
b110 +
b110 4
b11 )
b11 3
b10010101 (
b1101010 -
#1060
b11111110 !
b11111110 5
b11111110 7
b10 8
b1 :
b0 9
0"
b10000010 6
b0 '
b0 2
b1 +
b1 4
b110 )
b110 3
0*
b11111110 (
b1101011 -
#1070
b11111 !
b11111 5
b11111 8
b1 9
b100 :
b11111 7
0"
b11111 6
b1111 '
b1111 2
b11 )
b11 3
0,
b11111 (
b1101100 -
#1080
b1010100 !
b1010100 5
b1010100 8
b1010100 7
b101 :
b0 9
0"
b1010100 6
b10100 '
b10100 2
b10 +
b10 4
b10 )
b10 3
1*
b1010100 (
b1101101 -
#1090
b11001101 !
b11001101 5
b110011 8
b101 :
b1 9
b11001101 7
0"
b10110011 6
b10011 '
b10011 2
b1 +
b1 4
0*
1,
b11001101 (
b1101110 -
#1100
b11000101 !
b11000101 5
b11000101 7
b111011 8
0"
b10111011 6
b11011 '
b11011 2
b11000101 (
b1101111 -
#1110
b1110101 !
b1110101 5
b1110101 8
b11 :
b0 9
b1110101 7
0"
b1110101 6
b101 '
b101 2
b1110 +
b1110 4
b100 )
b100 3
1*
0,
b1110101 (
b1110000 -
#1120
b11100010 !
b11100010 5
b11110 8
b100 :
b0 9
b11100010 7
0"
b10011110 6
b1110 '
b1110 2
b1 +
b1 4
b11 )
b11 3
0*
1,
b11100010 (
b1110001 -
#1130
b1010 !
b1010 5
b1010 8
b1 9
b11 :
b1010 7
0"
b1010 6
b10 '
b10 2
b100 )
b100 3
0,
b1010 (
b1110010 -
#1140
b10110001 !
b10110001 5
b1001111 8
b0 9
b101 :
b10110001 7
0"
b11001111 6
b1111 '
b1111 2
b10 +
b10 4
b10 )
b10 3
1*
1,
b10110001 (
b1110011 -
#1150
b10101 !
b10101 5
b10101 8
b0 9
b100 :
b10101 7
0"
b10101 6
b101 '
b101 2
b1 +
b1 4
b11 )
b11 3
0*
0,
b10101 (
b1110100 -
#1160
b10111100 !
b10111100 5
b1000100 8
b101 :
b0 9
b10111100 7
0"
b11000100 6
b100 '
b100 2
b10 +
b10 4
b10 )
b10 3
1*
1,
b10111100 (
b1110101 -
#1170
b1010011 !
b1010011 5
b1010011 8
b111 :
b1010011 7
0"
b1010011 6
b10011 '
b10011 2
0,
b1010011 (
b1110110 -
#1180
b100 !
b100 5
b100 8
b100 7
b10 :
b0 9
0"
b100 6
b0 '
b0 2
b1 +
b1 4
b101 )
b101 3
0*
b100 (
b1110111 -
#1190
b10011010 !
b10011010 5
b1100110 8
b100 :
b0 9
b10011010 7
0"
b11100110 6
b110 '
b110 2
b110 +
b110 4
b11 )
b11 3
1*
1,
b10011010 (
b1111000 -
#1200
b10001010 !
b10001010 5
b10001010 7
b1110110 8
b11110110 6
b11 :
b0 9
0"
b1110 +
b1110 4
b100 )
b100 3
b10001010 (
b1111001 -
#1210
b10000111 !
b10000111 5
b10000111 7
b1111001 8
b10 :
b0 9
0"
b11111001 6
b1 '
b1 2
b11110 +
b11110 4
b101 )
b101 3
b10000111 (
b1111010 -
#1220
b11111000 !
b11111000 5
b11111000 7
b1000 8
b11 :
b0 9
0"
b10001000 6
b0 '
b0 2
b1 +
b1 4
b100 )
b100 3
0*
b11111000 (
b1111011 -
#1230
b10100111 !
b10100111 5
b10100111 7
b1011001 8
b101 :
b0 9
0"
b11011001 6
b11001 '
b11001 2
b10 +
b10 4
b10 )
b10 3
1*
b10100111 (
b1111100 -
#1240
b10011 !
b10011 5
b10011 8
b0 9
b100 :
b10011 7
0"
b10011 6
b11 '
b11 2
b1 +
b1 4
b11 )
b11 3
0*
0,
b10011 (
b1111101 -
#1250
b1001011 !
b1001011 5
b1001011 8
b1001011 7
b101 :
b0 9
0"
b1001011 6
b1011 '
b1011 2
b10 +
b10 4
b10 )
b10 3
1*
b1001011 (
b1111110 -
#1260
b11000000 !
b11000000 5
b1000000 8
b111 :
b1 9
b11000000 7
0"
b11000000 6
b0 '
b0 2
1,
b11000000 (
b1111111 -
#1270
b1110001 !
b1110001 5
b1110001 8
b11 :
b0 9
b1110001 7
0"
b1110001 6
b1 '
b1 2
b1110 +
b1110 4
b100 )
b100 3
0,
b1110001 (
b10000000 -
#1280
b10101010 !
b10101010 5
b1010110 8
b101 :
b0 9
b10101010 7
0"
b11010110 6
b10110 '
b10110 2
b10 +
b10 4
b10 )
b10 3
1,
b10101010 (
b10000001 -
#1290
b10101000 !
b10101000 5
b10101000 7
b1011000 8
0"
b11011000 6
b11000 '
b11000 2
b10101000 (
b10000010 -
#1300
b100000 !
b100000 5
b100000 8
b1 9
b101 :
b100000 7
0"
b100000 6
b0 '
b0 2
b1 +
b1 4
0*
0,
b100000 (
b10000011 -
#1310
b110000 !
b110000 5
b110000 8
b110000 7
0"
b110000 6
b10000 '
b10000 2
b110000 (
b10000100 -
#1320
b11101000 !
b11101000 5
b11000 8
b1 9
b100 :
b11101000 7
0"
b10011000 6
b1000 '
b1000 2
b11 )
b11 3
1,
b11101000 (
b10000101 -
#1330
b11101111 !
b11101111 5
b11101111 7
b10001 8
0"
b10010001 6
b1 '
b1 2
b11101111 (
b10000110 -
#1340
b11011010 !
b11011010 5
b11011010 7
b100110 8
b101 :
b1 9
0"
b10100110 6
b110 '
b110 2
b10 )
b10 3
b11011010 (
b10000111 -
#1350
b10000110 !
b10000110 5
b10000110 7
b1111010 8
b10 :
b0 9
0"
b11111010 6
b10 '
b10 2
b11110 +
b11110 4
b101 )
b101 3
1*
b10000110 (
b10001000 -
#1360
b11000110 !
b11000110 5
b11000110 7
b111010 8
b101 :
b0 9
0"
b10111010 6
b11010 '
b11010 2
b1 +
b1 4
b10 )
b10 3
0*
b11000110 (
b10001001 -
#1370
b101110 !
b101110 5
b101110 8
b111 :
b101110 7
0"
b101110 6
b1110 '
b1110 2
0,
b101110 (
b10001010 -
#1380
b11110101 !
b11110101 5
b1011 8
b11 :
b1 9
b11110101 7
0"
b10001011 6
b11 '
b11 2
b100 )
b100 3
1,
b11110101 (
b10001011 -
#1390
b10010111 !
b10010111 5
b10010111 7
b1101001 8
b100 :
b0 9
0"
b11101001 6
b1001 '
b1001 2
b110 +
b110 4
b11 )
b11 3
1*
b10010111 (
b10001100 -
#1400
b10001011 !
b10001011 5
b10001011 7
b1110101 8
b11 :
b0 9
0"
b11110101 6
b101 '
b101 2
b1110 +
b1110 4
b100 )
b100 3
b10001011 (
b10001101 -
