src/p8e0/p8e0_mul.sv
/*
 *  Fri Nov 12 18:00:09 CET 2021
 *
 *  p8e0_mul
 *
 *  ===================================
 *  notes:
 *  Wed Nov 17 18:55:24 CET 2021
 *     - todo: fix inferred latches 
 *
 *
 *  ~/Documents/dev/yosys/yosys -p "synth_intel -family max10 -top p8e0_mul -vqm p8e0_mul.vqm" p8e0_mul.sv > yosys.out
 *  iverilog -D POST_IMPL -o verif_post -s p8e0_mul p8e0_mul.sv  $(yosys-config --datdir/intel/max10/cells_sim.v) && vvp -N verif_post
 */


module p8e0_mul(
        input      [7:0]    a,
        input      [7:0]    b,
`ifdef PROBE_SIGNALS
        output logic [7:0]    ui_a,   ui_b,
        output logic [7:0]    k_a,    k_b,
        output logic [7:0]    frac_a, frac_b,
        output logic [7:0]    k_c,
        output logic [15:0]   frac16,
        output logic          rcarry,
`endif
        output /* wire */           is_zero,
        output    wire     is_nar,
        output logic [7:0]    z
    );

    /*=============== functions ==================*/
    function [7:0] c2(input [7:0] a);
        c2 = ~a + 1'b1;
    endfunction

    function [15:0] separate_bits(
            input [7:0] bits
        );
        begin: _separate_bits
            logic [7:0] k;
            logic [7:0] tmp;
            logic [7:0] reg_length;
            logic first_regime_bit;

            first_regime_bit = (bits & 8'h40) >> 6 == 1;

            casex (bits)
                8'bx0000001: k = -6;
                8'bx000001x: k = -5;
                8'bx00001xx: k = -4;
                8'bx0001xxx: k = -3;
                8'bx001xxxx: k = -2;
                8'bx01xxxxx: k = -1;
                8'bx10xxxxx: k =  0;
                8'bx110xxxx: k =  1;
                8'bx1110xxx: k =  2;
                8'bx11110xx: k =  3;
                8'bx111110x: k =  4;
                8'bx1111110: k =  5;
                8'bx1111111: k =  6;
                default:     k =  8'hff; // never occurs
            endcase
            
            reg_length = 1 + 
                         (first_regime_bit == 1'b1 ? k + 1 : c2(k));

            if (reg_length == 8) reg_length = 7;                            // <---- is this line unnecessary?

            tmp = ((bits << reg_length) & 8'h7f) | 8'h80;

            separate_bits = {k, tmp};
        end
    endfunction

    /*
    function [7:0] calc_ui(
            input [7:0] k,
            input [7:0] frac16
        );
        begin: _calc_ui
            logic [7:0] regime;               // 8 bits
            logic       reg_s;                // 1 bit
            logic [7:0] reg_len;              // 8 bits
            
            logic       bits_more;

            {regime, reg_s, reg_len} = calculate_regime(k);
            
            if (reg_len > 6) begin
                if (reg_s)  calc_ui = 8'h7f;
                else        calc_ui = 8'h01;
            end else begin
                frac16 = (frac16 & 16'h3fff) >> reg_len;
                calc_ui = regime + (frac16 >> 8);
                if ((frac16 & 8'h80) != 0) begin
                    bits_more = (frac16 & 8'h7f) != 0;
                    calc_ui = calc_ui + ((calc_ui & 1'b1) | bits_more);
                end
            end
        end
    endfunction
    */

    function [(8+1+8)-1:0] calculate_regime(
            input [7:0] k
        );
        begin: _calculate_regime
            logic [7:0] regime;
            logic       reg_s; 
            logic [7:0] length;

            if (k & 8'h80) begin
            //  └── check if k is negative
                length = c2(k);
                regime = checked_shr(8'h40, length);
                reg_s = 1'b0;
            end else begin
                length = k + 1;
                regime = 8'h7f - checked_shr(8'h7f, length);
                reg_s = 1'b1;
            end
            calculate_regime = {regime, reg_s, length};
        end
    endfunction

    function [7:0] checked_shr(
            input [7:0] bits,
            input [7:0] rhs   
        );
        checked_shr = bits >> rhs;
    endfunction
    /*============= endfunctions ================*/

    logic sign_a, sign_b, sign_z;

`ifndef PROBE_SIGNALS
    logic [7:0]  ui_a, ui_b;
    logic [7:0]  k_a,    k_b;
    logic [7:0]  frac_a, frac_b;

    logic [7:0]  k_c;
    logic [15:0] frac16;

    logic        rcarry;
`endif


    // calc_ui regs
    logic [7:0] regime;               // 8 bits
    logic       reg_s;                // 1 bit
    logic [7:0] reg_len;              // 8 bits
    // end calc_ui regs

    logic [7:0] frac;
    logic       bits_more;
    
    logic [7:0] u_z;

    always_comb begin

      //////  z = 0; // always comb does not infer purely combinational logic? 

        if (a == 0 || b == 0 || a == 8'h80 || b == 8'h80) begin
            if (a == 0 || b == 0) begin
                z = 0;
            end else if (a == 8'h80  || b == 8'h80) begin
                z = 8'h80;
            end
            ui_a = 0;
            ui_b = 0;
            k_a = 0;
            k_b = 0;
            k_c = 0;
            sign_a = 0;
            sign_b = 0;
            sign_z = 0;
            frac_a = 0; 
            frac_b = 0;
            frac16 = 0;
            rcarry = 0;
            u_z = 0;
            
            reg_len = 0;
            regime = 0;
            reg_s = 0;

        end else begin
            sign_a = (a & 8'h80) >> 7;
            sign_b = (b & 8'h80) >> 7;
            sign_z = sign_a ^ sign_b;

            ui_a = sign_a == 0 ? a : c2(a);
            ui_b = sign_b == 0 ? b : c2(b);

            {k_a, frac_a} = separate_bits(ui_a);
            {k_b, frac_b} = separate_bits(ui_b);

            k_c = k_a + k_b;
            frac16 = frac_a * frac_b;
            rcarry = (frac16 & 16'h8000) != 0;

            if (rcarry) begin
                k_c = k_c + 1'b1;
                frac16 = frac16 >> 1;
            end else begin
                k_c = k_c;
                frac16 = frac16;
            end


            // calc_ui function            
            {regime, reg_s, reg_len} = calculate_regime(k_c);
            if (reg_len > 6) begin
                case (reg_s)
                    1'b1: u_z = 8'h7f;
                    1'b0: u_z = 8'h01;
                endcase
            end else begin
                frac16 = (frac16 & 16'h3fff) >> reg_len;
                u_z = regime + (frac16 >> 8);
                if ((frac16 & 8'h80) != 0) begin
                    u_z = u_z + ( (u_z & 1'b1) | ((frac16 & 8'h7f) != 0) );
                end
            end
            
            // u_z = calc_ui(k_c, frac16);

            z = sign_z == 0 ? u_z : c2(u_z);
        end
    end

    assign is_zero = z == 0   ? 1 : 0;
    assign is_nar  = z == 8'h80 ? 1 : 0;

endmodule

src/p8e0/tb_p8e0_mul.template.sv

// iverilog -g2012 -DPROBE_SIGNALS p8e0_mul.sv tb_p8e0_mul.sv && ./a.out

// synopsys translate_off                   // <- include guards for quartus (et al.) so that he ingores this
module tb_p8e0_mul;

    localparam ZERO = 'h0;
    localparam P8_NAR = 8'h80;
    /// localparam UNDEFINED = 'hz; // generic, no length specified.

    function diff(
            input [7:0] reference,
            input [7:0] expected
        );
        diff = reference === expected ? 0 : 1'bx;
    endfunction

    logic  [7:0]  a, b;
    wire [7:0]  ui_a, ui_b;
    
    logic  [100:0] a_ascii, b_ascii, z_ascii;

    wire [7:0]  z;
    wire        is_zero;
    wire        is_nar;

    wire [7:0]  k_a, k_b;
    wire [7:0]  frac_a, frac_b;
    wire [7:0]  k_c;
    wire [15:0] frac16;
    wire        rcarry;

    p8e0_mul p8e0_mul_inst(
        .a      (a),
        .b      (b),
`ifdef PROBE_SIGNALS
        .ui_a   (ui_a),
        .ui_b   (ui_b),
        .k_a    (k_a),
        .k_b    (k_b),
        .frac_a (frac_a),
        .frac_b (frac_b),
        .k_c    (k_c),
        .rcarry (rcarry),
        .frac16 (frac16),
`endif
        .is_zero(is_zero),
        .is_nar (is_nar),
        .z      (z)
    );

    logic [7:0] z_exp;
    logic diff_z;


// `ifdef PROBE_SIGNALS
    logic [7:0] ui_a_exp, ui_b_exp;
    logic [7:0] k_a_exp, k_b_exp, k_c_exp;
    
    logic rcarry_exp;

    logic [7:0] frac_a_exp, frac_b_exp;
    logic [15:0] frac16_exp;

    logic diff_ui_a, diff_ui_b,
        diff_k_a, diff_k_b, diff_k_c,
        diff_rcarry,
        diff_frac_a, diff_frac_b,
        diff_frac16;

    integer test_no;
        
// `endif

    always_comb begin
        diff_z   = diff(z, z_exp);
`ifdef PROBE_SIGNALS
        diff_ui_a = diff(ui_a, ui_a_exp);
        diff_ui_b = diff(ui_b, ui_b_exp);
        diff_k_a = diff(k_a, k_a_exp);
        diff_k_b = diff(k_b, k_b_exp);
        diff_k_c = diff(k_c, k_c_exp);
        diff_rcarry = diff(rcarry, rcarry_exp);
        diff_frac_a = diff(frac_a, frac_a_exp);
        diff_frac_b = diff(frac_b, frac_b_exp);
        diff_frac16 = diff(frac16, frac16_exp);
`endif
    end

    initial begin
`ifdef PROBE_SIGNALS
        $dumpfile("tb_p8e0_mul.vcd");
        $display("probe defined");
`else
        $dumpfile("tb_p8e0_mul_noprobe.vcd");
        $display("probe NOT defined");
`endif
        $dumpvars(0, tb_p8e0_mul);
    end

    initial begin
                

    /*{add stuff here}*/


    end
endmodule
// synopsys translate_on

src/p8e0/tb_p8e0_mul.vcd
$date
	Fri Nov 19 11:40:24 2021
$end
$version
	Icarus Verilog
$end
$timescale
	1s
$end
$scope module tb_p8e0_mul $end
$var wire 8 ! z [7:0] $end
$var wire 8 " ui_b [7:0] $end
$var wire 8 # ui_a [7:0] $end
$var wire 1 $ rcarry $end
$var wire 8 % k_c [7:0] $end
$var wire 8 & k_b [7:0] $end
$var wire 8 ' k_a [7:0] $end
$var wire 1 ( is_zero $end
$var wire 1 ) is_nar $end
$var wire 8 * frac_b [7:0] $end
$var wire 8 + frac_a [7:0] $end
$var wire 16 , frac16 [15:0] $end
$var reg 8 - a [7:0] $end
$var reg 101 . a_ascii [100:0] $end
$var reg 8 / b [7:0] $end
$var reg 101 0 b_ascii [100:0] $end
$var reg 1 1 diff_frac16 $end
$var reg 1 2 diff_frac_a $end
$var reg 1 3 diff_frac_b $end
$var reg 1 4 diff_k_a $end
$var reg 1 5 diff_k_b $end
$var reg 1 6 diff_k_c $end
$var reg 1 7 diff_rcarry $end
$var reg 1 8 diff_ui_a $end
$var reg 1 9 diff_ui_b $end
$var reg 1 : diff_z $end
$var reg 16 ; frac16_exp [15:0] $end
$var reg 8 < frac_a_exp [7:0] $end
$var reg 8 = frac_b_exp [7:0] $end
$var reg 8 > k_a_exp [7:0] $end
$var reg 8 ? k_b_exp [7:0] $end
$var reg 8 @ k_c_exp [7:0] $end
$var reg 1 A rcarry_exp $end
$var reg 8 B ui_a_exp [7:0] $end
$var reg 8 C ui_b_exp [7:0] $end
$var reg 101 D z_ascii [100:0] $end
$var reg 8 E z_exp [7:0] $end
$var integer 32 F test_no [31:0] $end
$scope function diff $end
$var reg 8 G expected [7:0] $end
$var reg 8 H reference [7:0] $end
$upscope $end
$scope module p8e0_mul_inst $end
$var wire 8 I a [7:0] $end
$var wire 8 J b [7:0] $end
$var wire 1 ( is_zero $end
$var wire 1 ) is_nar $end
$var reg 16 K frac16 [15:0] $end
$var reg 8 L frac_a [7:0] $end
$var reg 8 M frac_b [7:0] $end
$var reg 8 N k_a [7:0] $end
$var reg 8 O k_b [7:0] $end
$var reg 8 P k_c [7:0] $end
$var reg 1 $ rcarry $end
$var reg 8 Q reg_len [7:0] $end
$var reg 1 R reg_s $end
$var reg 8 S regime [7:0] $end
$var reg 1 T sign_a $end
$var reg 1 U sign_b $end
$var reg 1 V sign_z $end
$var reg 8 W u_z [7:0] $end
$var reg 8 X ui_a [7:0] $end
$var reg 8 Y ui_b [7:0] $end
$var reg 8 Z z [7:0] $end
$scope function c2 $end
$var reg 8 [ a [7:0] $end
$upscope $end
$scope function calculate_regime $end
$var reg 8 \ k [7:0] $end
$scope begin _calculate_regime $end
$var reg 8 ] length [7:0] $end
$var reg 1 ^ reg_s $end
$var reg 8 _ regime [7:0] $end
$upscope $end
$upscope $end
$scope function checked_shr $end
$var reg 8 ` bits [7:0] $end
$var reg 8 a rhs [7:0] $end
$upscope $end
$scope function separate_bits $end
$var reg 8 b bits [7:0] $end
$scope begin _separate_bits $end
$var reg 1 c first_regime_bit $end
$var reg 8 d k [7:0] $end
$var reg 8 e reg_length [7:0] $end
$var reg 8 f tmp [7:0] $end
$upscope $end
$upscope $end
$upscope $end
$upscope $end
$enddefinitions $end
#0
$dumpvars
bx f
bx e
bx d
xc
bx b
bx a
bx `
bx _
x^
bx ]
bx \
bx [
b0 Z
b0 Y
b0 X
b0 W
0V
0U
0T
b0 S
0R
b0 Q
b0 P
b0 O
b0 N
b0 M
b0 L
b0 K
b11 J
b0 I
b0 H
b0 G
b1 F
b0 E
b1100000010111000110000 D
b0 C
b0 B
0A
b0 @
b0 ?
b0 >
b0 =
b0 <
b0 ;
0:
09
08
07
06
05
04
03
02
01
b11000000101110001100000011010000110110001110000011011100110101 0
b11 /
b1100000010111000110000 .
b0 -
b0 ,
b0 +
b0 *
0)
1(
b0 '
b0 &
b0 %
0$
b0 #
b0 "
b0 !
$end
#10
0(
1)
b0 H
b0 G
b10000000 !
b10000000 Z
b11011100110000101101110 D
b10000000 E
b101101001101000010111000110000 0
b11011100110000101101110 .
b10010000 /
b10010000 J
b10000000 -
b10000000 I
b10 F
#20
0)
b1011110 H
b1011110 G
b10010000 !
b10010000 Z
b1110000 W
b1110000 S
1R
b11 Q
1^
b1110000 _
b1111111 `
b11 a
b11 ]
b10 \
1$
b1011110 ,
b1011110 K
b10 %
b10 P
b1 &
b1 O
b10101000 *
b10101000 M
b11001100 +
b11001100 L
b10101000 f
b11 e
b1 d
1c
b1100101 b
b1100101 "
b1100101 Y
b1110000 [
b1010011 #
b1010011 X
1V
1U
b101101001101000010111000110000 D
b10010000 E
1A
b1011110 ;
b10101000 =
b11001100 <
b10 @
b1 ?
b1100101 C
b1010011 B
b1011010011001000101110001101100011001000110101 0
b110001001011100011010100111001001100110011011100110101 .
b10011011 /
b10011011 J
b1010011 -
b1010011 I
b11 F
#30
b10000000 H
b10000000 G
b10100000 !
b10100000 Z
b1100000 W
b1100000 S
b10 Q
b1100000 _
b10 a
b10 ]
b1 \
b10000000 ,
b10000000 K
b1 %
b1 P
b0 &
b0 O
b11000000 *
b11000000 M
b10110000 +
b10110000 L
b11000000 f
b10 e
b0 d
b1010000 b
b1010000 "
b1010000 Y
b1001100 #
b1001100 X
b1100000 [
0U
1T
b101101001100100010111000110000 D
b10100000 E
b10000000 ;
b11000000 =
b10110000 <
b1 @
b0 ?
b1010000 C
b1001100 B
b1100010010111000110101 0
b1011010011000100101110001100110011011100110101 .
b1010000 /
b1010000 J
b10110100 -
b10110100 I
b100 F
#40
b11101100 H
b11101100 G
b11101100 !
b11101100 Z
b10100 W
b10000 S
0R
0^
b10000 _
b1000000 `
b11111110 \
b1111101100 ,
b1111101100 K
b11111110 %
b11111110 P
b11111111 &
b11111111 O
b11001100 *
b11001100 M
b11111110 '
b11111110 N
b11001000 +
b11001000 L
b11001100 f
b10 e
b11111111 d
0c
b110011 b
b110011 "
b110011 Y
b11001 #
b11001 X
b10100 [
b101101001100000010111000110011001100010011001000110101 D
b11101100 E
b1111101100 ;
b11001100 =
b11001000 <
b11111110 @
b11111111 ?
b11111110 >
b110011 C
b11001 B
b11000000101110001101110011100100110110001110000011011100110101 0
b1011010011000000101110001100110011100100110000001101100011001000110101 .
b110011 /
b110011 J
b11100111 -
b11100111 I
b101 F
#50
b10010000 H
b10010000 G
b1010101 !
b1010101 Z
b1010101 W
b1000000 S
1R
b1 Q
1^
b1000000 _
b1111111 `
b1 a
b1 ]
b0 \
b1010010010000 ,
b1010010010000 K
b0 %
b0 P
b0 &
b0 O
b11101000 *
b11101000 M
b0 d
1c
b11111111 '
b11111111 N
b11101000 +
b11101000 L
b11101000 f
b1011010 b
b1011010 "
b1011010 Y
b111010 #
b111010 X
b11111111 [
0V
1U
b110001001011100011011000110101001101100011001000110101 D
b1010101 E
b1010010010000 ;
b11101000 =
b11101000 <
b0 @
b0 ?
b11111111 >
b1011010 C
b111010 B
b101101001100010010111000111000001100010011001000110101 0
b10110100110000001011100011100100110000001101100011001000110101 .
b10100110 /
b10100110 J
b11000110 -
b11000110 I
b110 F
#60
b111000 H
b111000 G
b110001 !
b110001 Z
b110001 W
b100000 S
0R
0^
b100000 _
b1000000 `
b11111111 \
0$
b1000100111000 ,
b1000100111000 K
b11111111 %
b11111111 P
b10110100 *
b10110100 M
b10001100 +
b10001100 L
b10110100 f
b0 d
1c
b1001101 b
b1001101 "
b1001101 Y
b100011 #
b100011 X
0U
0T
b11000000101110001101110011011000110101001101100011001000110101 D
b110001 E
0A
b1000100111000 ;
b10110100 =
b10001100 <
b11111111 @
b1001101 C
b100011 B
b110001001011100011010000110000001101100011001000110101 0
b11000000101110001101010011010000110110001110000011011100110101 .
b1001101 /
b1001101 J
b100011 -
b100011 I
b111 F
#70
b0 H
b0 G
b1010001 !
b1010001 Z
b1010001 W
b1000000 S
1R
1^
b1000000 _
b1111111 `
b0 \
b0 %
b0 P
1$
b1000100000000 ,
b1000100000000 K
b11100000 *
b11100000 M
b11100000 +
b11100000 L
b11100000 f
b0 d
1c
b1011000 b
b1011000 "
b1011000 Y
b111000 #
b111000 X
b110001001011100011010100110011001100010011001000110101 D
b1010001 E
1A
b1000100000000 ;
b11100000 =
b11100000 <
b0 @
b1011000 C
b111000 B
b110001001011100011011100110101 0
b11000000101110001110000011011100110101 .
b1011000 /
b1011000 J
b111000 -
b111000 I
b1000 F
#80
b11001000 H
b11001000 G
b11111110 !
b11111110 Z
b10 W
b1 S
0R
b110 Q
0^
b1 _
b1000000 `
b110 a
b110 ]
b11111010 \
0$
b11001000 ,
b11001000 K
b11111010 %
b11111010 P
b11111110 &
b11111110 O
b10011000 *
b10011000 M
b11111100 '
b11111100 N
b11000000 +
b11000000 L
b10011000 f
b11 e
b11111110 d
0c
b10011 b
b10011 "
b10011 Y
b110 #
b110 X
b10 [
1V
1T
b10110100110000001011100011000000110011001100010011001000110101 D
b11111110 E
0A
b11001000 ;
b10011000 =
b11000000 <
b11111010 @
b11111110 ?
b11111100 >
b10011 C
b110 B
b11000000101110001100100011100100110110001110000011011100110101 0
b10110100110000001011100011000000111001001100110011011100110101 .
b10011 /
b10011 J
b11111010 -
b11111010 I
b1001 F
#90
1(
b0 H
b0 G
b0 S
b0 Q
b0 W
b0 ,
b0 K
b0 *
b0 M
b0 +
b0 L
0V
0T
b0 %
b0 P
b0 &
b0 O
b0 '
b0 N
b0 "
b0 Y
b0 #
b0 X
b0 !
b0 Z
b1100000010111000110000 D
b0 E
b0 ;
b0 =
b0 <
b0 @
b0 ?
b0 >
b0 C
b0 B
b11001000101110001100010011001000110101 0
b1100000010111000110000 .
b1100001 /
b1100001 J
b0 -
b0 I
b1010 F
#100
0(
b100000 H
b100000 G
b100100 !
b100100 Z
b100100 W
b100000 S
b1 Q
b100000 _
b1 a
b1 ]
b11111111 \
b10000100000 ,
b10000100000 K
b11111111 %
b11111111 P
b10001000 *
b10001000 M
1c
b11111111 '
b11111111 N
b10001000 +
b10001000 L
b10001000 f
b10 e
b0 d
b1000010 b
b1000010 "
b1000010 Y
b100010 #
b100010 X
b11111111 [
1U
1T
b1100000010111000110101001101100011001000110101 D
b100100 E
b10000100000 ;
b10001000 =
b10001000 <
b11111111 @
b11111111 >
b1000010 C
b100010 B
b101101001100010010111000110000001101100011001000110101 0
b10110100110000001011100011010100110011001100010011001000110101 .
b10111110 /
b10111110 J
b11011110 -
b11011110 I
b1011 F
#110
b11100000 H
b11100000 G
b1100001 !
b1100001 Z
b1100001 W
b1100000 S
1R
b10 Q
1^
b1100000 _
b1111111 `
b10 a
b10 ]
b1 \
1$
b11100000 ,
b11100000 K
b1 %
b1 P
b11110000 *
b11110000 M
b0 '
b0 N
b10010000 +
b10010000 L
b11110000 f
b1011100 b
b1011100 "
b1011100 Y
b1000100 #
b1000100 X
0U
0T
b11001000101110001100010011001000110101 D
b1100001 E
1A
b11100000 ;
b11110000 =
b10010000 <
b1 @
b0 >
b1011100 C
b1000100 B
b11000100101110001110000011011100110101 0
b11000100101110001100010011001000110101 .
b1011100 /
b1011100 J
b1000100 -
b1000100 I
b1100 F
#120
b11011000 H
b11011000 G
b101000 !
b101000 Z
b101000 W
b100000 S
0R
b1 Q
0^
b100000 _
b1000000 `
b1 a
b1 ]
b11111111 \
b11111011000 ,
b11111011000 K
b11111111 %
b11111111 P
b11111110 &
b11111110 O
b11001000 *
b11001000 M
b11 e
b11111111 [
b11111110 d
0c
b11001100 +
b11001100 L
b11001000 f
b11001 b
b11001 "
b11001 Y
b1010011 #
b1010011 X
b11000000101110001101100011001000110101 D
b101000 E
b11111011000 ;
b11001000 =
b11001100 <
b11111111 @
b11111110 ?
b11001 C
b1010011 B
b11000000101110001100110011100100110000001101100011001000110101 0
b110001001011100011010100111001001100110011011100110101 .
b11001 /
b11001 J
b1010011 -
b1010011 I
b1101 F
#130
b10000 H
b10000 G
b1110110 !
b1110110 Z
b1110110 W
b1110000 S
1R
b11 Q
1^
b1110000 _
b1111111 `
b11 a
b11 ]
b10 \
b11000010000 ,
b11000010000 K
b10 %
b10 P
b11111111 &
b11111111 O
b11110000 *
b11110000 M
b10 '
b10 N
b11110000 +
b11110000 L
b11110000 f
b10 e
b11111111 d
0c
b111100 b
b111100 "
b111100 Y
b1110111 #
b1110111 X
b11111111 [
1U
1T
b1101110010111000110000 D
b1110110 E
b11000010000 ;
b11110000 =
b11110000 <
b10 @
b11111111 ?
b10 >
b111100 C
b1110111 B
b101101001100000010111000111001001100110011011100110101 0
b101101001101110010111000110101 .
b11000100 /
b11000100 J
b10001001 -
b10001001 I
b1110 F
#140
b1000100 H
b1000100 G
b10011010 !
b10011010 Z
b1100110 W
b1100000 S
b10 Q
b1100000 _
b10 a
b10 ]
b1 \
b11001000100 ,
b11001000100 K
b1 %
b1 P
b0 &
b0 O
b11100100 *
b11100100 M
b0 '
b0 N
b11001000 +
b11001000 L
b11100100 f
b0 d
1c
b1011001 b
b1011001 "
b1011001 Y
b1010010 #
b1010010 X
b1100110 [
1V
0U
b10110100110010001011100011011100110101 D
b10011010 E
b11001000100 ;
b11100100 =
b11001000 <
b1 @
b0 ?
b0 >
b1011001 C
b1010010 B
b110001001011100011011100111000001100010011001000110101 0
b101101001100010010111000110101001101100011001000110101 .
b1011001 /
b1011001 J
b10101110 -
b10101110 I
b1111 F
#150
b111010 H
b111010 G
b1110000 !
b1110000 Z
b1110000 W
b1110000 S
b11 Q
b1110000 _
b11 a
b11 ]
b10 \
b10 %
b10 P
b111010 ,
b111010 K
b10011100 *
b10011100 M
b1 '
b1 N
b11011000 +
b11011000 L
b10011100 f
b10 e
b0 d
b1000111 b
b1000111 "
b1000111 Y
b1101011 #
b1101011 X
0V
0T
b1101000010111000110000 D
b1110000 E
b111010 ;
b10011100 =
b11011000 <
b10 @
b1 >
b1000111 C
b1101011 B
b110001001011100011001000110001001110000011011100110101 0
b11001100101110001100110011011100110101 .
b1000111 /
b1000111 J
b1101011 -
b1101011 I
b10000 F
#160
b1111000 H
b1111000 G
b101 !
b101 Z
b101 W
b100 S
0R
b100 Q
0^
b100 _
b1000000 `
b100 a
b100 ]
b11111100 \
0$
b101111000 ,
b101111000 K
b11111100 %
b11111100 P
b10001100 *
b10001100 M
b11111100 '
b11111100 N
b10100000 +
b10100000 L
b10001100 f
b10 e
b11111100 [
b0 d
1c
b1000011 b
b1000011 "
b1000011 Y
b101 #
b101 X
b11000000101110001100000011011100111000001100010011001000110101 D
b101 E
0A
b101111000 ;
b10001100 =
b10100000 <
b11111100 @
b11111100 >
b1000011 C
b101 B
b110001001011100011000000111001001100110011011100110101 0
b11000000101110001100000011011100111000001100010011001000110101 .
b1000011 /
b1000011 J
b101 -
b101 I
b10001 F
#170
b1000000 H
b1000000 G
b1011 !
b1011 Z
b1011 W
b1000 S
b11 Q
b1000 _
b11 a
b11 ]
b11111101 \
b1101000000 ,
b1101000000 K
b11111101 %
b11111101 P
b10010000 *
b10010000 M
b11111101 '
b11111101 N
b10010000 f
b10 e
b11111101 [
b0 d
1c
b1000100 b
b1000100 "
b1000100 Y
b1010 #
b1010 X
b11000000101110001100010011011100110001001110000011011100110101 D
b1011 E
b1101000000 ;
b10010000 =
b11111101 @
b11111101 >
b1000100 C
b1010 B
b11000100101110001100010011001000110101 0
b110000001011100011000100110101001101100011001000110101 .
b1000100 /
b1000100 J
b1010 -
b1010 I
b10010 F
#180
b10000000 H
b10000000 G
b10011000 !
b10011000 Z
b1101000 W
b1100000 S
1R
b10 Q
1^
b1100000 _
b1111111 `
b10 a
b10 ]
b1 \
b11110000000 ,
b11110000000 K
b1 %
b1 P
b1 &
b1 O
b10000000 *
b10000000 M
b11 e
b1 d
b0 '
b0 N
b10111100 +
b10111100 L
b10000000 f
b1100000 b
b1100000 "
b1100000 Y
b1001111 #
b1001111 X
b1101000 [
1V
1T
b101101001100110010111000110000 D
b10011000 E
b11110000000 ;
b10000000 =
b10111100 <
b1 @
b1 ?
b0 >
b1100000 C
b1001111 B
b1100100010111000110000 0
b10110100110001001011100011010000110110001110000011011100110101 .
b1100000 /
b1100000 J
b10110001 -
b10110001 I
b10011 F
#190
b10110000 H
b10110000 G
b11011110 !
b11011110 Z
b100010 W
b100000 S
0R
b1 Q
0^
b100000 _
b1000000 `
b1 a
b1 ]
b11111111 \
1$
b110110000 ,
b110110000 K
b11111111 %
b11111111 P
b11111110 &
b11111110 O
b10110000 *
b10110000 M
0c
b11000100 +
b11000100 L
b10110000 f
b11 e
b11111110 d
b10110 b
b10110 "
b10110 Y
b100010 [
b1010001 #
b1010001 X
1U
0T
b10110100110000001011100011010100110011001100010011001000110101 D
b11011110 E
1A
b110110000 ;
b10110000 =
b11000100 <
b11111111 @
b11111110 ?
b10110 C
b1010001 B
b10110100110000001011100011001100110100001100110011011100110101 0
b110001001011100011010100110011001100010011001000110101 .
b11101010 /
b11101010 J
b1010001 -
b1010001 I
b10100 F
#200
b111000 H
b111000 G
b1111000 !
b1111000 Z
b1111000 W
b1111000 S
1R
b100 Q
1^
b1111000 _
b1111111 `
b100 a
b100 ]
b11 \
b111000 ,
b111000 K
b11 %
b11 P
b10 &
b10 O
b10010000 *
b10010000 M
b11110000 +
b11110000 L
b10010000 f
b100 e
b10 d
1c
b1110001 b
b1110001 "
b1110001 Y
b1011100 #
b1011100 X
0V
0U
b1110000010111000110000 D
b1111000 E
b111000 ;
b10010000 =
b11110000 <
b11 @
b10 ?
b1110001 C
b1011100 B
b1101000010111000110101 0
b11000100101110001110000011011100110101 .
b1110001 /
b1110001 J
b1011100 -
b1011100 I
b10101 F
#210
b11110000 H
b11110000 G
b1101 !
b1101 Z
b1101 W
b1000 S
0R
b11 Q
0^
b1000 _
b1000000 `
b11 a
b11 ]
b11111101 \
0$
b10011110000 ,
b10011110000 K
b11111101 %
b11111101 P
b11111110 &
b11111110 O
b10111000 *
b10111000 M
b10111000 f
b11111111 '
b11111111 N
b10010000 +
b10010000 L
b11 e
b11111101 [
b11111110 d
0c
b10111 b
b10111 "
b10111 Y
b100100 #
b100100 X
b11000000101110001100100011000000110011001100010011001000110101 D
b1101 E
0A
b10011110000 ;
b10111000 =
b10010000 <
b11111101 @
b11111110 ?
b11111111 >
b10111 C
b100100 B
b11000000101110001100110011010100111001001100110011011100110101 0
b1100000010111000110101001101100011001000110101 .
b10111 /
b10111 J
b100100 -
b100100 I
b10110 F
#220
b11100 H
b11100 G
b1111100 !
b1111100 Z
b1111100 W
b1111100 S
1R
b101 Q
1^
b1111100 _
b1111111 `
b101 a
b101 ]
b100 \
1$
b11100 ,
b11100 K
b100 %
b100 P
b11 &
b11 O
b10100000 *
b10100000 M
b0 '
b0 N
b11011000 +
b11011000 L
b10100000 f
b101 e
b11 d
1c
b1111001 b
b1111001 "
b1111001 Y
b1010110 #
b1010110 X
b10000111 [
1U
1T
b110001001101100010111000110000 D
b1111100 E
1A
b11100 ;
b10100000 =
b11011000 <
b100 @
b11 ?
b0 >
b1111001 C
b1010110 B
b10110100110001001100000010111000110000 0
b101101001100010010111000110110001110000011011100110101 .
b10000111 /
b10000111 J
b10101010 -
b10101010 I
b10111 F
#230
b0 H
b0 G
b111110 !
b111110 Z
b111110 W
b100000 S
0R
b1 Q
0^
b100000 _
b1000000 `
b1 a
b1 ]
b11111111 \
0$
b1111000000000 ,
b1111000000000 K
b11111111 %
b11111111 P
b11111111 &
b11111111 O
b10000000 *
b10000000 M
b11111111 [
0c
b11111000 +
b11111000 L
b10000000 f
b10 e
b11111111 d
b100000 b
b100000 "
b100000 Y
b1011110 #
b1011110 X
0U
0T
b110000001011100011100100110110001110000011011100110101 D
b111110 E
0A
b1111000000000 ;
b10000000 =
b11111000 <
b11111111 @
b11111111 ?
b100000 C
b1011110 B
b1100000010111000110101 0
b1100010010111000111001001100110011011100110101 .
b100000 /
b100000 J
b1011110 -
b1011110 I
b11000 F
#240
b100000 H
b100000 G
b1111 !
b1111 Z
b1111 W
b1000 S
b11 Q
b1000 _
b11 a
b11 ]
b11111101 \
b11100100000 ,
b11100100000 K
b11111101 %
b11111101 P
b0 &
b0 O
b10110000 *
b10110000 M
1c
b11111101 '
b11111101 N
b10110000 +
b10110000 L
b10110000 f
b10 e
b0 d
b1001100 b
b1001100 "
b1001100 Y
b1011 #
b1011 X
b11111101 [
1U
1T
b11000000101110001100100011001100110100001100110011011100110101 D
b1111 E
b11100100000 ;
b10110000 =
b10110000 <
b11111101 @
b0 ?
b11111101 >
b1001100 C
b1011 B
b1011010011000100101110001100110011011100110101 0
b1011010011000000101110001100010011011100110001001110000011011100110101 .
b10110100 /
b10110100 J
b11110101 -
b11110101 I
b11001 F
#250
b11110000 H
b11110000 G
b10000 !
b10000 Z
b10000 W
b11111110000 ,
b11111110000 K
b11111111 &
b11111111 O
b11001100 *
b11001100 M
b11111110 '
b11111110 N
b10100000 +
b10100000 L
b11001100 f
b10 e
b11111111 d
0c
b110011 b
b110011 "
b110011 Y
b10100 #
b10100 X
b11111101 [
b110000001011100011001000110101 D
b10000 E
b11111110000 ;
b11001100 =
b10100000 <
b11111111 ?
b11111110 >
b110011 C
b10100 B
b1011010011000000101110001101110011100100110110001110000011011100110101 0
b101101001100000010111000110011001100010011001000110101 .
b11001101 /
b11001101 J
b11101100 -
b11101100 I
b11010 F
