src/p8e0/p8e0_mul.sv
/*
 *  Fri Nov 12 18:00:09 CET 2021
 *
 *  p8e0_mul
 *
 *  ===================================
 *  notes:
 *  Wed Nov 17 18:55:24 CET 2021
 *     - todo: fix inferred latches 
 *
 *  ~/Documents/dev/yosys/yosys -p "synth_intel -family max10 -top p8e0_mul -vqm p8e0_mul.vqm" p8e0_mul.sv > yosys.out
 *  iverilog -D POST_IMPL -o verif_post -s p8e0_mul p8e0_mul.sv  $(yosys-config --datdir/intel/max10/cells_sim.v) && vvp -N verif_post
 */

`define PROBE_SIGNALS

module p8e0_mul(
        input      [7:0]    a,
        input      [7:0]    b,
`ifdef PROBE_SIGNALS
        output reg [7:0]    ui_a, ui_b,
        output reg [7:0]    k_a,    k_b,
        output reg [7:0]    frac_a, frac_b,
        output reg [7:0]    k_c,
        output reg [15:0]   frac16,
        output reg          rcarry,
`endif
        output              is_zero,
        output              is_nar,
        output reg [7:0]    z
    );

    /*=============== functions ==================*/
    function [7:0] c2(input [7:0] a);
        c2 = ~a + 1'b1;
    endfunction

    function [15:0] separate_bits(
            input [7:0] bits
        );
        begin: _separate_bits
            reg [7:0] k;
            reg [7:0] tmp;
            reg [7:0] reg_length;
            
            // {k, tmp} = separate_bits_tmp(bits);
            tmp = 8'h01;

            casex (bits)
                8'bx0000001: k = -6;
                8'bx000001x: k = -5;
                8'bx00001xx: k = -4;
                8'bx0001xxx: k = -3;
                8'bx001xxxx: k = -2;
                8'bx01xxxxx: k = -1;
                8'bx10xxxxx: k =  0;
                8'bx110xxxx: k =  1;
                8'bx1110xxx: k =  2;
                8'bx11110xx: k =  3;
                8'bx111110x: k =  4;
                8'bx1111110: k =  5;
                8'bx1111111: k =  6;
                default:     k =  8'hxx;
            endcase
            reg_length = 1 + (bits[6] == 1'b1 ? k + 1 : -k);
            ////              ^^^^^^-- first (i.e. leftmost) regime bit

            if (reg_length == 8) reg_length = 7;

            tmp = ((bits << reg_length) & 8'h7f) | 8'h80;

            separate_bits = {k, tmp};
        end
    endfunction

    function [7:0] calc_ui(
            input [7:0] k,
            input [7:0] frac16
        );
        begin: _calc_ui
            reg [7:0] regime;               // 8 bits
            reg       reg_s;                // 1 bit
            reg [7:0] reg_len;              // 8 bits
            
            reg       bits_more;

            {regime, reg_s, reg_len} = calculate_regime(k);
            
            if (reg_len > 6) begin
                if (reg_s)  calc_ui = 8'h7f;
                else        calc_ui = 8'h01;
            end else begin
                frac16 = (frac16 & 16'h3fff) >> reg_len;
                calc_ui = regime + (frac16 >> 8);
                if ((frac16 & 8'h80) != 0) begin
                    bits_more = (frac16 & 8'h7f) != 0;
                    calc_ui = calc_ui + ((calc_ui & 1'b1) | bits_more);
                end
            end
        end
    endfunction

    function [(8+1+8)-1:0] calculate_regime(
            input [7:0] k
        );
        begin: _calculate_regime
            reg [7:0] regime;
            reg       reg_s; 
            reg [7:0] length;

            if (k & 8'h80) begin
            //  └── check if k is negative
                length = -k;
                regime = checked_shr(8'h40, length);
                reg_s = 1'b0;
            end else begin
                length = k + 1;
                regime = 8'h7f - checked_shr(8'h7f, length);
                reg_s = 1'b1;
            end
            calculate_regime = {regime, reg_s, length};
        end
    endfunction

    function [7:0] checked_shr(
            input [7:0] bits,
            input [7:0] rhs   
        );
        checked_shr = bits >> rhs;
    endfunction
    /*============= endfunctions ================*/

    reg sign_a, sign_b, sign_z;

`ifndef PROBE_SIGNALS
    reg [7:0]  ui_a, ui_b;
    reg [7:0]  k_a,    k_b;
    reg [7:0]  frac_a, frac_b;

    reg [7:0]  k_c;
    reg [15:0] frac16;

    reg        rcarry;
`endif


    // calc_ui regs
    reg [7:0] regime;               // 8 bits
    reg       reg_s;                // 1 bit
    reg [7:0] reg_len;              // 8 bits
    // end calc_ui regs

    reg [7:0] frac;
    reg       bits_more;
    
    reg [7:0] u_z;

    always @(*) begin

        if (a == 0 || b == 0 || a == 8'h80 || b == 8'h80) begin
            if (a == 0 || b == 0) begin
                z = 0;
            end else if (a == 8'h80  || b == 8'h80) begin
                z = 8'h80;
            end
            ui_a = 0;
            ui_b = 0;
            k_a = 0;
            k_b = 0;
            k_c = 0;
            sign_a = 0;
            sign_b = 0;
            sign_z = 0;
            frac_a = 0; 
            frac_b = 0;
            frac16 = 0;
            rcarry = 0;
            u_z = 0;
            
            reg_len = 0;
            regime = 0;
            reg_s = 0;

        end else begin
            sign_a = (a & 8'h80) >> 7;
            sign_b = (b & 8'h80) >> 7;
            sign_z = sign_a ^ sign_b;

            ui_a = sign_a == 0 ? a : c2(a);
            ui_b = sign_b == 0 ? b : c2(b);

            {k_a, frac_a} = separate_bits(ui_a);
            {k_b, frac_b} = separate_bits(ui_b);

            k_c = k_a + k_b;
            frac16 = frac_a * frac_b;
            rcarry = (frac16 & 16'h8000) != 0;

            if (rcarry) begin
                k_c = k_c + 1'b1;
                frac16 = frac16 >> 1;
            end else begin
                k_c = k_c;
                frac16 = frac16;
            end


            // calc_ui function            
            {regime, reg_s, reg_len} = calculate_regime(k_c);
            if (reg_len > 6) begin
                case (reg_s)
                    1'b1: u_z = 8'h7f;
                    1'b0: u_z = 8'h01;
                endcase
            end else begin
                frac16 = (frac16 & 16'h3fff) >> reg_len;
                u_z = regime + (frac16 >> 8);
                if ((frac16 & 8'h80) != 0) begin
                    bits_more = (frac16 & 8'h7f) != 0;
                    u_z = u_z + ((u_z & 1'b1) | bits_more);
                end
            end
            
            // u_z = calc_ui(k_c, frac16);

            z = sign_z == 0 ? u_z : c2(u_z);
        end
    end

    assign is_zero = z == 0   ? 1 : 0;
    assign is_nar  = z == 8'h80 ? 1 : 0;

endmodule

src/p8e0/tb_p8e0_mul.template.sv

// iverilog p8e0_mul.sv tb_p8e0_mul.sv && ./a.out

// synopsys translate_off                   // <- include guards for quartus (et al.) so that he ingores this
module tb_p8e0_mul;

    localparam ZERO = 'h0;
    localparam P8_NAR = 8'h80;
    /// localparam UNDEFINED = 'hz; // generic, no length specified.

    function diff(
            input [7:0] reference,
            input [7:0] expected
        );
        diff = reference === expected ? 0 : 1'bx;
    endfunction

    reg  [7:0]  a, b;
    wire [7:0]  ui_a, ui_b;
    
    reg  [100:0] a_ascii, b_ascii, z_ascii;

    wire [7:0]  z;
    wire        is_zero;
    wire        is_nar;

    wire [7:0]  k_a, k_b;
    wire [7:0]  frac_a, frac_b;
    wire [7:0]  k_c;
    wire [15:0] frac16;
    wire        rcarry;

    p8e0_mul p8e0_mul_inst(
        .a      (a),
        .b      (b),
`ifdef PROBE_SIGNALS
        .ui_a   (ui_a),
        .ui_b   (ui_b),
        .k_a    (k_a),
        .k_b    (k_b),
        .frac_a (frac_a),
        .frac_b (frac_b),
        .k_c    (k_c),
        .rcarry (rcarry),
        .frac16 (frac16),
`endif
        .is_zero(is_zero),
        .is_nar (is_nar),
        .z      (z)
    );

    reg [7:0] z_exp;
    reg diff_z;


// `ifdef PROBE_SIGNALS
    reg [7:0] ui_a_exp, ui_b_exp;
    reg [7:0] k_a_exp, k_b_exp, k_c_exp;
    
    reg rcarry_exp;

    reg [7:0] frac_a_exp, frac_b_exp;
    reg [15:0] frac16_exp;

    reg diff_ui_a, diff_ui_b,
        diff_k_a, diff_k_b, diff_k_c,
        diff_rcarry,
        diff_frac_a, diff_frac_b,
        diff_frac16;

    integer test_no;
        
// `endif

    always @(*) begin
        diff_z   = diff(z, z_exp);
`ifdef PROBE_SIGNALS
        diff_ui_a = diff(ui_a, ui_a_exp);
        diff_ui_b = diff(ui_b, ui_b_exp);
        diff_k_a = diff(k_a, k_a_exp);
        diff_k_b = diff(k_b, k_b_exp);
        diff_k_c = diff(k_c, k_c_exp);
        diff_rcarry = diff(rcarry, rcarry_exp);
        diff_frac_a = diff(frac_a, frac_a_exp);
        diff_frac_b = diff(frac_b, frac_b_exp);
        diff_frac16 = diff(frac16, frac16_exp);
`endif
    end

    initial begin
        $dumpfile("tb_p8e0_mul.vcd");
        $dumpvars(0, tb_p8e0_mul);
    end

    initial begin
                

    /*{add stuff here}*/


    end
endmodule
// synopsys translate_on

src/p8e0/tb_p8e0_mul.vcd
$date
	Thu Nov 18 15:17:06 2021
$end
$version
	Icarus Verilog
$end
$timescale
	1s
$end
$scope module tb_p8e0_mul $end
$var wire 8 ! z [7:0] $end
$var wire 8 " ui_b [7:0] $end
$var wire 8 # ui_a [7:0] $end
$var wire 1 $ rcarry $end
$var wire 8 % k_c [7:0] $end
$var wire 8 & k_b [7:0] $end
$var wire 8 ' k_a [7:0] $end
$var wire 1 ( is_zero $end
$var wire 1 ) is_nar $end
$var wire 8 * frac_b [7:0] $end
$var wire 8 + frac_a [7:0] $end
$var wire 16 , frac16 [15:0] $end
$var reg 8 - a [7:0] $end
$var reg 101 . a_ascii [100:0] $end
$var reg 8 / b [7:0] $end
$var reg 101 0 b_ascii [100:0] $end
$var reg 1 1 diff_frac16 $end
$var reg 1 2 diff_frac_a $end
$var reg 1 3 diff_frac_b $end
$var reg 1 4 diff_k_a $end
$var reg 1 5 diff_k_b $end
$var reg 1 6 diff_k_c $end
$var reg 1 7 diff_rcarry $end
$var reg 1 8 diff_ui_a $end
$var reg 1 9 diff_ui_b $end
$var reg 1 : diff_z $end
$var reg 16 ; frac16_exp [15:0] $end
$var reg 8 < frac_a_exp [7:0] $end
$var reg 8 = frac_b_exp [7:0] $end
$var reg 8 > k_a_exp [7:0] $end
$var reg 8 ? k_b_exp [7:0] $end
$var reg 8 @ k_c_exp [7:0] $end
$var reg 1 A rcarry_exp $end
$var reg 8 B ui_a_exp [7:0] $end
$var reg 8 C ui_b_exp [7:0] $end
$var reg 101 D z_ascii [100:0] $end
$var reg 8 E z_exp [7:0] $end
$var integer 32 F test_no [31:0] $end
$scope function diff $end
$var reg 8 G expected [7:0] $end
$var reg 8 H reference [7:0] $end
$upscope $end
$scope module p8e0_mul_inst $end
$var wire 8 I a [7:0] $end
$var wire 8 J b [7:0] $end
$var wire 1 ( is_zero $end
$var wire 1 ) is_nar $end
$var reg 1 K bits_more $end
$var reg 16 L frac16 [15:0] $end
$var reg 8 M frac_a [7:0] $end
$var reg 8 N frac_b [7:0] $end
$var reg 8 O k_a [7:0] $end
$var reg 8 P k_b [7:0] $end
$var reg 8 Q k_c [7:0] $end
$var reg 1 $ rcarry $end
$var reg 8 R reg_len [7:0] $end
$var reg 1 S reg_s $end
$var reg 8 T regime [7:0] $end
$var reg 1 U sign_a $end
$var reg 1 V sign_b $end
$var reg 1 W sign_z $end
$var reg 8 X u_z [7:0] $end
$var reg 8 Y ui_a [7:0] $end
$var reg 8 Z ui_b [7:0] $end
$var reg 8 [ z [7:0] $end
$scope function c2 $end
$var reg 8 \ a [7:0] $end
$upscope $end
$scope function calc_ui $end
$var reg 8 ] frac16 [7:0] $end
$var reg 8 ^ k [7:0] $end
$scope begin _calc_ui $end
$var reg 1 _ bits_more $end
$var reg 8 ` reg_len [7:0] $end
$var reg 1 a reg_s $end
$var reg 8 b regime [7:0] $end
$upscope $end
$upscope $end
$scope function calculate_regime $end
$var reg 8 c k [7:0] $end
$scope begin _calculate_regime $end
$var reg 8 d length [7:0] $end
$var reg 1 e reg_s $end
$var reg 8 f regime [7:0] $end
$upscope $end
$upscope $end
$scope function checked_shr $end
$var reg 8 g bits [7:0] $end
$var reg 8 h rhs [7:0] $end
$upscope $end
$scope function separate_bits $end
$var reg 8 i bits [7:0] $end
$scope begin _separate_bits $end
$var reg 8 j k [7:0] $end
$var reg 8 k reg_length [7:0] $end
$var reg 8 l tmp [7:0] $end
$upscope $end
$upscope $end
$upscope $end
$upscope $end
$enddefinitions $end
#0
$dumpvars
bx l
bx k
bx j
bx i
bx h
bx g
bx f
xe
bx d
bx c
bx b
xa
bx `
x_
bx ^
bx ]
bx \
b0 [
b0 Z
b0 Y
b0 X
0W
0V
0U
b0 T
0S
b0 R
b0 Q
b0 P
b0 O
b0 N
b0 M
b0 L
xK
b11 J
b0 I
b0 H
b0 G
b1 F
b0 E
b1100000010111000110000 D
b0 C
b0 B
0A
b0 @
b0 ?
b0 >
b0 =
b0 <
b0 ;
0:
09
08
07
06
05
04
03
02
01
b11000000101110001100000011010000110110001110000011011100110101 0
b11 /
b1100000010111000110000 .
b0 -
b0 ,
b0 +
b0 *
0)
1(
b0 '
b0 &
b0 %
0$
b0 #
b0 "
b0 !
$end
#10
0(
1)
b0 H
b0 G
b10000000 !
b10000000 [
b11011100110000101101110 D
b10000000 E
b101101001101000010111000110000 0
b11011100110000101101110 .
b10010000 /
b10010000 J
b10000000 -
b10000000 I
b10 F
#20
0)
b10000000 H
b10000000 G
b1010010 !
b1010010 [
0K
b1010010 X
b1000000 T
1S
b1 R
1e
b1000000 f
b1111111 g
b1 h
b1 d
b0 c
b1000110000000 ,
b1000110000000 L
b10 &
b10 P
b10010000 *
b10010000 N
b11111110 '
b11111110 O
b10110000 +
b10110000 M
b100 k
b10 j
b10010000 l
b1110001 i
b1110001 "
b1110001 Z
b10110 #
b10110 Y
b10001111 \
1V
1U
b1100010010111000110101001101100011001000110101 D
b1010010 E
b1000110000000 ;
b10010000 =
b10110000 <
b10 ?
b11111110 >
b1110001 C
b10110 B
b101101001101000010111000110101 0
b10110100110000001011100011001100110100001100110011011100110101 .
b10001111 /
b10001111 J
b11101010 -
b11101010 I
b11 F
#30
b0 H
b0 G
b11 !
b11 [
b11 X
b10 T
0S
b101 R
0e
b10 f
b1000000 g
b101 h
b101 d
b11111011 c
b100000000 ,
b100000000 L
b11111011 %
b11111011 Q
b11111110 &
b11111110 P
b10000000 *
b10000000 N
b11 k
b11111101 '
b11111101 O
b11000000 +
b11000000 M
b11111110 j
b10000000 l
b10000 i
b10000 "
b10000 Z
b1100 #
b1100 Y
b11110000 \
b11000000101110001100000011010000110110001110000011011100110101 D
b11 E
b100000000 ;
b10000000 =
b11000000 <
b11111011 @
b11111110 ?
b11111101 >
b10000 C
b1100 B
b10110100110000001011100011001000110101 0
b101101001100000010111000110001001110000011011100110101 .
b11110000 /
b11110000 J
b11110100 -
b11110100 I
b100 F
#40
b11111100 H
b11111100 G
b11110111 !
b11110111 [
1K
b1001 X
b1000 T
b11 R
b1000 f
b11 h
b11 d
b11111101 c
1$
b11111100 ,
b11111100 L
b11111101 %
b11111101 Q
b10111000 *
b10111000 N
b11111110 '
b11111110 O
b11001000 +
b11001000 M
b10111000 l
b10111 i
b10111 "
b10111 Z
b1001 \
b11001 #
b11001 Y
1W
0U
b1011010011000000101110001100010011010000110000001101100011001000110101 D
b11110111 E
1A
b11111100 ;
b10111000 =
b11001000 <
b11111101 @
b11111110 >
b10111 C
b11001 B
b1011010011000000101110001100110011010100111001001100110011011100110101 0
b11000000101110001100110011100100110000001101100011001000110101 .
b11101001 /
b11101001 J
b11001 -
b11001 I
b101 F
#50
b10010000 H
b10010000 G
b111 !
b111 [
b111 X
b100 T
b100 R
b100 f
b100 h
b100 d
b11111100 c
b1010010000 ,
b1010010000 L
b11111100 %
b11111100 Q
b11110000 *
b11110000 N
b11111101 '
b11111101 O
b11100000 +
b11100000 M
b11 k
b11111110 j
b11110000 l
b11110 i
b11110 "
b11110 Z
b1110 #
b1110 Y
0W
0V
b11000000101110001100010011000000111001001100110011011100110101 D
b111 E
b1010010000 ;
b11110000 =
b11100000 <
b11111100 @
b11111101 >
b11110 C
b1110 B
b110000001011100011010000110110001110000011011100110101 0
b110000001011100011001000110001001110000011011100110101 .
b11110 /
b11110 J
b1110 -
b1110 I
b110 F
#60
b10100000 H
b10100000 G
b1101100 !
b1101100 [
b1101100 X
b1100000 T
1S
b10 R
1e
b1100000 f
b1111111 g
b10 h
b10 d
b1 c
0$
b101110100000 ,
b101110100000 L
b1 %
b1 Q
b0 &
b0 P
b10001000 *
b10001000 N
b10 k
b1 '
b1 O
b11010000 +
b11010000 M
b0 j
b10001000 l
b1000010 i
b1000010 "
b1000010 Z
b1101010 #
b1101010 Y
b10111110 \
1V
1U
b1100110010111000110101 D
b1101100 E
0A
b101110100000 ;
b10001000 =
b11010000 <
b1 @
b0 ?
b1 >
b1000010 C
b1101010 B
b101101001100010010111000110000001101100011001000110101 0
b10110100110011001011100011001000110101 .
b10111110 /
b10111110 J
b10010110 -
b10010110 I
b111 F
#70
b10001000 H
b10001000 G
b101101 !
b101101 [
b101101 X
b100000 T
0S
b1 R
0e
b100000 f
b1000000 g
b1 h
b1 d
b11111111 c
1$
b110010001000 ,
b110010001000 L
b11111111 %
b11111111 Q
b11111111 &
b11111111 P
b11100100 *
b11100100 N
b11111111 '
b11111111 O
b11001000 +
b11001000 M
b11111111 j
b11100100 l
b111001 i
b111001 "
b111001 Z
b110010 #
b110010 Y
0V
0U
b11000000101110001101110011000000110011001100010011001000110101 D
b101101 E
1A
b110010001000 ;
b11100100 =
b11001000 <
b11111111 @
b11111111 ?
b11111111 >
b111001 C
b110010 B
b11000000101110001110000011100100110000001101100011001000110101 0
b110000001011100011011100111000001100010011001000110101 .
b111001 /
b111001 J
b110010 -
b110010 I
b1000 F
#80
b11000000 H
b11000000 G
b10111 !
b10111 [
b10111 X
b10000 T
b10 R
b10000 f
b10 h
b10 d
b11111110 c
b11011000000 ,
b11011000000 L
b11111110 %
b11111110 Q
b11111101 &
b11111101 P
b11010000 *
b11010000 N
b100 k
b0 '
b0 O
b11100000 +
b11100000 M
b11111101 j
b11010000 l
b1101 i
b1101 "
b1101 Z
b1011000 #
b1011000 Y
b11000000101110001100110011010100111001001100110011011100110101 D
b10111 E
b11011000000 ;
b11010000 =
b11100000 <
b11111110 @
b11111101 ?
b0 >
b1101 C
b1011000 B
b11000000101110001100100011000000110011001100010011001000110101 0
b110001001011100011011100110101 .
b1101 /
b1101 J
b1011000 -
b1011000 I
b1001 F
#90
b1110000 H
b1110000 G
b11111001 !
b11111001 [
b111 X
b100 T
b100 R
b100 f
b100 h
b100 d
b11111100 c
0$
b1101110000 ,
b1101110000 L
b11111100 %
b11111100 Q
b11111110 &
b11111110 P
b10001000 *
b10001000 N
b11111110 '
b11111110 O
b11 k
b11111110 j
b10001000 l
b10001 i
b10001 "
b10001 Z
b111 \
b11100 #
b11100 Y
1W
1V
b1011010011000000101110001100010011000000111001001100110011011100110101 D
b11111001 E
0A
b1101110000 ;
b10001000 =
b11111100 @
b11111110 ?
b11111110 >
b10001 C
b11100 B
b1011010011000000101110001100100011011000110101001101100011001000110101 0
b1100000010111000110100001100110011011100110101 .
b11101111 /
b11101111 J
b11100 -
b11100 I
b1010 F
#100
b1100000 H
b1100000 G
b10100001 !
b10100001 [
b1011111 X
b1000000 T
1S
b1 R
1e
b1000000 f
b1111111 g
b1 h
b1 d
b0 c
b1111101100000 ,
b1111101100000 L
b0 %
b0 Q
b11111111 &
b11111111 P
b10011100 *
b10011100 N
b10 k
b1 '
b1 O
b11010000 +
b11010000 M
b11111111 j
b10011100 l
b100111 i
b100111 "
b100111 Z
b1011111 \
b1101010 #
b1101010 Y
b10110100110001001011100011100100110110001110000011011100110101 D
b10100001 E
b1111101100000 ;
b10011100 =
b11010000 <
b0 @
b11111111 ?
b1 >
b100111 C
b1101010 B
b1011010011000000101110001101100011000000111001001100110011011100110101 0
b110011001011100011001000110101 .
b11011001 /
b11011001 J
b1101010 -
b1101010 I
b1011 F
#110
b1100000 H
b1100000 G
b1011 !
b1011 [
b1011 X
b1000 T
0S
b11 R
0e
b1000 f
b1000000 g
b11 h
b11 d
b11111101 c
1$
b1101100000 ,
b1101100000 L
b11111101 %
b11111101 Q
b11010000 *
b11010000 N
b11111101 '
b11111101 O
b11100000 +
b11100000 M
b10 k
b11111111 j
b11010000 l
b110100 i
b110100 "
b110100 Z
b1110 #
b1110 Y
b11001100 \
0W
1U
b11000000101110001100010011011100110001001110000011011100110101 D
b1011 E
1A
b1101100000 ;
b11010000 =
b11100000 <
b11111101 @
b11111101 >
b110100 C
b1110 B
b101101001100000010111000111000001100010011001000110101 0
b10110100110000001011100011001000110001001110000011011100110101 .
b11001100 /
b11001100 J
b11110010 -
b11110010 I
b1100 F
#120
b1111000 H
b1111000 G
b1110111 !
b1110111 [
b1110111 X
b1110000 T
1S
1e
b1110000 f
b1111111 g
b10 c
0$
b11101111000 ,
b11101111000 L
b10 %
b10 Q
b10 &
b10 P
b10010000 *
b10010000 N
b100 k
b0 '
b0 O
b11011100 +
b11011100 M
b10 j
b10010000 l
b1110001 i
b1110001 "
b1110001 Z
b1010111 #
b1010111 Y
0V
0U
b1101110010111000110101 D
b1110111 E
0A
b11101111000 ;
b10010000 =
b11011100 <
b10 @
b10 ?
b0 >
b1110001 C
b1010111 B
b1101000010111000110101 0
b110001001011100011011100110001001110000011011100110101 .
b1110001 /
b1110001 J
b1010111 -
b1010111 I
b1101 F
#130
b10100000 H
b10100000 G
b11110101 !
b11110101 [
b1011 X
b1000 T
0S
0e
b1000 f
b1000000 g
b11111101 c
b1010100000 ,
b1010100000 L
b11111101 %
b11111101 Q
b1 &
b1 P
b10001000 *
b10001000 N
b11111100 '
b11111100 O
b10100000 +
b10100000 M
b11 k
b1 j
b10001000 l
b1100001 i
b1100001 "
b1100001 Z
b101 #
b101 Y
b1011 \
1W
1U
b1011010011000000101110001100010011011100110001001110000011011100110101 D
b11110101 E
b1010100000 ;
b10001000 =
b10100000 <
b11111101 @
b1 ?
b11111100 >
b1100001 C
b101 B
b11001000101110001100010011001000110101 0
b1011010011000000101110001100000011011100111000001100010011001000110101 .
b1100001 /
b1100001 J
b11111011 -
b11111011 I
b1110 F
#140
b11000000 H
b11000000 G
b10001110 !
b10001110 [
b1110010 X
b1110000 T
1S
1e
b1110000 f
b1111111 g
b10 c
b111000000 ,
b111000000 L
b10 %
b10 Q
b0 &
b0 P
b10011100 *
b10011100 N
b10 '
b10 O
b10000000 +
b10000000 M
b10 k
b0 j
b10011100 l
b1000111 i
b1000111 "
b1000111 Z
b1110000 #
b1110000 Y
b1110010 \
b101101001101010010111000110000 D
b10001110 E
b111000000 ;
b10011100 =
b10000000 <
b10 @
b0 ?
b10 >
b1000111 C
b1110000 B
b110001001011100011001000110001001110000011011100110101 0
b101101001101000010111000110000 .
b1000111 /
b1000111 J
b10010000 -
b10010000 I
b1111 F
#150
b10000000 H
b10000000 G
b11111010 !
b11111010 [
0K
b110 X
b100 T
0S
b100 R
0e
b100 f
b1000000 g
b100 h
b100 d
b11111100 c
b110000000 ,
b110000000 L
b11111100 %
b11111100 Q
b10110000 *
b10110000 N
b11111100 '
b11111100 O
b10 k
b0 j
b10110000 l
b1001100 i
b1001100 "
b1001100 Z
b100 #
b100 Y
b110 \
b10110100110000001011100011000000111001001100110011011100110101 D
b11111010 E
b110000000 ;
b10110000 =
b11111100 @
b11111100 >
b1001100 C
b100 B
b11000100101110001100110011011100110101 0
b101101001100000010111000110000001101100011001000110101 .
b1001100 /
b1001100 J
b11111100 -
b11111100 I
b10000 F
#160
b10111000 H
b10111000 G
b1100 !
b1100 [
1K
b1100 X
b1000 T
b11 R
b1000 f
b11 h
b11 d
b11111101 c
b11111101 %
b11111101 Q
1$
b1110111000 ,
b1110111000 L
b11111110 &
b11111110 P
b11001000 *
b11001000 N
b11111110 '
b11111110 O
b11110000 +
b11110000 M
b11 k
b11111110 j
b11001000 l
b11001 i
b11001 "
b11001 Z
b11110 #
b11110 Y
b11100111 \
0W
1V
b1100000010111000110001001110000011011100110101 D
b1100 E
1A
b1110111000 ;
b11001000 =
b11110000 <
b11111101 @
b11111110 ?
b11111110 >
b11001 C
b11110 B
b1011010011000000101110001100110011100100110000001101100011001000110101 0
b10110100110000001011100011010000110110001110000011011100110101 .
b11100111 /
b11100111 J
b11100010 -
b11100010 I
b10001 F
#170
b10010000 H
b10010000 G
b10101111 !
b10101111 [
b1010001 X
b1000000 T
1S
b1 R
1e
b1000000 f
b1111111 g
b1 h
b1 d
b0 c
0$
b1000010010000 ,
b1000010010000 L
b0 %
b0 Q
b1 &
b1 P
b10101000 *
b10101000 N
b11111111 '
b11111111 O
b10010100 +
b10010100 M
b11 k
b1 j
b10101000 l
b1100101 i
b1100101 "
b1100101 Z
b1010001 \
b100101 #
b100101 Y
1W
0U
b10110100110001001011100011010100110011001100010011001000110101 D
b10101111 E
0A
b1000010010000 ;
b10101000 =
b10010100 <
b0 @
b1 ?
b11111111 >
b1100101 C
b100101 B
b1011010011001000101110001101100011001000110101 0
b11000000101110001101010011011100111000001100010011001000110101 .
b10011011 /
b10011011 J
b100101 -
b100101 I
b10010 F
#180
b11010000 H
b11010000 G
b10111001 !
b10111001 [
b1000111 X
1$
b11011010000 ,
b11011010000 L
b0 %
b0 Q
b0 &
b0 P
b10111000 *
b10111000 N
b11011000 +
b11011000 M
b10 k
b0 j
b10111000 l
b1001110 i
b1001110 "
b1001110 Z
b110110 #
b110110 Y
b1000111 \
0V
1U
b10110100110001001011100011001000110001001110000011011100110101 D
b10111001 E
1A
b11011010000 ;
b10111000 =
b11011000 <
b0 ?
b1001110 C
b110110 B
b1100010010111000110100001100110011011100110101 0
b10110100110000001011100011100000110100001100110011011100110101 .
b1001110 /
b1001110 J
b11001010 -
b11001010 I
b10011 F
#190
b1100000 H
b1100000 G
b10001101 !
b10001101 [
b1110011 X
b1110000 T
b11 R
b1110000 f
b11 h
b11 d
b10 c
b1101100000 ,
b1101100000 L
b10 %
b10 Q
b1 &
b1 P
b11010000 *
b11010000 N
b11 k
b1 j
b0 '
b0 O
b11100000 +
b11100000 M
b11010000 l
b1101010 i
b1101010 "
b1101010 Z
b1011000 #
b1011000 Y
b1110011 \
b101101001101010010111000110101 D
b10001101 E
b1101100000 ;
b11010000 =
b11100000 <
b10 @
b1 ?
b0 >
b1101010 C
b1011000 B
b110011001011100011001000110101 0
b10110100110001001011100011011100110101 .
b1101010 /
b1101010 J
b10101000 -
b10101000 I
b10100 F
#200
b10001100 H
b10001100 G
b1010101 !
b1010101 [
b1010101 X
b1000000 T
b1 R
b1000000 f
b1 h
b1 d
b0 c
b1010010001100 ,
b1010010001100 L
b0 %
b0 Q
b11111111 &
b11111111 P
b11100100 *
b11100100 N
b11101100 +
b11101100 M
b10 k
b11111111 j
b11100100 l
b111001 i
b111001 "
b111001 Z
b1011011 #
b1011011 Y
b11000111 \
0W
1V
b110001001011100011011000110101001101100011001000110101 D
b1010101 E
b1010010001100 ;
b11100100 =
b11101100 <
b0 @
b11111111 ?
b111001 C
b1011011 B
b1011010011000000101110001110000011100100110000001101100011001000110101 0
b10110100110001001011100011100000110100001100110011011100110101 .
b11000111 /
b11000111 J
b10100101 -
b10100101 I
b10101 F
#210
b1100000 H
b1100000 G
b11011110 !
b11011110 [
b100010 X
b100000 T
0S
0e
b100000 f
b1000000 g
b11111111 c
b1001100000 ,
b1001100000 L
b11111111 %
b11111111 Q
b11011100 *
b11011100 N
b11111111 '
b11111111 O
b10100000 +
b10100000 M
b11011100 l
b110111 i
b110111 "
b110111 Z
b101000 #
b101000 Y
b100010 \
1W
0V
b10110100110000001011100011010100110011001100010011001000110101 D
b11011110 E
b1001100000 ;
b11011100 =
b10100000 <
b11111111 @
b11111111 >
b110111 C
b101000 B
b11000000101110001110000011010100111001001100110011011100110101 0
b1011010011000000101110001101100011001000110101 .
b110111 /
b110111 J
b11011000 -
b11011000 I
b10110 F
#220
b1010100 H
b1010100 G
b10000111 !
b10000111 [
b1111001 X
b1111000 T
1S
b100 R
1e
b1111000 f
b1111111 g
b100 h
b100 d
b11 c
b101010100 ,
b101010100 L
b11 %
b11 Q
b0 &
b0 P
b11111000 *
b11111000 N
b10 '
b10 O
b10110000 +
b10110000 M
b10 k
b0 j
b11111000 l
b1011110 i
b1011110 "
b1011110 Z
b1110011 #
b1110011 Y
b1111001 \
b10110100110001001100000010111000110000 D
b10000111 E
b101010100 ;
b11111000 =
b10110000 <
b11 @
b0 ?
b10 >
b1011110 C
b1110011 B
b1100010010111000111001001100110011011100110101 0
b101101001101010010111000110101 .
b1011110 /
b1011110 J
b10001101 -
b10001101 I
b10111 F
#230
b10000100 H
b10000100 G
b1000010 !
b1000010 [
b1000010 X
b1000000 T
b1 R
b1000000 f
b1 h
b1 d
b0 c
b110000100 ,
b110000100 L
b0 %
b0 Q
b11011100 *
b11011100 N
b11111111 '
b11111111 O
b10011100 +
b10011100 M
b0 j
b11011100 l
b1010111 i
b1010111 "
b1010111 Z
b100111 #
b100111 Y
b10101001 \
0W
1V
b1100010010111000110000001101100011001000110101 D
b1000010 E
b110000100 ;
b11011100 =
b10011100 <
b0 @
b11111111 >
b1010111 C
b100111 B
b10110100110001001011100011011100110001001110000011011100110101 0
b1011010011000000101110001101100011000000111001001100110011011100110101 .
b10101001 /
b10101001 J
b11011001 -
b11011001 I
b11000 F
#240
b1010000 H
b1010000 G
b1111100 !
b1111100 [
b1111100 X
b1111100 T
b101 R
b1111100 f
b101 h
b101 d
b100 c
0$
b1010000 ,
b1010000 L
b100 %
b100 Q
b11111111 &
b11111111 P
b10010100 *
b10010100 N
b101 '
b101 O
b10000000 +
b10000000 M
b10 k
b11111111 j
b10010100 l
b100101 i
b100101 "
b100101 Z
b1111110 #
b1111110 Y
0V
0U
b110001001101100010111000110000 D
b1111100 E
0A
b1010000 ;
b10010100 =
b10000000 <
b100 @
b11111111 ?
b101 >
b100101 C
b1111110 B
b11000000101110001101010011011100111000001100010011001000110101 0
b110011001100100010111000110000 .
b100101 /
b100101 J
b1111110 -
b1111110 I
b11001 F
