src/p8e0/p8e0_mul.sv
/*
 *  Fri Nov 12 18:00:09 CET 2021
 *
 *  p8e0_mul
 *
 *  ===================================
 *  notes:
 *  Wed Nov 17 18:55:24 CET 2021
 *     - todo: fix inferred latches 
 *
 *
 *  ~/Documents/dev/yosys/yosys -p "synth_intel -family max10 -top p8e0_mul -vqm p8e0_mul.vqm" p8e0_mul.sv > yosys.out
 *  iverilog -D POST_IMPL -o verif_post -s p8e0_mul p8e0_mul.sv  $(yosys-config --datdir/intel/max10/cells_sim.v) && vvp -N verif_post
 */


module p8e0_mul(
        input      [7:0]    a,
        input      [7:0]    b,
`ifdef PROBE_SIGNALS
        output logic [7:0]    ui_a,   ui_b,
        output logic [7:0]    k_a,    k_b,
        output logic [7:0]    frac_a, frac_b,
        output logic [7:0]    k_c,
        output logic [15:0]   frac16,
        output logic          rcarry,
`endif
        output /* wire */           is_zero,
        output    wire     is_nar,
        output logic [7:0]    z
    );

    /*=============== functions ==================*/
    function [7:0] c2(input [7:0] a);
        c2 = ~a + 1'b1;
    endfunction

    function [15:0] separate_bits(
            input [7:0] bits
        );
        begin: _separate_bits
            logic [7:0] k;
            logic [7:0] tmp;
            logic [7:0] reg_length;
            logic first_regime_bit;

            first_regime_bit = (bits & 8'h40) >> 6 == 1;

            casex (bits)
                8'bx0000001: k = -6;
                8'bx000001x: k = -5;
                8'bx00001xx: k = -4;
                8'bx0001xxx: k = -3;
                8'bx001xxxx: k = -2;
                8'bx01xxxxx: k = -1;
                8'bx10xxxxx: k =  0;
                8'bx110xxxx: k =  1;
                8'bx1110xxx: k =  2;
                8'bx11110xx: k =  3;
                8'bx111110x: k =  4;
                8'bx1111110: k =  5;
                8'bx1111111: k =  6;
                default:     k =  8'hff; // never occurs
            endcase
            
            reg_length = 1 + 
                         (first_regime_bit == 1'b1 ? k + 1 : c2(k));

            if (reg_length == 8) reg_length = 7;                            // <---- is this line unnecessary?

            tmp = ((bits << reg_length) & 8'h7f) | 8'h80;

            separate_bits = {k, tmp};
        end
    endfunction

    /*
    function [7:0] calc_ui(
            input [7:0] k,
            input [7:0] frac16
        );
        begin: _calc_ui
            logic [7:0] regime;               // 8 bits
            logic       reg_s;                // 1 bit
            logic [7:0] reg_len;              // 8 bits
            
            logic       bits_more;

            {regime, reg_s, reg_len} = calculate_regime(k);
            
            if (reg_len > 6) begin
                if (reg_s)  calc_ui = 8'h7f;
                else        calc_ui = 8'h01;
            end else begin
                frac16 = (frac16 & 16'h3fff) >> reg_len;
                calc_ui = regime + (frac16 >> 8);
                if ((frac16 & 8'h80) != 0) begin
                    bits_more = (frac16 & 8'h7f) != 0;
                    calc_ui = calc_ui + ((calc_ui & 1'b1) | bits_more);
                end
            end
        end
    endfunction
    */

    function [(8+1+8)-1:0] calculate_regime(
            input [7:0] k
        );
        begin: _calculate_regime
            logic [7:0] regime;
            logic       reg_s; 
            logic [7:0] length;

            if (k & 8'h80) begin
            //  └── check if k is negative
                length = c2(k);
                regime = checked_shr(8'h40, length);
                reg_s = 1'b0;
            end else begin
                length = k + 1;
                regime = 8'h7f - checked_shr(8'h7f, length);
                reg_s = 1'b1;
            end
            calculate_regime = {regime, reg_s, length};
        end
    endfunction

    function [7:0] checked_shr(
            input [7:0] bits,
            input [7:0] rhs   
        );
        checked_shr = bits >> rhs;
    endfunction
    /*============= endfunctions ================*/

    logic sign_a, sign_b, sign_z;

`ifndef PROBE_SIGNALS
    logic [7:0]  ui_a, ui_b;
    logic [7:0]  k_a,    k_b;
    logic [7:0]  frac_a, frac_b;

    logic [7:0]  k_c;
    logic [15:0] frac16;

    logic        rcarry;
`endif


    // calc_ui regs
    logic [7:0] regime;               // 8 bits
    logic       reg_s;                // 1 bit
    logic [7:0] reg_len;              // 8 bits
    // end calc_ui regs

    logic [7:0] frac;
    logic       bits_more;
    
    logic [7:0] u_z;

    always_comb begin

      //////  z = 0; // always comb does not infer purely combinational logic? 

        if (a == 0 || b == 0 || a == 8'h80 || b == 8'h80) begin
            if (a == 0 || b == 0) begin
                z = 0;
            end else if (a == 8'h80  || b == 8'h80) begin
                z = 8'h80;
            end
            ui_a = 0;
            ui_b = 0;
            k_a = 0;
            k_b = 0;
            k_c = 0;
            sign_a = 0;
            sign_b = 0;
            sign_z = 0;
            frac_a = 0; 
            frac_b = 0;
            frac16 = 0;
            rcarry = 0;
            u_z = 0;
            
            reg_len = 0;
            regime = 0;
            reg_s = 0;

        end else begin
            sign_a = (a & 8'h80) >> 7;
            sign_b = (b & 8'h80) >> 7;
            sign_z = sign_a ^ sign_b;

            ui_a = sign_a == 0 ? a : c2(a);
            ui_b = sign_b == 0 ? b : c2(b);

            {k_a, frac_a} = separate_bits(ui_a);
            {k_b, frac_b} = separate_bits(ui_b);

            k_c = k_a + k_b;
            frac16 = frac_a * frac_b;
            rcarry = (frac16 & 16'h8000) != 0;

            if (rcarry) begin
                k_c = k_c + 1'b1;
                frac16 = frac16 >> 1;
            end else begin
                k_c = k_c;
                frac16 = frac16;
            end


            // calc_ui function            
            {regime, reg_s, reg_len} = calculate_regime(k_c);
            if (reg_len > 6) begin
                case (reg_s)
                    1'b1: u_z = 8'h7f;
                    1'b0: u_z = 8'h01;
                endcase
            end else begin
                frac16 = (frac16 & 16'h3fff) >> reg_len;
                u_z = regime + (frac16 >> 8);
                if ((frac16 & 8'h80) != 0) begin
                    u_z = u_z + ( (u_z & 1'b1) | ((frac16 & 8'h7f) != 0) );
                end
            end
            
            // u_z = calc_ui(k_c, frac16);

            z = sign_z == 0 ? u_z : c2(u_z);
        end
    end

    assign is_zero = z == 0   ? 1 : 0;
    assign is_nar  = z == 8'h80 ? 1 : 0;

endmodule

src/p8e0/tb_p8e0_mul.template.sv

// iverilog [-D PROBE_SIGNALS] p8e0_mul.sv tb_p8e0_mul.sv && ./a.out

// synopsys translate_off                   // <- include guards for quartus (et al.) so that he ingores this
module tb_p8e0_mul;

    localparam ZERO = 'h0;
    localparam P8_NAR = 8'h80;
    /// localparam UNDEFINED = 'hz; // generic, no length specified.

    function diff(
            input [7:0] reference,
            input [7:0] expected
        );
        diff = reference === expected ? 0 : 1'bx;
    endfunction

    reg  [7:0]  a, b;
    wire [7:0]  ui_a, ui_b;
    
    reg  [100:0] a_ascii, b_ascii, z_ascii;

    wire [7:0]  z;
    wire        is_zero;
    wire        is_nar;

    wire [7:0]  k_a, k_b;
    wire [7:0]  frac_a, frac_b;
    wire [7:0]  k_c;
    wire [15:0] frac16;
    wire        rcarry;

    p8e0_mul p8e0_mul_inst(
        .a      (a),
        .b      (b),
`ifdef PROBE_SIGNALS
        .ui_a   (ui_a),
        .ui_b   (ui_b),
        .k_a    (k_a),
        .k_b    (k_b),
        .frac_a (frac_a),
        .frac_b (frac_b),
        .k_c    (k_c),
        .rcarry (rcarry),
        .frac16 (frac16),
`endif
        .is_zero(is_zero),
        .is_nar (is_nar),
        .z      (z)
    );

    reg [7:0] z_exp;
    reg diff_z;


// `ifdef PROBE_SIGNALS
    reg [7:0] ui_a_exp, ui_b_exp;
    reg [7:0] k_a_exp, k_b_exp, k_c_exp;
    
    reg rcarry_exp;

    reg [7:0] frac_a_exp, frac_b_exp;
    reg [15:0] frac16_exp;

    reg diff_ui_a, diff_ui_b,
        diff_k_a, diff_k_b, diff_k_c,
        diff_rcarry,
        diff_frac_a, diff_frac_b,
        diff_frac16;

    integer test_no;
        
// `endif

    always @(*) begin
        diff_z   = diff(z, z_exp);
`ifdef PROBE_SIGNALS
        diff_ui_a = diff(ui_a, ui_a_exp);
        diff_ui_b = diff(ui_b, ui_b_exp);
        diff_k_a = diff(k_a, k_a_exp);
        diff_k_b = diff(k_b, k_b_exp);
        diff_k_c = diff(k_c, k_c_exp);
        diff_rcarry = diff(rcarry, rcarry_exp);
        diff_frac_a = diff(frac_a, frac_a_exp);
        diff_frac_b = diff(frac_b, frac_b_exp);
        diff_frac16 = diff(frac16, frac16_exp);
`endif
    end

    initial begin
`ifdef PROBE_SIGNALS
        $dumpfile("tb_p8e0_mul.vcd");
        $display("probe defined");
`else
        $dumpfile("tb_p8e0_mul_noprobe.vcd");
        $display("probe NOT defined");
`endif
        $dumpvars(0, tb_p8e0_mul);
    end

    initial begin
                

    /*{add stuff here}*/


    end
endmodule
// synopsys translate_on

src/p8e0/tb_p8e0_mul.vcd
$date
	Fri Nov 19 11:55:23 2021
$end
$version
	Icarus Verilog
$end
$timescale
	1s
$end
$scope module tb_p8e0_mul $end
$var wire 8 ! z [7:0] $end
$var wire 8 " ui_b [7:0] $end
$var wire 8 # ui_a [7:0] $end
$var wire 1 $ rcarry $end
$var wire 8 % k_c [7:0] $end
$var wire 8 & k_b [7:0] $end
$var wire 8 ' k_a [7:0] $end
$var wire 1 ( is_zero $end
$var wire 1 ) is_nar $end
$var wire 8 * frac_b [7:0] $end
$var wire 8 + frac_a [7:0] $end
$var wire 16 , frac16 [15:0] $end
$var reg 8 - a [7:0] $end
$var reg 101 . a_ascii [100:0] $end
$var reg 8 / b [7:0] $end
$var reg 101 0 b_ascii [100:0] $end
$var reg 1 1 diff_frac16 $end
$var reg 1 2 diff_frac_a $end
$var reg 1 3 diff_frac_b $end
$var reg 1 4 diff_k_a $end
$var reg 1 5 diff_k_b $end
$var reg 1 6 diff_k_c $end
$var reg 1 7 diff_rcarry $end
$var reg 1 8 diff_ui_a $end
$var reg 1 9 diff_ui_b $end
$var reg 1 : diff_z $end
$var reg 16 ; frac16_exp [15:0] $end
$var reg 8 < frac_a_exp [7:0] $end
$var reg 8 = frac_b_exp [7:0] $end
$var reg 8 > k_a_exp [7:0] $end
$var reg 8 ? k_b_exp [7:0] $end
$var reg 8 @ k_c_exp [7:0] $end
$var reg 1 A rcarry_exp $end
$var reg 8 B ui_a_exp [7:0] $end
$var reg 8 C ui_b_exp [7:0] $end
$var reg 101 D z_ascii [100:0] $end
$var reg 8 E z_exp [7:0] $end
$var integer 32 F test_no [31:0] $end
$scope function diff $end
$var reg 8 G expected [7:0] $end
$var reg 8 H reference [7:0] $end
$upscope $end
$scope module p8e0_mul_inst $end
$var wire 8 I a [7:0] $end
$var wire 8 J b [7:0] $end
$var wire 1 ( is_zero $end
$var wire 1 ) is_nar $end
$var reg 16 K frac16 [15:0] $end
$var reg 8 L frac_a [7:0] $end
$var reg 8 M frac_b [7:0] $end
$var reg 8 N k_a [7:0] $end
$var reg 8 O k_b [7:0] $end
$var reg 8 P k_c [7:0] $end
$var reg 1 $ rcarry $end
$var reg 8 Q reg_len [7:0] $end
$var reg 1 R reg_s $end
$var reg 8 S regime [7:0] $end
$var reg 1 T sign_a $end
$var reg 1 U sign_b $end
$var reg 1 V sign_z $end
$var reg 8 W u_z [7:0] $end
$var reg 8 X ui_a [7:0] $end
$var reg 8 Y ui_b [7:0] $end
$var reg 8 Z z [7:0] $end
$scope function c2 $end
$var reg 8 [ a [7:0] $end
$upscope $end
$scope function calculate_regime $end
$var reg 8 \ k [7:0] $end
$scope begin _calculate_regime $end
$var reg 8 ] length [7:0] $end
$var reg 1 ^ reg_s $end
$var reg 8 _ regime [7:0] $end
$upscope $end
$upscope $end
$scope function checked_shr $end
$var reg 8 ` bits [7:0] $end
$var reg 8 a rhs [7:0] $end
$upscope $end
$scope function separate_bits $end
$var reg 8 b bits [7:0] $end
$scope begin _separate_bits $end
$var reg 1 c first_regime_bit $end
$var reg 8 d k [7:0] $end
$var reg 8 e reg_length [7:0] $end
$var reg 8 f tmp [7:0] $end
$upscope $end
$upscope $end
$upscope $end
$upscope $end
$enddefinitions $end
#0
$dumpvars
bx f
bx e
bx d
xc
bx b
bx a
bx `
bx _
x^
bx ]
bx \
bx [
b0 Z
b0 Y
b0 X
b0 W
0V
0U
0T
b0 S
0R
b0 Q
b0 P
b0 O
b0 N
b0 M
b0 L
b0 K
b11 J
b0 I
b0 H
b0 G
b1 F
b0 E
b1100000010111000110000 D
b0 C
b0 B
0A
b0 @
b0 ?
b0 >
b0 =
b0 <
b0 ;
0:
09
08
07
06
05
04
03
02
01
b11000000101110001100000011010000110110001110000011011100110101 0
b11 /
b1100000010111000110000 .
b0 -
b0 ,
b0 +
b0 *
0)
1(
b0 '
b0 &
b0 %
0$
b0 #
b0 "
b0 !
$end
#10
0(
1)
b0 H
b0 G
b10000000 !
b10000000 Z
b11011100110000101101110 D
b10000000 E
b101101001101000010111000110000 0
b11011100110000101101110 .
b10010000 /
b10010000 J
b10000000 -
b10000000 I
b10 F
#20
0)
b1010000 H
b1010000 G
b110111 !
b110111 Z
b110111 W
b100000 S
b1 Q
0^
b100000 _
b1000000 `
b1 a
b1 ]
b11111111 \
1$
b1011101010000 ,
b1011101010000 K
b11111111 %
b11111111 P
b11111111 &
b11111111 O
b11101100 *
b11101100 M
b11111111 '
b11111111 N
b11110000 +
b11110000 L
b11101100 f
b10 e
b11111111 [
b11111111 d
0c
b111011 b
b111011 "
b111011 Y
b111100 #
b111100 X
b11000000101110001110000011010100111001001100110011011100110101 D
b110111 E
1A
b1011101010000 ;
b11101100 =
b11110000 <
b11111111 @
b11111111 ?
b11111111 >
b111011 C
b111100 B
b11000000101110001110010011001000110001001110000011011100110101 0
b1100000010111000111001001100110011011100110101 .
b111011 /
b111011 J
b111100 -
b111100 I
b11 F
#30
b10000 H
b10000 G
b1000111 !
b1000111 Z
b1000111 W
b1000000 S
1R
1^
b1000000 _
b1111111 `
b0 \
b0 %
b0 P
b11100010000 ,
b11100010000 K
b11111110 &
b11111110 O
b11001000 *
b11001000 M
b1 '
b1 N
b11001000 +
b11001000 L
b11001000 f
b11 e
b11111110 d
0c
b11001 b
b11001 "
b11001 Y
b1101001 #
b1101001 X
b11111110 [
1U
1T
b110001001011100011001000110001001110000011011100110101 D
b1000111 E
b11100010000 ;
b11001000 =
b11001000 <
b0 @
b11111110 ?
b1 >
b11001 C
b1101001 B
b1011010011000000101110001100110011100100110000001101100011001000110101 0
b1011010011001100101110001100010011001000110101 .
b11100111 /
b11100111 J
b10010111 -
b10010111 I
b100 F
#40
b1111100 H
b1111100 G
b10000111 !
b10000111 Z
b1111001 W
b1111000 S
b100 Q
b1111000 _
b100 a
b100 ]
b11 \
b101111100 ,
b101111100 K
b11 %
b11 P
b0 &
b0 O
b11011000 *
b11011000 M
b10 '
b10 N
b11010000 +
b11010000 L
b11011000 f
b10 e
b0 d
1c
b1010110 b
b1010110 "
b1010110 Y
b1110101 #
b1110101 X
b1111001 [
1V
0U
b10110100110001001100000010111000110000 D
b10000111 E
b101111100 ;
b11011000 =
b11010000 <
b11 @
b0 ?
b10 >
b1010110 C
b1110101 B
b1100010010111000110110001110000011011100110101 0
b101101001101100010111000110101 .
b1010110 /
b1010110 J
b10001011 -
b10001011 I
b101 F
#50
b10010000 H
b10010000 G
b11001100 !
b11001100 Z
b110100 W
b100000 S
0R
b1 Q
0^
b100000 _
b1000000 `
b1 a
b1 ]
b11111111 \
0$
b1001110010000 ,
b1001110010000 K
b11111111 %
b11111111 P
b11001000 *
b11001000 M
b11111111 '
b11111111 N
b10000100 +
b10000100 L
b11001000 f
b0 d
1c
b1010010 b
b1010010 "
b1010010 Y
b110100 [
b100001 #
b100001 X
1U
0T
b101101001100000010111000111000001100010011001000110101 D
b11001100 E
0A
b1001110010000 ;
b11001000 =
b10000100 <
b11111111 @
b11111111 >
b1010010 C
b100001 B
b101101001100010010111000110101001101100011001000110101 0
b11000000101110001101010011000100110101001101100011001000110101 .
b10101110 /
b10101110 J
b100001 -
b100001 I
b110 F
#60
b10100000 H
b10100000 G
b11010101 !
b11010101 Z
b101011 W
1$
b101010100000 ,
b101010100000 K
b11111111 %
b11111111 P
b11111110 &
b11111110 O
b10110000 *
b10110000 M
b11 e
b11111110 d
0c
b0 '
b0 N
b11111000 +
b11111000 L
b10110000 f
b10110 b
b10110 "
b10110 Y
b101011 [
b1011110 #
b1011110 X
b1011010011000000101110001101100011011100110001001110000011011100110101 D
b11010101 E
1A
b101010100000 ;
b10110000 =
b11111000 <
b11111110 ?
b0 >
b10110 C
b1011110 B
b10110100110000001011100011001100110100001100110011011100110101 0
b1100010010111000111001001100110011011100110101 .
b11101010 /
b11101010 J
b1011110 -
b1011110 I
b111 F
#70
b10001000 H
b10001000 G
b111 !
b111 Z
b111 W
b100 S
b100 Q
b100 _
b100 a
b100 ]
b11111100 \
0$
b1010001000 ,
b1010001000 K
b11111100 %
b11111100 P
b10011000 *
b10011000 M
b10011000 f
b10011 b
b11111110 '
b11111110 N
b10110000 +
b10110000 L
b10011 "
b10011 Y
b10110 #
b10110 X
b11111100 [
0V
1T
b11000000101110001100010011000000111001001100110011011100110101 D
b111 E
0A
b1010001000 ;
b10011000 =
b10110000 <
b11111100 @
b11111110 >
b10011 C
b10110 B
b1011010011000000101110001100100011100100110110001110000011011100110101 0
b10110100110000001011100011001100110100001100110011011100110101 .
b11101101 /
b11101101 J
b11101010 -
b11101010 I
b1000 F
#80
b1000000 H
b1000000 G
b11101101 !
b11101101 Z
b10011 W
b10000 S
b10 Q
b10000 _
b10 a
b10 ]
b11111110 \
1$
b1101000000 ,
b1101000000 K
b11111110 %
b11111110 P
b11111100 &
b11111100 O
b11100000 *
b11100000 M
b101 e
b1 '
b1 N
b11100000 f
b11111100 d
0c
b111 b
b111 "
b111 Y
b1100110 #
b1100110 X
b10011 [
1V
0U
b1011010011000000101110001100100011100100110110001110000011011100110101 D
b11101101 E
1A
b1101000000 ;
b11100000 =
b11111110 @
b11111100 ?
b1 >
b111 C
b1100110 B
b11000000101110001100010011000000111001001100110011011100110101 0
b10110100110010001011100011011100110101 .
b111 /
b111 J
b10011010 -
b10011010 I
b1001 F
#90
b10010000 H
b10010000 G
b10001100 !
b10001100 Z
b1110100 W
b1110000 S
1R
b11 Q
1^
b1110000 _
b1111111 `
b11 a
b11 ]
b10 \
0$
b1110010000 ,
b1110010000 K
b10 %
b10 P
b11111111 &
b11111111 O
b10010100 *
b10010100 M
b10 e
b11 '
b11 N
b10100000 +
b10100000 L
b10010100 f
b11111111 d
0c
b100101 b
b100101 "
b100101 Y
b1110100 [
b1111001 #
b1111001 X
1U
0T
b101101001101100010111000110000 D
b10001100 E
0A
b1110010000 ;
b10010100 =
b10100000 <
b10 @
b11111111 ?
b11 >
b100101 C
b1111001 B
b1011010011000000101110001101010011011100111000001100010011001000110101 0
b110001001100000010111000110000 .
b11011011 /
b11011011 J
b1111001 -
b1111001 I
b1010 F
#100
b10000000 H
b10000000 G
b10011100 !
b10011100 Z
b1100100 W
b1100000 S
b10 Q
b1100000 _
b10 a
b10 ]
b1 \
b1110000000 ,
b1110000000 K
b1 %
b1 P
b0 &
b0 O
b10011100 *
b10011100 M
b1 '
b1 N
b10000000 +
b10000000 L
b10011100 f
b10 e
b0 d
1c
b1000111 b
b1000111 "
b1000111 Y
b1100000 #
b1100000 X
b1100100 [
0U
1T
b101101001100100010111000110101 D
b10011100 E
b1110000000 ;
b10011100 =
b10000000 <
b1 @
b0 ?
b1 >
b1000111 C
b1100000 B
b110001001011100011001000110001001110000011011100110101 0
b101101001100100010111000110000 .
b1000111 /
b1000111 J
b10100000 -
b10100000 I
b1011 F
#110
b10011000 H
b10011000 G
b1111001 !
b1111001 Z
b1111001 W
b1111000 S
b100 Q
b1111000 _
b100 a
b100 ]
b11 \
1$
b10011000 ,
b10011000 K
b11 %
b11 P
b1 &
b1 O
b10101000 *
b10101000 M
b11100000 +
b11100000 L
b10101000 f
b11 e
b1 d
b1100101 b
b1100101 "
b1100101 Y
b1101100 #
b1101100 X
b10011011 [
0V
1U
b110001001100000010111000110000 D
b1111001 E
1A
b10011000 ;
b10101000 =
b11100000 <
b11 @
b1 ?
b1100101 C
b1101100 B
b1011010011001000101110001101100011001000110101 0
b101101001100110010111000110101 .
b10011011 /
b10011011 J
b10010100 -
b10010100 I
b1100 F
#120
b10000000 H
b10000000 G
b11100110 !
b11100110 Z
b11010 W
b10000 S
0R
b10 Q
0^
b10000 _
b1000000 `
b10 a
b10 ]
b11111110 \
0$
b101010000000 ,
b101010000000 K
b11111110 %
b11111110 P
b0 &
b0 O
b11010100 *
b11010100 M
b10 e
b11111110 '
b11111110 N
b10000000 +
b10000000 L
b11010100 f
b0 d
1c
b1010101 b
b1010101 "
b1010101 Y
b11010 [
b10000 #
b10000 X
1V
0T
b10110100110000001011100011010000110000001101100011001000110101 D
b11100110 E
0A
b101010000000 ;
b11010100 =
b10000000 <
b11111110 @
b0 ?
b11111110 >
b1010101 C
b10000 B
b10110100110001001011100011011000110101001101100011001000110101 0
b110000001011100011001000110101 .
b10101011 /
b10101011 J
b10000 -
b10000 I
b1101 F
#130
b110000 H
b110000 G
b1101110 !
b1101110 Z
b1101110 W
b1100000 S
1R
1^
b1100000 _
b1111111 `
b1 \
b111000110000 ,
b111000110000 K
b1 %
b1 P
b10111000 *
b10111000 M
b1 '
b1 N
b10101000 +
b10101000 L
b10111000 f
b10 e
b0 d
b1001110 b
b1001110 "
b1001110 Y
b1100101 #
b1100101 X
b10110010 [
0V
1T
b110011001011100011011100110101 D
b1101110 E
b111000110000 ;
b10111000 =
b10101000 <
b1 @
b1 >
b1001110 C
b1100101 B
b101101001100010010111000110100001100110011011100110101 0
b1011010011001000101110001101100011001000110101 .
b10110010 /
b10110010 J
b10011011 -
b10011011 I
b1110 F
#140
b11101100 H
b11101100 G
b10 !
b10 Z
b10 W
b1 S
0R
b110 Q
0^
b1 _
b1000000 `
b110 a
b110 ]
b11111010 \
b11101100 ,
b11101100 K
b11111010 %
b11111010 P
b11111111 &
b11111111 O
b10100100 *
b10100100 M
b11111011 '
b11111011 N
b11000000 +
b11000000 L
b10100100 f
b10 e
b11111010 [
b11111111 d
0c
b101001 b
b101001 "
b101001 Y
b11 #
b11 X
0U
0T
b110000001011100011000000110011001100010011001000110101 D
b10 E
b11101100 ;
b10100100 =
b11000000 <
b11111010 @
b11111111 ?
b11111011 >
b101001 C
b11 B
b11000000101110001101100011010000110000001101100011001000110101 0
b11000000101110001100000011010000110110001110000011011100110101 .
b101001 /
b101001 J
b11 -
b11 I
b1111 F
#150
b11100000 H
b11100000 G
b101 !
b101 Z
b101 W
b100 S
b100 Q
b100 _
b100 a
b100 ]
b11111100 \
1$
b11100000 ,
b11100000 K
b11111100 %
b11111100 P
b11111101 &
b11111101 O
b11010000 *
b11010000 M
b11111110 '
b11111110 N
b11010000 f
b100 e
b11111101 d
b1101 b
b1101 "
b1101 Y
b11000 #
b11000 X
b11111100 [
1U
1T
b11000000101110001100000011011100111000001100010011001000110101 D
b101 E
1A
b11100000 ;
b11010000 =
b11111100 @
b11111101 ?
b11111110 >
b1101 C
b11000 B
b1011010011000000101110001100100011000000110011001100010011001000110101 0
b1011010011000000101110001100110011011100110101 .
b11110011 /
b11110011 J
b11101000 -
b11101000 I
b10000 F
#160
b10100000 H
b10100000 G
b11000 !
b11000 Z
b11000 W
b10000 S
b10 Q
b10000 _
b10 a
b10 ]
b11111110 \
0$
b11110100000 ,
b11110100000 K
b11111110 %
b11111110 P
b11111111 &
b11111111 O
b10010000 *
b10010000 M
b11111111 '
b11111111 N
b10101000 +
b10101000 L
b10010000 f
b10 e
b11111111 d
b100100 b
b100100 "
b100100 Y
b101010 #
b101010 X
b11111110 [
b11000000101110001100110011011100110101 D
b11000 E
0A
b11110100000 ;
b10010000 =
b10101000 <
b11111110 @
b11111111 ?
b11111111 >
b100100 C
b101010 B
b101101001100000010111000110101001101100011001000110101 0
b10110100110000001011100011011000110101001101100011001000110101 .
b11011100 /
b11011100 J
b11010110 -
b11010110 I
b10001 F
#170
b1100000 H
b1100000 G
b1111010 !
b1111010 Z
b1111010 W
b1111000 S
1R
b100 Q
1^
b1111000 _
b1111111 `
b100 a
b100 ]
b11 \
b1001100000 ,
b1001100000 K
b11 %
b11 P
b0 &
b0 O
b11001100 *
b11001100 M
b11 '
b11 N
b10000000 +
b10000000 L
b11001100 f
b10 e
b0 d
1c
b1010011 b
b1010011 "
b1010011 Y
b1111000 #
b1111000 X
0U
0T
b110001001100100010111000110000 D
b1111010 E
b1001100000 ;
b11001100 =
b10000000 <
b11 @
b0 ?
b11 >
b1010011 C
b1111000 B
b110001001011100011010100111001001100110011011100110101 0
b1110000010111000110000 .
b1010011 /
b1010011 J
b1111000 -
b1111000 I
b10010 F
#180
b11100000 H
b11100000 G
b10001001 !
b10001001 Z
b1110111 W
b1110000 S
b11 Q
b1110000 _
b11 a
b11 ]
b10 \
b11011100000 ,
b11011100000 K
b10 %
b10 P
b10 &
b10 O
b11100000 *
b11100000 M
b100 e
b10 d
b0 '
b0 N
b10001000 +
b10001000 L
b11100000 f
b1110110 b
b1110110 "
b1110110 Y
b1110111 [
b1000010 #
b1000010 X
1V
1U
b101101001101110010111000110101 D
b10001001 E
b11011100000 ;
b11100000 =
b10001000 <
b10 @
b10 ?
b0 >
b1110110 C
b1000010 B
b101101001101110010111000110000 0
b1100010010111000110000001101100011001000110101 .
b10001010 /
b10001010 J
b1000010 -
b1000010 I
b10011 F
#190
b10000000 H
b10000000 G
b10000 !
b10000 Z
b10000 W
b10000 S
0R
b10 Q
0^
b10000 _
b1000000 `
b10 a
b10 ]
b11111110 \
1$
b10000000 ,
b10000000 K
b11111110 %
b11111110 P
b11111011 &
b11111011 O
b11000000 *
b11000000 M
b110 e
b11111011 d
0c
b10 '
b10 N
b10110000 +
b10110000 L
b11000000 f
b11 b
b11 "
b11 Y
b1110011 #
b1110011 X
b11111110 [
0V
1T
b110000001011100011001000110101 D
b10000 E
1A
b10000000 ;
b11000000 =
b10110000 <
b11111110 @
b11111011 ?
b10 >
b11 C
b1110011 B
b1011010011000000101110001100000011010000110110001110000011011100110101 0
b101101001101010010111000110101 .
b11111101 /
b11111101 J
b10001101 -
b10001101 I
b10100 F
#200
b10101000 H
b10101000 G
b10010100 !
b10010100 Z
b1101100 W
b1100000 S
1R
1^
b1100000 _
b1111111 `
b1 \
b101110101000 ,
b101110101000 K
b1 %
b1 P
b1 &
b1 O
b11110000 *
b11110000 M
1c
b11111111 '
b11111111 N
b11101100 +
b11101100 L
b11110000 f
b11 e
b1 d
b1101110 b
b1101110 "
b1101110 Y
b1101100 [
b111011 #
b111011 X
1V
0T
b101101001100110010111000110101 D
b10010100 E
b101110101000 ;
b11110000 =
b11101100 <
b1 @
b1 ?
b11111111 >
b1101110 C
b111011 B
b10110100110011001011100011011100110101 0
b11000000101110001110010011001000110001001110000011011100110101 .
b10010010 /
b10010010 J
b111011 -
b111011 I
b10101 F
#210
b10111100 H
b10111100 G
b10011000 !
b10011000 Z
b1101000 W
b11110111100 ,
b11110111100 K
b1 %
b1 P
b11111000 *
b11111000 M
b11000100 +
b11000100 L
b11111000 f
b11 e
b1 d
1c
b1101111 b
b1101111 "
b1101111 Y
b1101000 [
b110001 #
b110001 X
b101101001100110010111000110000 D
b10011000 E
b11110111100 ;
b11111000 =
b11000100 <
b1101111 C
b110001 B
b1011010011001100101110001110000011011100110101 0
b11000000101110001101110011011000110101001101100011001000110101 .
b10010001 /
b10010001 J
b110001 -
b110001 I
b10110 F
#220
b1010000 H
b1010000 G
b11011111 !
b11011111 Z
b100001 W
b100000 S
0R
b1 Q
0^
b100000 _
b1000000 `
b1 a
b1 ]
b11111111 \
b101010000 ,
b101010000 K
b11111111 %
b11111111 P
b11111110 &
b11111110 O
b11010000 *
b11010000 M
0c
b0 '
b0 N
b10100100 +
b10100100 L
b11010000 f
b11 e
b11111110 d
b11010 b
b11010 "
b11010 Y
b1001001 #
b1001001 X
b100001 [
0U
1T
b1011010011000000101110001101010011000100110101001101100011001000110101 D
b11011111 E
b101010000 ;
b11010000 =
b10100100 <
b11111111 @
b11111110 ?
b0 >
b11010 C
b1001001 B
b110000001011100011010000110000001101100011001000110101 0
b10110100110001001011100011001000111000001100010011001000110101 .
b11010 /
b11010 J
b10110111 -
b10110111 I
b10111 F
#230
b1010000 H
b1010000 G
b10110 !
b10110 Z
b10110 W
b10000 S
b10 Q
b10000 _
b10 a
b10 ]
b11111110 \
0$
b11001010000 ,
b11001010000 K
b11111110 %
b11111110 P
b0 &
b0 O
b10101000 *
b10101000 M
b10 e
b0 d
1c
b11111110 '
b11111110 N
b10001000 +
b10001000 L
b10101000 f
b1001010 b
b1001010 "
b1001010 Y
b10001 #
b10001 X
b11111110 [
0V
1U
b110000001011100011001100110100001100110011011100110101 D
b10110 E
0A
b11001010000 ;
b10101000 =
b10001000 <
b11111110 @
b0 ?
b11111110 >
b1001010 C
b10001 B
b101101001100010010111000110011001100010011001000110101 0
b1011010011000000101110001100100011011000110101001101100011001000110101 .
b10110110 /
b10110110 J
b11101111 -
b11101111 I
b11000 F
#240
b111100 H
b111100 G
b1111010 !
b1111010 Z
b1111010 W
b1111000 S
1R
b100 Q
1^
b1111000 _
b1111111 `
b100 a
b100 ]
b11 \
1$
b1000111100 ,
b1000111100 K
b11 %
b11 P
b11100100 *
b11100100 M
b10 '
b10 N
b11100000 +
b11100000 L
b11100100 f
b10 e
b0 d
b1011001 b
b1011001 "
b1011001 Y
b1110110 #
b1110110 X
b10100111 [
b110001001100100010111000110000 D
b1111010 E
1A
b1000111100 ;
b11100100 =
b11100000 <
b11 @
b10 >
b1011001 C
b1110110 B
b10110100110001001011100011011100111000001100010011001000110101 0
b101101001101110010111000110000 .
b10100111 /
b10100111 J
b10001010 -
b10001010 I
b11001 F
